Workbook

Sheet Trésorerie
D2: 44561 | E2: 2022 | Q2: 44926 | R2: 2023 | AD2: 2024
C3: Solde de Trésorerie (CC+CM+Caisse) : | D3: =207964.31+100711.45+1229.06 -> 309904.82 | E3: =D3+E43+E71 -> 200930.88 | F3: =E3+F43+F71 -> 249307.44 | G3: =F3+G43+G71 -> 297762.78 | H3: =G3+H43+H71 -> 227618.05 | I3: =H3+I43+I71 -> 271818 | J3: =I3+J43+J71 -> 296726.8 | K3: =J3+K43+K71 -> 220757.38 | L3: =K3+L43+L71 -> 104408.7 | M3: =L3+M43+M71+90000 -> 97952.77 | N3: =M3+N43+N71 -> 299366.99 | O3: =N3+O43+O71 -> 331662.62 | P3: =O3+P43+P71 -> 203888.9 | Q3: =109619.71+92951.16+1380.7 -> 203951.57 | R3: =Q3+R43+R71+40000 -> 79651.43 | S3: =R3+S43+S71+95006.53 -> 82184.66 | T3: =S3+T43+T71 -> 366194.25 | U3: =T3+U43+U71 -> 383255.87 | V3: =U3+V43+V71 -> 355386.51 | W3: =V3+W43+W71 -> 405582.13 | X3: =W3+X43+X71 -> 452749.75 | Y3: =X3+Y43+Y71 -> 320465.3 | Z3: =Y3+Z43+Z71 -> 518238.26 | AA3: =Z3+AA43+AA71 -> 522684.11 | ... AC3: =AB3+AC43+AC71 -> 259616.29 | AD3: =AC3+R72 -> 95316.15 | AE3: =AD3+S72 -> 2842.85 | AF3: =AE3+T72 -> 286852.44 | AG3: =AF3+U72 -> 303914.06
E4: 1 | F4: 2 | G4: 3 | H4: 4 | I4: 5 | J4: 6 | K4: 7 | L4: 8 | M4: 9 | N4: 10 | O4: 11 | P4: 12 | R4: 1 | S4: 2 | T4: 3 | U4: 4 | V4: 5 | W4: 6 | X4: 7 | Y4: 8 | Z4: 9 | AA4: 10 | AB4: 11 | AC4: 12 | AD4: 1 | AE4: 2 | AF4: 3 | AG4: 4
A5: =SUM(E5:P5) -> 553708.3 | B5: 468740 | C5: VILLE A RECEVOIR | D5: Entrée | E5: =-SUMIFS('2022'!$M:$M,'2022'!$E:$E,Trésorerie!E$4,'2022'!$F:$F,Trésorerie!$B5)+SUMIFS('2022'!$N:$N,'2022'!$E:$E,Trésorerie!E$4,'2022'!$F:$F,Trésorerie!$B5) -> 0 | F5: =-SUMIFS('2022'!$M:$M,'2022'!$E:$E,Trésorerie!F$4,'2022'!$F:$F,Trésorerie!$B5)+SUMIFS('2022'!$N:$N,'2022'!$E:$E,Trésorerie!F$4,'2022'!$F:$F,Trésorerie!$B5) -> 172245.3 | G5: =-SUMIFS('2022'!$M:$M,'2022'!$E:$E,Trésorerie!G$4,'2022'!$F:$F,Trésorerie!$B5)+SUMIFS('2022'!$N:$N,'2022'!$E:$E,Trésorerie!G$4,'2022'!$F:$F,Trésorerie!$B5) -> 123296 | H5: =-SUMIFS('2022'!$M:$M,'2022'!$E:$E,Trésorerie!H$4,'2022'!$F:$F,Trésorerie!$B5)+SUMIFS('2022'!$N:$N,'2022'!$E:$E,Trésorerie!H$4,'2022'!$F:$F,Trésorerie!$B5) -> 17000 | I5: =-SUMIFS('2022'!$M:$M,'2022'!$E:$E,Trésorerie!I$4,'2022'!$F:$F,Trésorerie!$B5)+SUMIFS('2022'!$N:$N,'2022'!$E:$E,Trésorerie!I$4,'2022'!$F:$F,Trésorerie!$B5) -> 0 | J5: =-SUMIFS('2022'!$M:$M,'2022'!$E:$E,Trésorerie!J$4,'2022'!$F:$F,Trésorerie!$B5)+SUMIFS('2022'!$N:$N,'2022'!$E:$E,Trésorerie!J$4,'2022'!$F:$F,Trésorerie!$B5) -> 11099.8 | K5: =-SUMIFS('2022'!$M:$M,'2022'!$E:$E,Trésorerie!K$4,'2022'!$F:$F,Trésorerie!$B5)+SUMIFS('2022'!$N:$N,'2022'!$E:$E,Trésorerie!K$4,'2022'!$F:$F,Trésorerie!$B5) -> 1200 | L5: =-SUMIFS('2022'!$M:$M,'2022'!$E:$E,Trésorerie!L$4,'2022'!$F:$F,Trésorerie!$B5)+SUMIFS('2022'!$N:$N,'2022'!$E:$E,Trésorerie!L$4,'2022'!$F:$F,Trésorerie!$B5) -> 169.2 | ... P5: =-SUMIFS('2022'!$M:$M,'2022'!$E:$E,Trésorerie!P$4,'2022'!$F:$F,Trésorerie!$B5)+SUMIFS('2022'!$N:$N,'2022'!$E:$E,Trésorerie!P$4,'2022'!$F:$F,Trésorerie!$B5) -> 344 | R5: =-SUMIFS('2023-01'!$M:$M,'2023-01'!$E:$E,Trésorerie!R$4,'2023-01'!$F:$F,Trésorerie!$B5)+SUMIFS('2023-01'!$N:$N,'2023-01'!$E:$E,Trésorerie!R$4,'2023-01'!$F:$F,Trésorerie!$B5) -> 430 | S5: =-SUMIFS('2023-02'!$M:$M,'2023-02'!$E:$E,Trésorerie!S$4,'2023-02'!$F:$F,Trésorerie!$B5)+SUMIFS('2023-02'!$N:$N,'2023-02'!$E:$E,Trésorerie!S$4,'2023-02'!$F:$F,Trésorerie!$B5) -> 0 | T5: =-SUMIFS('2023-03'!$M:$M,'2023-03'!$E:$E,Trésorerie!T$4,'2023-03'!$F:$F,Trésorerie!$B5)+SUMIFS('2023-03'!$N:$N,'2023-03'!$E:$E,Trésorerie!T$4,'2023-03'!$F:$F,Trésorerie!$B5) -> 176370 | U5: =-SUMIFS('2023-04'!$M:$M,'2023-04'!$E:$E,Trésorerie!U$4,'2023-04'!$F:$F,Trésorerie!$B5)+SUMIFS('2023-04'!$N:$N,'2023-04'!$E:$E,Trésorerie!U$4,'2023-04'!$F:$F,Trésorerie!$B5) -> 88447.5 | V5: =-SUMIFS('2023-05'!$M:$M,'2023-05'!$E:$E,Trésorerie!V$4,'2023-05'!$F:$F,Trésorerie!$B5)+SUMIFS('2023-05'!$N:$N,'2023-05'!$E:$E,Trésorerie!V$4,'2023-05'!$F:$F,Trésorerie!$B5) -> 473 | W5: =-SUMIFS('2023-06'!$M:$M,'2023-06'!$E:$E,Trésorerie!W$4,'2023-06'!$F:$F,Trésorerie!$B5)+SUMIFS('2023-06'!$N:$N,'2023-06'!$E:$E,Trésorerie!W$4,'2023-06'!$F:$F,Trésorerie!$B5) -> 0 | X5: =-SUMIFS('2023-07'!$M:$M,'2023-07'!$E:$E,Trésorerie!X$4,'2023-07'!$F:$F,Trésorerie!$B5)+SUMIFS('2023-07'!$N:$N,'2023-07'!$E:$E,Trésorerie!X$4,'2023-07'!$F:$F,Trésorerie!$B5) -> 54000 | Y5: =-SUMIFS('2023-08'!$M:$M,'2023-08'!$E:$E,Trésorerie!Y$4,'2023-08'!$F:$F,Trésorerie!$B5)+SUMIFS('2023-08'!$N:$N,'2023-08'!$E:$E,Trésorerie!Y$4,'2023-08'!$F:$F,Trésorerie!$B5) -> 6774 | Z5: =-SUMIFS('2023-09'!$M:$M,'2023-09'!$E:$E,Trésorerie!Z$4,'2023-09'!$F:$F,Trésorerie!$B5)+SUMIFS('2023-09'!$N:$N,'2023-09'!$E:$E,Trésorerie!Z$4,'2023-09'!$F:$F,Trésorerie!$B5) -> 161766.5 | AA5: =-SUMIFS('2023-10'!$M:$M,'2023-10'!$E:$E,Trésorerie!AA$4,'2023-10'!$F:$F,Trésorerie!$B5)+SUMIFS('2023-10'!$N:$N,'2023-10'!$E:$E,Trésorerie!AA$4,'2023-10'!$F:$F,Trésorerie!$B5) -> 5200 | AB5: =IF(SUM($E5:O5)>SUM($R5:AA5),SUM($E5:O5)-SUM($R5:AA5),0) -> 59903.3 | AC5: =IF(SUM($E5:P5)>SUM($R5:AB5),SUM($E5:P5)-SUM($R5:AB5),0) -> 344
A6: =SUM(E6:P6) -> 173624.12 | B6: 445020 | C6: CAF PS BABILHOME | D6: Entrée | E6: =-SUMIFS('2022'!$M:$M,'2022'!$E:$E,Trésorerie!E$4,'2022'!$F:$F,Trésorerie!$B6)+SUMIFS('2022'!$N:$N,'2022'!$E:$E,Trésorerie!E$4,'2022'!$F:$F,Trésorerie!$B6) -> 0 | F6: =-SUMIFS('2022'!$M:$M,'2022'!$E:$E,Trésorerie!F$4,'2022'!$F:$F,Trésorerie!$B6)+SUMIFS('2022'!$N:$N,'2022'!$E:$E,Trésorerie!F$4,'2022'!$F:$F,Trésorerie!$B6) -> 0 | G6: =-SUMIFS('2022'!$M:$M,'2022'!$E:$E,Trésorerie!G$4,'2022'!$F:$F,Trésorerie!$B6)+SUMIFS('2022'!$N:$N,'2022'!$E:$E,Trésorerie!G$4,'2022'!$F:$F,Trésorerie!$B6) -> 0 | H6: =-SUMIFS('2022'!$M:$M,'2022'!$E:$E,Trésorerie!H$4,'2022'!$F:$F,Trésorerie!$B6)+SUMIFS('2022'!$N:$N,'2022'!$E:$E,Trésorerie!H$4,'2022'!$F:$F,Trésorerie!$B6) -> 18666 | I6: =-SUMIFS('2022'!$M:$M,'2022'!$E:$E,Trésorerie!I$4,'2022'!$F:$F,Trésorerie!$B6)+SUMIFS('2022'!$N:$N,'2022'!$E:$E,Trésorerie!I$4,'2022'!$F:$F,Trésorerie!$B6) -> 52278.63 | J6: =-SUMIFS('2022'!$M:$M,'2022'!$E:$E,Trésorerie!J$4,'2022'!$F:$F,Trésorerie!$B6)+SUMIFS('2022'!$N:$N,'2022'!$E:$E,Trésorerie!J$4,'2022'!$F:$F,Trésorerie!$B6) -> 47050.76 | K6: =-SUMIFS('2022'!$M:$M,'2022'!$E:$E,Trésorerie!K$4,'2022'!$F:$F,Trésorerie!$B6)+SUMIFS('2022'!$N:$N,'2022'!$E:$E,Trésorerie!K$4,'2022'!$F:$F,Trésorerie!$B6) -> 23987.2 | L6: =-SUMIFS('2022'!$M:$M,'2022'!$E:$E,Trésorerie!L$4,'2022'!$F:$F,Trésorerie!$B6)+SUMIFS('2022'!$N:$N,'2022'!$E:$E,Trésorerie!L$4,'2022'!$F:$F,Trésorerie!$B6) -> 0 | ... P6: =-SUMIFS('2022'!$M:$M,'2022'!$E:$E,Trésorerie!P$4,'2022'!$F:$F,Trésorerie!$B6)+SUMIFS('2022'!$N:$N,'2022'!$E:$E,Trésorerie!P$4,'2022'!$F:$F,Trésorerie!$B6) -> 0 | R6: =-SUMIFS('2023-01'!$M:$M,'2023-01'!$E:$E,Trésorerie!R$4,'2023-01'!$F:$F,Trésorerie!$B6)+SUMIFS('2023-01'!$N:$N,'2023-01'!$E:$E,Trésorerie!R$4,'2023-01'!$F:$F,Trésorerie!$B6) -> 0 | S6: =-SUMIFS('2023-02'!$M:$M,'2023-02'!$E:$E,Trésorerie!S$4,'2023-02'!$F:$F,Trésorerie!$B6)+SUMIFS('2023-02'!$N:$N,'2023-02'!$E:$E,Trésorerie!S$4,'2023-02'!$F:$F,Trésorerie!$B6) -> 0 | T6: =-SUMIFS('2023-03'!$M:$M,'2023-03'!$E:$E,Trésorerie!T$4,'2023-03'!$F:$F,Trésorerie!$B6)+SUMIFS('2023-03'!$N:$N,'2023-03'!$E:$E,Trésorerie!T$4,'2023-03'!$F:$F,Trésorerie!$B6) -> 79819.26 | U6: =-SUMIFS('2023-04'!$M:$M,'2023-04'!$E:$E,Trésorerie!U$4,'2023-04'!$F:$F,Trésorerie!$B6)+SUMIFS('2023-04'!$N:$N,'2023-04'!$E:$E,Trésorerie!U$4,'2023-04'!$F:$F,Trésorerie!$B6) -> 0 | V6: =-SUMIFS('2023-05'!$M:$M,'2023-05'!$E:$E,Trésorerie!V$4,'2023-05'!$F:$F,Trésorerie!$B6)+SUMIFS('2023-05'!$N:$N,'2023-05'!$E:$E,Trésorerie!V$4,'2023-05'!$F:$F,Trésorerie!$B6) -> 0 | W6: =-SUMIFS('2023-06'!$M:$M,'2023-06'!$E:$E,Trésorerie!W$4,'2023-06'!$F:$F,Trésorerie!$B6)+SUMIFS('2023-06'!$N:$N,'2023-06'!$E:$E,Trésorerie!W$4,'2023-06'!$F:$F,Trésorerie!$B6) -> 47728.19 | X6: =-SUMIFS('2023-07'!$M:$M,'2023-07'!$E:$E,Trésorerie!X$4,'2023-07'!$F:$F,Trésorerie!$B6)+SUMIFS('2023-07'!$N:$N,'2023-07'!$E:$E,Trésorerie!X$4,'2023-07'!$F:$F,Trésorerie!$B6) -> 0 | Y6: =-SUMIFS('2023-08'!$M:$M,'2023-08'!$E:$E,Trésorerie!Y$4,'2023-08'!$F:$F,Trésorerie!$B6)+SUMIFS('2023-08'!$N:$N,'2023-08'!$E:$E,Trésorerie!Y$4,'2023-08'!$F:$F,Trésorerie!$B6) -> 0 | Z6: =-SUMIFS('2023-09'!$M:$M,'2023-09'!$E:$E,Trésorerie!Z$4,'2023-09'!$F:$F,Trésorerie!$B6)+SUMIFS('2023-09'!$N:$N,'2023-09'!$E:$E,Trésorerie!Z$4,'2023-09'!$F:$F,Trésorerie!$B6) -> 45258.77 | AA6: =-SUMIFS('2023-10'!$M:$M,'2023-10'!$E:$E,Trésorerie!AA$4,'2023-10'!$F:$F,Trésorerie!$B6)+SUMIFS('2023-10'!$N:$N,'2023-10'!$E:$E,Trésorerie!AA$4,'2023-10'!$F:$F,Trésorerie!$B6) -> 0 | AB6: =IF(SUM($E6:O6)>SUM($R6:AA6),SUM($E6:O6)-SUM($R6:AA6),0) -> 817.9 | AC6: =IF(SUM($E6:P6)>SUM($R6:AB6),SUM($E6:P6)-SUM($R6:AB6),0) -> 0
A7: =SUM(E7:P7) -> 162124.29 | B7: 445030 | C7: CAF PS GRIBOUILLE | D7: Entrée | E7: =-SUMIFS('2022'!$M:$M,'2022'!$E:$E,Trésorerie!E$4,'2022'!$F:$F,Trésorerie!$B7)+SUMIFS('2022'!$N:$N,'2022'!$E:$E,Trésorerie!E$4,'2022'!$F:$F,Trésorerie!$B7) -> 0 | F7: =-SUMIFS('2022'!$M:$M,'2022'!$E:$E,Trésorerie!F$4,'2022'!$F:$F,Trésorerie!$B7)+SUMIFS('2022'!$N:$N,'2022'!$E:$E,Trésorerie!F$4,'2022'!$F:$F,Trésorerie!$B7) -> 0 | G7: =-SUMIFS('2022'!$M:$M,'2022'!$E:$E,Trésorerie!G$4,'2022'!$F:$F,Trésorerie!$B7)+SUMIFS('2022'!$N:$N,'2022'!$E:$E,Trésorerie!G$4,'2022'!$F:$F,Trésorerie!$B7) -> 0 | H7: =-SUMIFS('2022'!$M:$M,'2022'!$E:$E,Trésorerie!H$4,'2022'!$F:$F,Trésorerie!$B7)+SUMIFS('2022'!$N:$N,'2022'!$E:$E,Trésorerie!H$4,'2022'!$F:$F,Trésorerie!$B7) -> 0 | I7: =-SUMIFS('2022'!$M:$M,'2022'!$E:$E,Trésorerie!I$4,'2022'!$F:$F,Trésorerie!$B7)+SUMIFS('2022'!$N:$N,'2022'!$E:$E,Trésorerie!I$4,'2022'!$F:$F,Trésorerie!$B7) -> 35683.97 | J7: =-SUMIFS('2022'!$M:$M,'2022'!$E:$E,Trésorerie!J$4,'2022'!$F:$F,Trésorerie!$B7)+SUMIFS('2022'!$N:$N,'2022'!$E:$E,Trésorerie!J$4,'2022'!$F:$F,Trésorerie!$B7) -> 37199.36 | K7: =-SUMIFS('2022'!$M:$M,'2022'!$E:$E,Trésorerie!K$4,'2022'!$F:$F,Trésorerie!$B7)+SUMIFS('2022'!$N:$N,'2022'!$E:$E,Trésorerie!K$4,'2022'!$F:$F,Trésorerie!$B7) -> 53774.63 | L7: =-SUMIFS('2022'!$M:$M,'2022'!$E:$E,Trésorerie!L$4,'2022'!$F:$F,Trésorerie!$B7)+SUMIFS('2022'!$N:$N,'2022'!$E:$E,Trésorerie!L$4,'2022'!$F:$F,Trésorerie!$B7) -> 0 | ... P7: =-SUMIFS('2022'!$M:$M,'2022'!$E:$E,Trésorerie!P$4,'2022'!$F:$F,Trésorerie!$B7)+SUMIFS('2022'!$N:$N,'2022'!$E:$E,Trésorerie!P$4,'2022'!$F:$F,Trésorerie!$B7) -> 0 | R7: =-SUMIFS('2023-01'!$M:$M,'2023-01'!$E:$E,Trésorerie!R$4,'2023-01'!$F:$F,Trésorerie!$B7)+SUMIFS('2023-01'!$N:$N,'2023-01'!$E:$E,Trésorerie!R$4,'2023-01'!$F:$F,Trésorerie!$B7) -> 0 | S7: =-SUMIFS('2023-02'!$M:$M,'2023-02'!$E:$E,Trésorerie!S$4,'2023-02'!$F:$F,Trésorerie!$B7)+SUMIFS('2023-02'!$N:$N,'2023-02'!$E:$E,Trésorerie!S$4,'2023-02'!$F:$F,Trésorerie!$B7) -> 0 | T7: =-SUMIFS('2023-03'!$M:$M,'2023-03'!$E:$E,Trésorerie!T$4,'2023-03'!$F:$F,Trésorerie!$B7)+SUMIFS('2023-03'!$N:$N,'2023-03'!$E:$E,Trésorerie!T$4,'2023-03'!$F:$F,Trésorerie!$B7) -> 66666.06 | U7: =-SUMIFS('2023-04'!$M:$M,'2023-04'!$E:$E,Trésorerie!U$4,'2023-04'!$F:$F,Trésorerie!$B7)+SUMIFS('2023-04'!$N:$N,'2023-04'!$E:$E,Trésorerie!U$4,'2023-04'!$F:$F,Trésorerie!$B7) -> 0 | V7: =-SUMIFS('2023-05'!$M:$M,'2023-05'!$E:$E,Trésorerie!V$4,'2023-05'!$F:$F,Trésorerie!$B7)+SUMIFS('2023-05'!$N:$N,'2023-05'!$E:$E,Trésorerie!V$4,'2023-05'!$F:$F,Trésorerie!$B7) -> 0 | W7: =-SUMIFS('2023-06'!$M:$M,'2023-06'!$E:$E,Trésorerie!W$4,'2023-06'!$F:$F,Trésorerie!$B7)+SUMIFS('2023-06'!$N:$N,'2023-06'!$E:$E,Trésorerie!W$4,'2023-06'!$F:$F,Trésorerie!$B7) -> 0 | X7: =-SUMIFS('2023-07'!$M:$M,'2023-07'!$E:$E,Trésorerie!X$4,'2023-07'!$F:$F,Trésorerie!$B7)+SUMIFS('2023-07'!$N:$N,'2023-07'!$E:$E,Trésorerie!X$4,'2023-07'!$F:$F,Trésorerie!$B7) -> 0 | Y7: =-SUMIFS('2023-08'!$M:$M,'2023-08'!$E:$E,Trésorerie!Y$4,'2023-08'!$F:$F,Trésorerie!$B7)+SUMIFS('2023-08'!$N:$N,'2023-08'!$E:$E,Trésorerie!Y$4,'2023-08'!$F:$F,Trésorerie!$B7) -> 0 | Z7: =-SUMIFS('2023-09'!$M:$M,'2023-09'!$E:$E,Trésorerie!Z$4,'2023-09'!$F:$F,Trésorerie!$B7)+SUMIFS('2023-09'!$N:$N,'2023-09'!$E:$E,Trésorerie!Z$4,'2023-09'!$F:$F,Trésorerie!$B7) -> 31089.94 | AA7: =-SUMIFS('2023-10'!$M:$M,'2023-10'!$E:$E,Trésorerie!AA$4,'2023-10'!$F:$F,Trésorerie!$B7)+SUMIFS('2023-10'!$N:$N,'2023-10'!$E:$E,Trésorerie!AA$4,'2023-10'!$F:$F,Trésorerie!$B7) -> 0 | AB7: =IF(SUM($E7:O7)>SUM($R7:AA7),SUM($E7:O7)-SUM($R7:AA7),0) -> 64368.29 | AC7: =IF(SUM($E7:P7)>SUM($R7:AB7),SUM($E7:P7)-SUM($R7:AB7),0) -> 0
A8: =SUM(E8:P8) -> 141360.8 | B8: 445050 | C8: CAF PS PILOTAGE ANIMATION GLOBALE | D8: Entrée | E8: =-SUMIFS('2022'!$M:$M,'2022'!$E:$E,Trésorerie!E$4,'2022'!$F:$F,Trésorerie!$B8)+SUMIFS('2022'!$N:$N,'2022'!$E:$E,Trésorerie!E$4,'2022'!$F:$F,Trésorerie!$B8) -> 0 | F8: =-SUMIFS('2022'!$M:$M,'2022'!$E:$E,Trésorerie!F$4,'2022'!$F:$F,Trésorerie!$B8)+SUMIFS('2022'!$N:$N,'2022'!$E:$E,Trésorerie!F$4,'2022'!$F:$F,Trésorerie!$B8) -> 0 | G8: =-SUMIFS('2022'!$M:$M,'2022'!$E:$E,Trésorerie!G$4,'2022'!$F:$F,Trésorerie!$B8)+SUMIFS('2022'!$N:$N,'2022'!$E:$E,Trésorerie!G$4,'2022'!$F:$F,Trésorerie!$B8) -> 31853.22 | H8: =-SUMIFS('2022'!$M:$M,'2022'!$E:$E,Trésorerie!H$4,'2022'!$F:$F,Trésorerie!$B8)+SUMIFS('2022'!$N:$N,'2022'!$E:$E,Trésorerie!H$4,'2022'!$F:$F,Trésorerie!$B8) -> 0 | I8: =-SUMIFS('2022'!$M:$M,'2022'!$E:$E,Trésorerie!I$4,'2022'!$F:$F,Trésorerie!$B8)+SUMIFS('2022'!$N:$N,'2022'!$E:$E,Trésorerie!I$4,'2022'!$F:$F,Trésorerie!$B8) -> 45801.06 | J8: =-SUMIFS('2022'!$M:$M,'2022'!$E:$E,Trésorerie!J$4,'2022'!$F:$F,Trésorerie!$B8)+SUMIFS('2022'!$N:$N,'2022'!$E:$E,Trésorerie!J$4,'2022'!$F:$F,Trésorerie!$B8) -> 0 | K8: =-SUMIFS('2022'!$M:$M,'2022'!$E:$E,Trésorerie!K$4,'2022'!$F:$F,Trésorerie!$B8)+SUMIFS('2022'!$N:$N,'2022'!$E:$E,Trésorerie!K$4,'2022'!$F:$F,Trésorerie!$B8) -> 0 | L8: =-SUMIFS('2022'!$M:$M,'2022'!$E:$E,Trésorerie!L$4,'2022'!$F:$F,Trésorerie!$B8)+SUMIFS('2022'!$N:$N,'2022'!$E:$E,Trésorerie!L$4,'2022'!$F:$F,Trésorerie!$B8) -> 0 | ... P8: =-SUMIFS('2022'!$M:$M,'2022'!$E:$E,Trésorerie!P$4,'2022'!$F:$F,Trésorerie!$B8)+SUMIFS('2022'!$N:$N,'2022'!$E:$E,Trésorerie!P$4,'2022'!$F:$F,Trésorerie!$B8) -> 0 | R8: =-SUMIFS('2023-01'!$M:$M,'2023-01'!$E:$E,Trésorerie!R$4,'2023-01'!$F:$F,Trésorerie!$B8)+SUMIFS('2023-01'!$N:$N,'2023-01'!$E:$E,Trésorerie!R$4,'2023-01'!$F:$F,Trésorerie!$B8) -> 0 | S8: =-SUMIFS('2023-02'!$M:$M,'2023-02'!$E:$E,Trésorerie!S$4,'2023-02'!$F:$F,Trésorerie!$B8)+SUMIFS('2023-02'!$N:$N,'2023-02'!$E:$E,Trésorerie!S$4,'2023-02'!$F:$F,Trésorerie!$B8) -> 0 | T8: =-SUMIFS('2023-03'!$M:$M,'2023-03'!$E:$E,Trésorerie!T$4,'2023-03'!$F:$F,Trésorerie!$B8)+SUMIFS('2023-03'!$N:$N,'2023-03'!$E:$E,Trésorerie!T$4,'2023-03'!$F:$F,Trésorerie!$B8) -> 31853.22 | U8: =-SUMIFS('2023-04'!$M:$M,'2023-04'!$E:$E,Trésorerie!U$4,'2023-04'!$F:$F,Trésorerie!$B8)+SUMIFS('2023-04'!$N:$N,'2023-04'!$E:$E,Trésorerie!U$4,'2023-04'!$F:$F,Trésorerie!$B8) -> 31853.26 | V8: =-SUMIFS('2023-05'!$M:$M,'2023-05'!$E:$E,Trésorerie!V$4,'2023-05'!$F:$F,Trésorerie!$B8)+SUMIFS('2023-05'!$N:$N,'2023-05'!$E:$E,Trésorerie!V$4,'2023-05'!$F:$F,Trésorerie!$B8) -> 0 | W8: =-SUMIFS('2023-06'!$M:$M,'2023-06'!$E:$E,Trésorerie!W$4,'2023-06'!$F:$F,Trésorerie!$B8)+SUMIFS('2023-06'!$N:$N,'2023-06'!$E:$E,Trésorerie!W$4,'2023-06'!$F:$F,Trésorerie!$B8) -> 13380.12 | X8: =-SUMIFS('2023-07'!$M:$M,'2023-07'!$E:$E,Trésorerie!X$4,'2023-07'!$F:$F,Trésorerie!$B8)+SUMIFS('2023-07'!$N:$N,'2023-07'!$E:$E,Trésorerie!X$4,'2023-07'!$F:$F,Trésorerie!$B8) -> 31853.26 | Y8: =-SUMIFS('2023-08'!$M:$M,'2023-08'!$E:$E,Trésorerie!Y$4,'2023-08'!$F:$F,Trésorerie!$B8)+SUMIFS('2023-08'!$N:$N,'2023-08'!$E:$E,Trésorerie!Y$4,'2023-08'!$F:$F,Trésorerie!$B8) -> 0 | Z8: =-SUMIFS('2023-09'!$M:$M,'2023-09'!$E:$E,Trésorerie!Z$4,'2023-09'!$F:$F,Trésorerie!$B8)+SUMIFS('2023-09'!$N:$N,'2023-09'!$E:$E,Trésorerie!Z$4,'2023-09'!$F:$F,Trésorerie!$B8) -> 0 | AA8: =-SUMIFS('2023-10'!$M:$M,'2023-10'!$E:$E,Trésorerie!AA$4,'2023-10'!$F:$F,Trésorerie!$B8)+SUMIFS('2023-10'!$N:$N,'2023-10'!$E:$E,Trésorerie!AA$4,'2023-10'!$F:$F,Trésorerie!$B8) -> 31853.26 | AB8: =IF(SUM($E8:O8)>SUM($R8:AA8),SUM($E8:O8)-SUM($R8:AA8),0) -> 567.68 | AC8: =IF(SUM($E8:P8)>SUM($R8:AB8),SUM($E8:P8)-SUM($R8:AB8),0) -> 0
A9: =SUM(E9:P9) -> 108029.15 | B9: 511000 | C9: CH DIFFERES | D9: Entrée | E9: =-SUMIFS('2022'!$M:$M,'2022'!$E:$E,Trésorerie!E$4,'2022'!$F:$F,Trésorerie!$B9)+SUMIFS('2022'!$N:$N,'2022'!$E:$E,Trésorerie!E$4,'2022'!$F:$F,Trésorerie!$B9) -> 7551.88 | F9: =-SUMIFS('2022'!$M:$M,'2022'!$E:$E,Trésorerie!F$4,'2022'!$F:$F,Trésorerie!$B9)+SUMIFS('2022'!$N:$N,'2022'!$E:$E,Trésorerie!F$4,'2022'!$F:$F,Trésorerie!$B9) -> 13099.93 | G9: =-SUMIFS('2022'!$M:$M,'2022'!$E:$E,Trésorerie!G$4,'2022'!$F:$F,Trésorerie!$B9)+SUMIFS('2022'!$N:$N,'2022'!$E:$E,Trésorerie!G$4,'2022'!$F:$F,Trésorerie!$B9) -> 8928.19 | H9: =-SUMIFS('2022'!$M:$M,'2022'!$E:$E,Trésorerie!H$4,'2022'!$F:$F,Trésorerie!$B9)+SUMIFS('2022'!$N:$N,'2022'!$E:$E,Trésorerie!H$4,'2022'!$F:$F,Trésorerie!$B9) -> 7922.26 | I9: =-SUMIFS('2022'!$M:$M,'2022'!$E:$E,Trésorerie!I$4,'2022'!$F:$F,Trésorerie!$B9)+SUMIFS('2022'!$N:$N,'2022'!$E:$E,Trésorerie!I$4,'2022'!$F:$F,Trésorerie!$B9) -> 4306.24 | J9: =-SUMIFS('2022'!$M:$M,'2022'!$E:$E,Trésorerie!J$4,'2022'!$F:$F,Trésorerie!$B9)+SUMIFS('2022'!$N:$N,'2022'!$E:$E,Trésorerie!J$4,'2022'!$F:$F,Trésorerie!$B9) -> 13962.97 | K9: =-SUMIFS('2022'!$M:$M,'2022'!$E:$E,Trésorerie!K$4,'2022'!$F:$F,Trésorerie!$B9)+SUMIFS('2022'!$N:$N,'2022'!$E:$E,Trésorerie!K$4,'2022'!$F:$F,Trésorerie!$B9) -> 0 | L9: =-SUMIFS('2022'!$M:$M,'2022'!$E:$E,Trésorerie!L$4,'2022'!$F:$F,Trésorerie!$B9)+SUMIFS('2022'!$N:$N,'2022'!$E:$E,Trésorerie!L$4,'2022'!$F:$F,Trésorerie!$B9) -> 7478.7 | ... P9: =-SUMIFS('2022'!$M:$M,'2022'!$E:$E,Trésorerie!P$4,'2022'!$F:$F,Trésorerie!$B9)+SUMIFS('2022'!$N:$N,'2022'!$E:$E,Trésorerie!P$4,'2022'!$F:$F,Trésorerie!$B9) -> 7695.54 | R9: =-SUMIFS('2023-01'!$M:$M,'2023-01'!$E:$E,Trésorerie!R$4,'2023-01'!$F:$F,Trésorerie!$B9)+SUMIFS('2023-01'!$N:$N,'2023-01'!$E:$E,Trésorerie!R$4,'2023-01'!$F:$F,Trésorerie!$B9) -> 10472.39 | S9: =-SUMIFS('2023-02'!$M:$M,'2023-02'!$E:$E,Trésorerie!S$4,'2023-02'!$F:$F,Trésorerie!$B9)+SUMIFS('2023-02'!$N:$N,'2023-02'!$E:$E,Trésorerie!S$4,'2023-02'!$F:$F,Trésorerie!$B9) -> 16536.94 | T9: =-SUMIFS('2023-03'!$M:$M,'2023-03'!$E:$E,Trésorerie!T$4,'2023-03'!$F:$F,Trésorerie!$B9)+SUMIFS('2023-03'!$N:$N,'2023-03'!$E:$E,Trésorerie!T$4,'2023-03'!$F:$F,Trésorerie!$B9) -> 7603.93 | U9: =-SUMIFS('2023-04'!$M:$M,'2023-04'!$E:$E,Trésorerie!U$4,'2023-04'!$F:$F,Trésorerie!$B9)+SUMIFS('2023-04'!$N:$N,'2023-04'!$E:$E,Trésorerie!U$4,'2023-04'!$F:$F,Trésorerie!$B9) -> 10499.49 | V9: =-SUMIFS('2023-05'!$M:$M,'2023-05'!$E:$E,Trésorerie!V$4,'2023-05'!$F:$F,Trésorerie!$B9)+SUMIFS('2023-05'!$N:$N,'2023-05'!$E:$E,Trésorerie!V$4,'2023-05'!$F:$F,Trésorerie!$B9) -> 4135.27 | W9: =-SUMIFS('2023-06'!$M:$M,'2023-06'!$E:$E,Trésorerie!W$4,'2023-06'!$F:$F,Trésorerie!$B9)+SUMIFS('2023-06'!$N:$N,'2023-06'!$E:$E,Trésorerie!W$4,'2023-06'!$F:$F,Trésorerie!$B9) -> 0 | X9: =-SUMIFS('2023-07'!$M:$M,'2023-07'!$E:$E,Trésorerie!X$4,'2023-07'!$F:$F,Trésorerie!$B9)+SUMIFS('2023-07'!$N:$N,'2023-07'!$E:$E,Trésorerie!X$4,'2023-07'!$F:$F,Trésorerie!$B9) -> 26937.39 | Y9: =-SUMIFS('2023-08'!$M:$M,'2023-08'!$E:$E,Trésorerie!Y$4,'2023-08'!$F:$F,Trésorerie!$B9)+SUMIFS('2023-08'!$N:$N,'2023-08'!$E:$E,Trésorerie!Y$4,'2023-08'!$F:$F,Trésorerie!$B9) -> 0 | Z9: =-SUMIFS('2023-09'!$M:$M,'2023-09'!$E:$E,Trésorerie!Z$4,'2023-09'!$F:$F,Trésorerie!$B9)+SUMIFS('2023-09'!$N:$N,'2023-09'!$E:$E,Trésorerie!Z$4,'2023-09'!$F:$F,Trésorerie!$B9) -> 11311.02 | AA9: =-SUMIFS('2023-10'!$M:$M,'2023-10'!$E:$E,Trésorerie!AA$4,'2023-10'!$F:$F,Trésorerie!$B9)+SUMIFS('2023-10'!$N:$N,'2023-10'!$E:$E,Trésorerie!AA$4,'2023-10'!$F:$F,Trésorerie!$B9) -> 8009.76 | AB9: =IF(SUM($E9:O9)>SUM($R9:AA9),SUM($E9:O9)-SUM($R9:AA9),0) -> 4827.42 | AC9: =IF(SUM($E9:P9)>SUM($R9:AB9),SUM($E9:P9)-SUM($R9:AB9),0) -> 7695.54
A10: =SUM(E10:P10) -> 90202 | B10: 445060 | C10: CAF SUBV.FONCTIONNEMENT | D10: Entrée | E10: =-SUMIFS('2022'!$M:$M,'2022'!$E:$E,Trésorerie!E$4,'2022'!$F:$F,Trésorerie!$B10)+SUMIFS('2022'!$N:$N,'2022'!$E:$E,Trésorerie!E$4,'2022'!$F:$F,Trésorerie!$B10) -> 0 | F10: =-SUMIFS('2022'!$M:$M,'2022'!$E:$E,Trésorerie!F$4,'2022'!$F:$F,Trésorerie!$B10)+SUMIFS('2022'!$N:$N,'2022'!$E:$E,Trésorerie!F$4,'2022'!$F:$F,Trésorerie!$B10) -> 0 | G10: =-SUMIFS('2022'!$M:$M,'2022'!$E:$E,Trésorerie!G$4,'2022'!$F:$F,Trésorerie!$B10)+SUMIFS('2022'!$N:$N,'2022'!$E:$E,Trésorerie!G$4,'2022'!$F:$F,Trésorerie!$B10) -> 0 | H10: =-SUMIFS('2022'!$M:$M,'2022'!$E:$E,Trésorerie!H$4,'2022'!$F:$F,Trésorerie!$B10)+SUMIFS('2022'!$N:$N,'2022'!$E:$E,Trésorerie!H$4,'2022'!$F:$F,Trésorerie!$B10) -> 0 | I10: =-SUMIFS('2022'!$M:$M,'2022'!$E:$E,Trésorerie!I$4,'2022'!$F:$F,Trésorerie!$B10)+SUMIFS('2022'!$N:$N,'2022'!$E:$E,Trésorerie!I$4,'2022'!$F:$F,Trésorerie!$B10) -> 0 | J10: =-SUMIFS('2022'!$M:$M,'2022'!$E:$E,Trésorerie!J$4,'2022'!$F:$F,Trésorerie!$B10)+SUMIFS('2022'!$N:$N,'2022'!$E:$E,Trésorerie!J$4,'2022'!$F:$F,Trésorerie!$B10) -> 45101 | K10: =-SUMIFS('2022'!$M:$M,'2022'!$E:$E,Trésorerie!K$4,'2022'!$F:$F,Trésorerie!$B10)+SUMIFS('2022'!$N:$N,'2022'!$E:$E,Trésorerie!K$4,'2022'!$F:$F,Trésorerie!$B10) -> 0 | L10: =-SUMIFS('2022'!$M:$M,'2022'!$E:$E,Trésorerie!L$4,'2022'!$F:$F,Trésorerie!$B10)+SUMIFS('2022'!$N:$N,'2022'!$E:$E,Trésorerie!L$4,'2022'!$F:$F,Trésorerie!$B10) -> 0 | ... P10: =-SUMIFS('2022'!$M:$M,'2022'!$E:$E,Trésorerie!P$4,'2022'!$F:$F,Trésorerie!$B10)+SUMIFS('2022'!$N:$N,'2022'!$E:$E,Trésorerie!P$4,'2022'!$F:$F,Trésorerie!$B10) -> 0 | R10: =-SUMIFS('2023-01'!$M:$M,'2023-01'!$E:$E,Trésorerie!R$4,'2023-01'!$F:$F,Trésorerie!$B10)+SUMIFS('2023-01'!$N:$N,'2023-01'!$E:$E,Trésorerie!R$4,'2023-01'!$F:$F,Trésorerie!$B10) -> 0 | S10: =-SUMIFS('2023-02'!$M:$M,'2023-02'!$E:$E,Trésorerie!S$4,'2023-02'!$F:$F,Trésorerie!$B10)+SUMIFS('2023-02'!$N:$N,'2023-02'!$E:$E,Trésorerie!S$4,'2023-02'!$F:$F,Trésorerie!$B10) -> 0 | T10: =-SUMIFS('2023-03'!$M:$M,'2023-03'!$E:$E,Trésorerie!T$4,'2023-03'!$F:$F,Trésorerie!$B10)+SUMIFS('2023-03'!$N:$N,'2023-03'!$E:$E,Trésorerie!T$4,'2023-03'!$F:$F,Trésorerie!$B10) -> 0 | U10: =-SUMIFS('2023-04'!$M:$M,'2023-04'!$E:$E,Trésorerie!U$4,'2023-04'!$F:$F,Trésorerie!$B10)+SUMIFS('2023-04'!$N:$N,'2023-04'!$E:$E,Trésorerie!U$4,'2023-04'!$F:$F,Trésorerie!$B10) -> 0 | V10: =-SUMIFS('2023-05'!$M:$M,'2023-05'!$E:$E,Trésorerie!V$4,'2023-05'!$F:$F,Trésorerie!$B10)+SUMIFS('2023-05'!$N:$N,'2023-05'!$E:$E,Trésorerie!V$4,'2023-05'!$F:$F,Trésorerie!$B10) -> 0 | W10: =-SUMIFS('2023-06'!$M:$M,'2023-06'!$E:$E,Trésorerie!W$4,'2023-06'!$F:$F,Trésorerie!$B10)+SUMIFS('2023-06'!$N:$N,'2023-06'!$E:$E,Trésorerie!W$4,'2023-06'!$F:$F,Trésorerie!$B10) -> 44039 | X10: =-SUMIFS('2023-07'!$M:$M,'2023-07'!$E:$E,Trésorerie!X$4,'2023-07'!$F:$F,Trésorerie!$B10)+SUMIFS('2023-07'!$N:$N,'2023-07'!$E:$E,Trésorerie!X$4,'2023-07'!$F:$F,Trésorerie!$B10) -> 0 | Y10: =-SUMIFS('2023-08'!$M:$M,'2023-08'!$E:$E,Trésorerie!Y$4,'2023-08'!$F:$F,Trésorerie!$B10)+SUMIFS('2023-08'!$N:$N,'2023-08'!$E:$E,Trésorerie!Y$4,'2023-08'!$F:$F,Trésorerie!$B10) -> 0 | Z10: =-SUMIFS('2023-09'!$M:$M,'2023-09'!$E:$E,Trésorerie!Z$4,'2023-09'!$F:$F,Trésorerie!$B10)+SUMIFS('2023-09'!$N:$N,'2023-09'!$E:$E,Trésorerie!Z$4,'2023-09'!$F:$F,Trésorerie!$B10) -> 44039 | AA10: =-SUMIFS('2023-10'!$M:$M,'2023-10'!$E:$E,Trésorerie!AA$4,'2023-10'!$F:$F,Trésorerie!$B10)+SUMIFS('2023-10'!$N:$N,'2023-10'!$E:$E,Trésorerie!AA$4,'2023-10'!$F:$F,Trésorerie!$B10) -> 0 | AB10: =IF(SUM($E10:O10)>SUM($R10:AA10),SUM($E10:O10)-SUM($R10:AA10),0) -> 2124 | AC10: =IF(SUM($E10:P10)>SUM($R10:AB10),SUM($E10:P10)-SUM($R10:AB10),0) -> 0
A11: =SUM(E11:P11) -> 56340 | B11: 468710 | C11: METROPOLE GRD LYON A RECEVOIR | D11: Entrée | E11: =-SUMIFS('2022'!$M:$M,'2022'!$E:$E,Trésorerie!E$4,'2022'!$F:$F,Trésorerie!$B11)+SUMIFS('2022'!$N:$N,'2022'!$E:$E,Trésorerie!E$4,'2022'!$F:$F,Trésorerie!$B11) -> 0 | F11: =-SUMIFS('2022'!$M:$M,'2022'!$E:$E,Trésorerie!F$4,'2022'!$F:$F,Trésorerie!$B11)+SUMIFS('2022'!$N:$N,'2022'!$E:$E,Trésorerie!F$4,'2022'!$F:$F,Trésorerie!$B11) -> 0 | G11: =-SUMIFS('2022'!$M:$M,'2022'!$E:$E,Trésorerie!G$4,'2022'!$F:$F,Trésorerie!$B11)+SUMIFS('2022'!$N:$N,'2022'!$E:$E,Trésorerie!G$4,'2022'!$F:$F,Trésorerie!$B11) -> 9780 | H11: =-SUMIFS('2022'!$M:$M,'2022'!$E:$E,Trésorerie!H$4,'2022'!$F:$F,Trésorerie!$B11)+SUMIFS('2022'!$N:$N,'2022'!$E:$E,Trésorerie!H$4,'2022'!$F:$F,Trésorerie!$B11) -> 0 | I11: =-SUMIFS('2022'!$M:$M,'2022'!$E:$E,Trésorerie!I$4,'2022'!$F:$F,Trésorerie!$B11)+SUMIFS('2022'!$N:$N,'2022'!$E:$E,Trésorerie!I$4,'2022'!$F:$F,Trésorerie!$B11) -> 22820 | J11: =-SUMIFS('2022'!$M:$M,'2022'!$E:$E,Trésorerie!J$4,'2022'!$F:$F,Trésorerie!$B11)+SUMIFS('2022'!$N:$N,'2022'!$E:$E,Trésorerie!J$4,'2022'!$F:$F,Trésorerie!$B11) -> 0 | K11: =-SUMIFS('2022'!$M:$M,'2022'!$E:$E,Trésorerie!K$4,'2022'!$F:$F,Trésorerie!$B11)+SUMIFS('2022'!$N:$N,'2022'!$E:$E,Trésorerie!K$4,'2022'!$F:$F,Trésorerie!$B11) -> 0 | L11: =-SUMIFS('2022'!$M:$M,'2022'!$E:$E,Trésorerie!L$4,'2022'!$F:$F,Trésorerie!$B11)+SUMIFS('2022'!$N:$N,'2022'!$E:$E,Trésorerie!L$4,'2022'!$F:$F,Trésorerie!$B11) -> 0 | ... P11: =-SUMIFS('2022'!$M:$M,'2022'!$E:$E,Trésorerie!P$4,'2022'!$F:$F,Trésorerie!$B11)+SUMIFS('2022'!$N:$N,'2022'!$E:$E,Trésorerie!P$4,'2022'!$F:$F,Trésorerie!$B11) -> 0 | R11: =-SUMIFS('2023-01'!$M:$M,'2023-01'!$E:$E,Trésorerie!R$4,'2023-01'!$F:$F,Trésorerie!$B11)+SUMIFS('2023-01'!$N:$N,'2023-01'!$E:$E,Trésorerie!R$4,'2023-01'!$F:$F,Trésorerie!$B11) -> 0 | S11: =-SUMIFS('2023-02'!$M:$M,'2023-02'!$E:$E,Trésorerie!S$4,'2023-02'!$F:$F,Trésorerie!$B11)+SUMIFS('2023-02'!$N:$N,'2023-02'!$E:$E,Trésorerie!S$4,'2023-02'!$F:$F,Trésorerie!$B11) -> 0 | T11: =-SUMIFS('2023-03'!$M:$M,'2023-03'!$E:$E,Trésorerie!T$4,'2023-03'!$F:$F,Trésorerie!$B11)+SUMIFS('2023-03'!$N:$N,'2023-03'!$E:$E,Trésorerie!T$4,'2023-03'!$F:$F,Trésorerie!$B11) -> 0 | U11: =-SUMIFS('2023-04'!$M:$M,'2023-04'!$E:$E,Trésorerie!U$4,'2023-04'!$F:$F,Trésorerie!$B11)+SUMIFS('2023-04'!$N:$N,'2023-04'!$E:$E,Trésorerie!U$4,'2023-04'!$F:$F,Trésorerie!$B11) -> 0 | V11: =-SUMIFS('2023-05'!$M:$M,'2023-05'!$E:$E,Trésorerie!V$4,'2023-05'!$F:$F,Trésorerie!$B11)+SUMIFS('2023-05'!$N:$N,'2023-05'!$E:$E,Trésorerie!V$4,'2023-05'!$F:$F,Trésorerie!$B11) -> 24661 | W11: =-SUMIFS('2023-06'!$M:$M,'2023-06'!$E:$E,Trésorerie!W$4,'2023-06'!$F:$F,Trésorerie!$B11)+SUMIFS('2023-06'!$N:$N,'2023-06'!$E:$E,Trésorerie!W$4,'2023-06'!$F:$F,Trésorerie!$B11) -> 0 | X11: =-SUMIFS('2023-07'!$M:$M,'2023-07'!$E:$E,Trésorerie!X$4,'2023-07'!$F:$F,Trésorerie!$B11)+SUMIFS('2023-07'!$N:$N,'2023-07'!$E:$E,Trésorerie!X$4,'2023-07'!$F:$F,Trésorerie!$B11) -> 0 | Y11: =-SUMIFS('2023-08'!$M:$M,'2023-08'!$E:$E,Trésorerie!Y$4,'2023-08'!$F:$F,Trésorerie!$B11)+SUMIFS('2023-08'!$N:$N,'2023-08'!$E:$E,Trésorerie!Y$4,'2023-08'!$F:$F,Trésorerie!$B11) -> 6000 | Z11: =-SUMIFS('2023-09'!$M:$M,'2023-09'!$E:$E,Trésorerie!Z$4,'2023-09'!$F:$F,Trésorerie!$B11)+SUMIFS('2023-09'!$N:$N,'2023-09'!$E:$E,Trésorerie!Z$4,'2023-09'!$F:$F,Trésorerie!$B11) -> 0 | AA11: =-SUMIFS('2023-10'!$M:$M,'2023-10'!$E:$E,Trésorerie!AA$4,'2023-10'!$F:$F,Trésorerie!$B11)+SUMIFS('2023-10'!$N:$N,'2023-10'!$E:$E,Trésorerie!AA$4,'2023-10'!$F:$F,Trésorerie!$B11) -> 25630 | AB11: =IF(SUM($E11:O11)>SUM($R11:AA11),SUM($E11:O11)-SUM($R11:AA11),0) -> 49 | AC11: =IF(SUM($E11:P11)>SUM($R11:AB11),SUM($E11:P11)-SUM($R11:AB11),0) -> 0
A12: =SUM(E12:P12) -> 51000 | B12: 468730 | C12: ETAT ACSE CGET | D12: Entrée | E12: =-SUMIFS('2022'!$M:$M,'2022'!$E:$E,Trésorerie!E$4,'2022'!$F:$F,Trésorerie!$B12)+SUMIFS('2022'!$N:$N,'2022'!$E:$E,Trésorerie!E$4,'2022'!$F:$F,Trésorerie!$B12) -> 0 | F12: =-SUMIFS('2022'!$M:$M,'2022'!$E:$E,Trésorerie!F$4,'2022'!$F:$F,Trésorerie!$B12)+SUMIFS('2022'!$N:$N,'2022'!$E:$E,Trésorerie!F$4,'2022'!$F:$F,Trésorerie!$B12) -> 0 | G12: =-SUMIFS('2022'!$M:$M,'2022'!$E:$E,Trésorerie!G$4,'2022'!$F:$F,Trésorerie!$B12)+SUMIFS('2022'!$N:$N,'2022'!$E:$E,Trésorerie!G$4,'2022'!$F:$F,Trésorerie!$B12) -> 0 | H12: =-SUMIFS('2022'!$M:$M,'2022'!$E:$E,Trésorerie!H$4,'2022'!$F:$F,Trésorerie!$B12)+SUMIFS('2022'!$N:$N,'2022'!$E:$E,Trésorerie!H$4,'2022'!$F:$F,Trésorerie!$B12) -> 0 | I12: =-SUMIFS('2022'!$M:$M,'2022'!$E:$E,Trésorerie!I$4,'2022'!$F:$F,Trésorerie!$B12)+SUMIFS('2022'!$N:$N,'2022'!$E:$E,Trésorerie!I$4,'2022'!$F:$F,Trésorerie!$B12) -> 0 | J12: =-SUMIFS('2022'!$M:$M,'2022'!$E:$E,Trésorerie!J$4,'2022'!$F:$F,Trésorerie!$B12)+SUMIFS('2022'!$N:$N,'2022'!$E:$E,Trésorerie!J$4,'2022'!$F:$F,Trésorerie!$B12) -> 0 | K12: =-SUMIFS('2022'!$M:$M,'2022'!$E:$E,Trésorerie!K$4,'2022'!$F:$F,Trésorerie!$B12)+SUMIFS('2022'!$N:$N,'2022'!$E:$E,Trésorerie!K$4,'2022'!$F:$F,Trésorerie!$B12) -> 0 | L12: =-SUMIFS('2022'!$M:$M,'2022'!$E:$E,Trésorerie!L$4,'2022'!$F:$F,Trésorerie!$B12)+SUMIFS('2022'!$N:$N,'2022'!$E:$E,Trésorerie!L$4,'2022'!$F:$F,Trésorerie!$B12) -> 51000 | ... P12: =-SUMIFS('2022'!$M:$M,'2022'!$E:$E,Trésorerie!P$4,'2022'!$F:$F,Trésorerie!$B12)+SUMIFS('2022'!$N:$N,'2022'!$E:$E,Trésorerie!P$4,'2022'!$F:$F,Trésorerie!$B12) -> 0 | R12: =-SUMIFS('2023-01'!$M:$M,'2023-01'!$E:$E,Trésorerie!R$4,'2023-01'!$F:$F,Trésorerie!$B12)+SUMIFS('2023-01'!$N:$N,'2023-01'!$E:$E,Trésorerie!R$4,'2023-01'!$F:$F,Trésorerie!$B12) -> 0 | S12: =-SUMIFS('2023-02'!$M:$M,'2023-02'!$E:$E,Trésorerie!S$4,'2023-02'!$F:$F,Trésorerie!$B12)+SUMIFS('2023-02'!$N:$N,'2023-02'!$E:$E,Trésorerie!S$4,'2023-02'!$F:$F,Trésorerie!$B12) -> 0 | T12: =-SUMIFS('2023-03'!$M:$M,'2023-03'!$E:$E,Trésorerie!T$4,'2023-03'!$F:$F,Trésorerie!$B12)+SUMIFS('2023-03'!$N:$N,'2023-03'!$E:$E,Trésorerie!T$4,'2023-03'!$F:$F,Trésorerie!$B12) -> 0 | U12: =-SUMIFS('2023-04'!$M:$M,'2023-04'!$E:$E,Trésorerie!U$4,'2023-04'!$F:$F,Trésorerie!$B12)+SUMIFS('2023-04'!$N:$N,'2023-04'!$E:$E,Trésorerie!U$4,'2023-04'!$F:$F,Trésorerie!$B12) -> 0 | V12: =-SUMIFS('2023-05'!$M:$M,'2023-05'!$E:$E,Trésorerie!V$4,'2023-05'!$F:$F,Trésorerie!$B12)+SUMIFS('2023-05'!$N:$N,'2023-05'!$E:$E,Trésorerie!V$4,'2023-05'!$F:$F,Trésorerie!$B12) -> 0 | W12: =-SUMIFS('2023-06'!$M:$M,'2023-06'!$E:$E,Trésorerie!W$4,'2023-06'!$F:$F,Trésorerie!$B12)+SUMIFS('2023-06'!$N:$N,'2023-06'!$E:$E,Trésorerie!W$4,'2023-06'!$F:$F,Trésorerie!$B12) -> 0 | X12: =-SUMIFS('2023-07'!$M:$M,'2023-07'!$E:$E,Trésorerie!X$4,'2023-07'!$F:$F,Trésorerie!$B12)+SUMIFS('2023-07'!$N:$N,'2023-07'!$E:$E,Trésorerie!X$4,'2023-07'!$F:$F,Trésorerie!$B12) -> 43000 | Y12: =-SUMIFS('2023-08'!$M:$M,'2023-08'!$E:$E,Trésorerie!Y$4,'2023-08'!$F:$F,Trésorerie!$B12)+SUMIFS('2023-08'!$N:$N,'2023-08'!$E:$E,Trésorerie!Y$4,'2023-08'!$F:$F,Trésorerie!$B12) -> 4500 | Z12: =-SUMIFS('2023-09'!$M:$M,'2023-09'!$E:$E,Trésorerie!Z$4,'2023-09'!$F:$F,Trésorerie!$B12)+SUMIFS('2023-09'!$N:$N,'2023-09'!$E:$E,Trésorerie!Z$4,'2023-09'!$F:$F,Trésorerie!$B12) -> 0 | AA12: =-SUMIFS('2023-10'!$M:$M,'2023-10'!$E:$E,Trésorerie!AA$4,'2023-10'!$F:$F,Trésorerie!$B12)+SUMIFS('2023-10'!$N:$N,'2023-10'!$E:$E,Trésorerie!AA$4,'2023-10'!$F:$F,Trésorerie!$B12) -> 666.6 | AB12: =IF(SUM($E12:O12)>SUM($R12:AA12),SUM($E12:O12)-SUM($R12:AA12),0) -> 2833.4 | AC12: =IF(SUM($E12:P12)>SUM($R12:AB12),SUM($E12:P12)-SUM($R12:AB12),0) -> 0
A13: =SUM(E13:P13) -> 47294 | B13: 445051 | C13: CAF ACF | D13: Entrée | E13: =-SUMIFS('2022'!$M:$M,'2022'!$E:$E,Trésorerie!E$4,'2022'!$F:$F,Trésorerie!$B13)+SUMIFS('2022'!$N:$N,'2022'!$E:$E,Trésorerie!E$4,'2022'!$F:$F,Trésorerie!$B13) -> 0 | F13: =-SUMIFS('2022'!$M:$M,'2022'!$E:$E,Trésorerie!F$4,'2022'!$F:$F,Trésorerie!$B13)+SUMIFS('2022'!$N:$N,'2022'!$E:$E,Trésorerie!F$4,'2022'!$F:$F,Trésorerie!$B13) -> 0 | G13: =-SUMIFS('2022'!$M:$M,'2022'!$E:$E,Trésorerie!G$4,'2022'!$F:$F,Trésorerie!$B13)+SUMIFS('2022'!$N:$N,'2022'!$E:$E,Trésorerie!G$4,'2022'!$F:$F,Trésorerie!$B13) -> 21313.8 | H13: =-SUMIFS('2022'!$M:$M,'2022'!$E:$E,Trésorerie!H$4,'2022'!$F:$F,Trésorerie!$B13)+SUMIFS('2022'!$N:$N,'2022'!$E:$E,Trésorerie!H$4,'2022'!$F:$F,Trésorerie!$B13) -> 0 | I13: =-SUMIFS('2022'!$M:$M,'2022'!$E:$E,Trésorerie!I$4,'2022'!$F:$F,Trésorerie!$B13)+SUMIFS('2022'!$N:$N,'2022'!$E:$E,Trésorerie!I$4,'2022'!$F:$F,Trésorerie!$B13) -> 4666.4 | J13: =-SUMIFS('2022'!$M:$M,'2022'!$E:$E,Trésorerie!J$4,'2022'!$F:$F,Trésorerie!$B13)+SUMIFS('2022'!$N:$N,'2022'!$E:$E,Trésorerie!J$4,'2022'!$F:$F,Trésorerie!$B13) -> 0 | K13: =-SUMIFS('2022'!$M:$M,'2022'!$E:$E,Trésorerie!K$4,'2022'!$F:$F,Trésorerie!$B13)+SUMIFS('2022'!$N:$N,'2022'!$E:$E,Trésorerie!K$4,'2022'!$F:$F,Trésorerie!$B13) -> 0 | L13: =-SUMIFS('2022'!$M:$M,'2022'!$E:$E,Trésorerie!L$4,'2022'!$F:$F,Trésorerie!$B13)+SUMIFS('2022'!$N:$N,'2022'!$E:$E,Trésorerie!L$4,'2022'!$F:$F,Trésorerie!$B13) -> 0 | ... P13: =-SUMIFS('2022'!$M:$M,'2022'!$E:$E,Trésorerie!P$4,'2022'!$F:$F,Trésorerie!$B13)+SUMIFS('2022'!$N:$N,'2022'!$E:$E,Trésorerie!P$4,'2022'!$F:$F,Trésorerie!$B13) -> 0 | R13: =-SUMIFS('2023-01'!$M:$M,'2023-01'!$E:$E,Trésorerie!R$4,'2023-01'!$F:$F,Trésorerie!$B13)+SUMIFS('2023-01'!$N:$N,'2023-01'!$E:$E,Trésorerie!R$4,'2023-01'!$F:$F,Trésorerie!$B13) -> 0 | S13: =-SUMIFS('2023-02'!$M:$M,'2023-02'!$E:$E,Trésorerie!S$4,'2023-02'!$F:$F,Trésorerie!$B13)+SUMIFS('2023-02'!$N:$N,'2023-02'!$E:$E,Trésorerie!S$4,'2023-02'!$F:$F,Trésorerie!$B13) -> 0 | T13: =-SUMIFS('2023-03'!$M:$M,'2023-03'!$E:$E,Trésorerie!T$4,'2023-03'!$F:$F,Trésorerie!$B13)+SUMIFS('2023-03'!$N:$N,'2023-03'!$E:$E,Trésorerie!T$4,'2023-03'!$F:$F,Trésorerie!$B13) -> 20632.68 | U13: =-SUMIFS('2023-04'!$M:$M,'2023-04'!$E:$E,Trésorerie!U$4,'2023-04'!$F:$F,Trésorerie!$B13)+SUMIFS('2023-04'!$N:$N,'2023-04'!$E:$E,Trésorerie!U$4,'2023-04'!$F:$F,Trésorerie!$B13) -> 0 | V13: =-SUMIFS('2023-05'!$M:$M,'2023-05'!$E:$E,Trésorerie!V$4,'2023-05'!$F:$F,Trésorerie!$B13)+SUMIFS('2023-05'!$N:$N,'2023-05'!$E:$E,Trésorerie!V$4,'2023-05'!$F:$F,Trésorerie!$B13) -> 0 | W13: =-SUMIFS('2023-06'!$M:$M,'2023-06'!$E:$E,Trésorerie!W$4,'2023-06'!$F:$F,Trésorerie!$B13)+SUMIFS('2023-06'!$N:$N,'2023-06'!$E:$E,Trésorerie!W$4,'2023-06'!$F:$F,Trésorerie!$B13) -> 0 | X13: =-SUMIFS('2023-07'!$M:$M,'2023-07'!$E:$E,Trésorerie!X$4,'2023-07'!$F:$F,Trésorerie!$B13)+SUMIFS('2023-07'!$N:$N,'2023-07'!$E:$E,Trésorerie!X$4,'2023-07'!$F:$F,Trésorerie!$B13) -> 0 | Y13: =-SUMIFS('2023-08'!$M:$M,'2023-08'!$E:$E,Trésorerie!Y$4,'2023-08'!$F:$F,Trésorerie!$B13)+SUMIFS('2023-08'!$N:$N,'2023-08'!$E:$E,Trésorerie!Y$4,'2023-08'!$F:$F,Trésorerie!$B13) -> 0 | Z13: =-SUMIFS('2023-09'!$M:$M,'2023-09'!$E:$E,Trésorerie!Z$4,'2023-09'!$F:$F,Trésorerie!$B13)+SUMIFS('2023-09'!$N:$N,'2023-09'!$E:$E,Trésorerie!Z$4,'2023-09'!$F:$F,Trésorerie!$B13) -> 0 | AA13: =-SUMIFS('2023-10'!$M:$M,'2023-10'!$E:$E,Trésorerie!AA$4,'2023-10'!$F:$F,Trésorerie!$B13)+SUMIFS('2023-10'!$N:$N,'2023-10'!$E:$E,Trésorerie!AA$4,'2023-10'!$F:$F,Trésorerie!$B13) -> 20632.68 | AB13: =IF(SUM($E13:O13)>SUM($R13:AA13),SUM($E13:O13)-SUM($R13:AA13),0) -> 6028.64 | AC13: =IF(SUM($E13:P13)>SUM($R13:AB13),SUM($E13:P13)-SUM($R13:AB13),0) -> 0
A14: =SUM(E14:P14) -> 38494.29 | B14: 468200 | C14: INDEMN.JOURNAL. A RECEVOIR | D14: Entrée | E14: =-SUMIFS('2022'!$M:$M,'2022'!$E:$E,Trésorerie!E$4,'2022'!$F:$F,Trésorerie!$B14)+SUMIFS('2022'!$N:$N,'2022'!$E:$E,Trésorerie!E$4,'2022'!$F:$F,Trésorerie!$B14) -> 2980.91 | F14: =-SUMIFS('2022'!$M:$M,'2022'!$E:$E,Trésorerie!F$4,'2022'!$F:$F,Trésorerie!$B14)+SUMIFS('2022'!$N:$N,'2022'!$E:$E,Trésorerie!F$4,'2022'!$F:$F,Trésorerie!$B14) -> 2585.36 | G14: =-SUMIFS('2022'!$M:$M,'2022'!$E:$E,Trésorerie!G$4,'2022'!$F:$F,Trésorerie!$B14)+SUMIFS('2022'!$N:$N,'2022'!$E:$E,Trésorerie!G$4,'2022'!$F:$F,Trésorerie!$B14) -> 1030.5 | H14: =-SUMIFS('2022'!$M:$M,'2022'!$E:$E,Trésorerie!H$4,'2022'!$F:$F,Trésorerie!$B14)+SUMIFS('2022'!$N:$N,'2022'!$E:$E,Trésorerie!H$4,'2022'!$F:$F,Trésorerie!$B14) -> 1879.11 | I14: =-SUMIFS('2022'!$M:$M,'2022'!$E:$E,Trésorerie!I$4,'2022'!$F:$F,Trésorerie!$B14)+SUMIFS('2022'!$N:$N,'2022'!$E:$E,Trésorerie!I$4,'2022'!$F:$F,Trésorerie!$B14) -> 6227.46 | J14: =-SUMIFS('2022'!$M:$M,'2022'!$E:$E,Trésorerie!J$4,'2022'!$F:$F,Trésorerie!$B14)+SUMIFS('2022'!$N:$N,'2022'!$E:$E,Trésorerie!J$4,'2022'!$F:$F,Trésorerie!$B14) -> 2199.56 | K14: =-SUMIFS('2022'!$M:$M,'2022'!$E:$E,Trésorerie!K$4,'2022'!$F:$F,Trésorerie!$B14)+SUMIFS('2022'!$N:$N,'2022'!$E:$E,Trésorerie!K$4,'2022'!$F:$F,Trésorerie!$B14) -> 878.92 | L14: =-SUMIFS('2022'!$M:$M,'2022'!$E:$E,Trésorerie!L$4,'2022'!$F:$F,Trésorerie!$B14)+SUMIFS('2022'!$N:$N,'2022'!$E:$E,Trésorerie!L$4,'2022'!$F:$F,Trésorerie!$B14) -> 3571.15 | ... P14: =-SUMIFS('2022'!$M:$M,'2022'!$E:$E,Trésorerie!P$4,'2022'!$F:$F,Trésorerie!$B14)+SUMIFS('2022'!$N:$N,'2022'!$E:$E,Trésorerie!P$4,'2022'!$F:$F,Trésorerie!$B14) -> 888.28 | R14: =-SUMIFS('2023-01'!$M:$M,'2023-01'!$E:$E,Trésorerie!R$4,'2023-01'!$F:$F,Trésorerie!$B14)+SUMIFS('2023-01'!$N:$N,'2023-01'!$E:$E,Trésorerie!R$4,'2023-01'!$F:$F,Trésorerie!$B14) -> 290.76 | S14: =-SUMIFS('2023-02'!$M:$M,'2023-02'!$E:$E,Trésorerie!S$4,'2023-02'!$F:$F,Trésorerie!$B14)+SUMIFS('2023-02'!$N:$N,'2023-02'!$E:$E,Trésorerie!S$4,'2023-02'!$F:$F,Trésorerie!$B14) -> 2046.45 | T14: =-SUMIFS('2023-03'!$M:$M,'2023-03'!$E:$E,Trésorerie!T$4,'2023-03'!$F:$F,Trésorerie!$B14)+SUMIFS('2023-03'!$N:$N,'2023-03'!$E:$E,Trésorerie!T$4,'2023-03'!$F:$F,Trésorerie!$B14) -> 3402.87 | U14: =-SUMIFS('2023-04'!$M:$M,'2023-04'!$E:$E,Trésorerie!U$4,'2023-04'!$F:$F,Trésorerie!$B14)+SUMIFS('2023-04'!$N:$N,'2023-04'!$E:$E,Trésorerie!U$4,'2023-04'!$F:$F,Trésorerie!$B14) -> 2414.05 | V14: =-SUMIFS('2023-05'!$M:$M,'2023-05'!$E:$E,Trésorerie!V$4,'2023-05'!$F:$F,Trésorerie!$B14)+SUMIFS('2023-05'!$N:$N,'2023-05'!$E:$E,Trésorerie!V$4,'2023-05'!$F:$F,Trésorerie!$B14) -> 953.48 | W14: =-SUMIFS('2023-06'!$M:$M,'2023-06'!$E:$E,Trésorerie!W$4,'2023-06'!$F:$F,Trésorerie!$B14)+SUMIFS('2023-06'!$N:$N,'2023-06'!$E:$E,Trésorerie!W$4,'2023-06'!$F:$F,Trésorerie!$B14) -> 2874.48 | X14: =-SUMIFS('2023-07'!$M:$M,'2023-07'!$E:$E,Trésorerie!X$4,'2023-07'!$F:$F,Trésorerie!$B14)+SUMIFS('2023-07'!$N:$N,'2023-07'!$E:$E,Trésorerie!X$4,'2023-07'!$F:$F,Trésorerie!$B14) -> 2138.07 | Y14: =-SUMIFS('2023-08'!$M:$M,'2023-08'!$E:$E,Trésorerie!Y$4,'2023-08'!$F:$F,Trésorerie!$B14)+SUMIFS('2023-08'!$N:$N,'2023-08'!$E:$E,Trésorerie!Y$4,'2023-08'!$F:$F,Trésorerie!$B14) -> 818.96 | Z14: =-SUMIFS('2023-09'!$M:$M,'2023-09'!$E:$E,Trésorerie!Z$4,'2023-09'!$F:$F,Trésorerie!$B14)+SUMIFS('2023-09'!$N:$N,'2023-09'!$E:$E,Trésorerie!Z$4,'2023-09'!$F:$F,Trésorerie!$B14) -> 1006.45 | AA14: =-SUMIFS('2023-10'!$M:$M,'2023-10'!$E:$E,Trésorerie!AA$4,'2023-10'!$F:$F,Trésorerie!$B14)+SUMIFS('2023-10'!$N:$N,'2023-10'!$E:$E,Trésorerie!AA$4,'2023-10'!$F:$F,Trésorerie!$B14) -> 8507.24 | AB14: =IF(SUM($E14:O14)>SUM($R14:AA14),SUM($E14:O14)-SUM($R14:AA14),0) -> 13153.2 | AC14: =IF(SUM($E14:P14)>SUM($R14:AB14),SUM($E14:P14)-SUM($R14:AB14),0) -> 888.28
A15: =SUM(E15:P15) -> 32172 | B15: 445000 | C15: CAF PS AL EXTRASCO CYP CFAL | D15: Entrée | E15: =-SUMIFS('2022'!$M:$M,'2022'!$E:$E,Trésorerie!E$4,'2022'!$F:$F,Trésorerie!$B15)+SUMIFS('2022'!$N:$N,'2022'!$E:$E,Trésorerie!E$4,'2022'!$F:$F,Trésorerie!$B15) -> 0 | F15: =-SUMIFS('2022'!$M:$M,'2022'!$E:$E,Trésorerie!F$4,'2022'!$F:$F,Trésorerie!$B15)+SUMIFS('2022'!$N:$N,'2022'!$E:$E,Trésorerie!F$4,'2022'!$F:$F,Trésorerie!$B15) -> 0 | G15: =-SUMIFS('2022'!$M:$M,'2022'!$E:$E,Trésorerie!G$4,'2022'!$F:$F,Trésorerie!$B15)+SUMIFS('2022'!$N:$N,'2022'!$E:$E,Trésorerie!G$4,'2022'!$F:$F,Trésorerie!$B15) -> 0 | H15: =-SUMIFS('2022'!$M:$M,'2022'!$E:$E,Trésorerie!H$4,'2022'!$F:$F,Trésorerie!$B15)+SUMIFS('2022'!$N:$N,'2022'!$E:$E,Trésorerie!H$4,'2022'!$F:$F,Trésorerie!$B15) -> 0 | I15: =-SUMIFS('2022'!$M:$M,'2022'!$E:$E,Trésorerie!I$4,'2022'!$F:$F,Trésorerie!$B15)+SUMIFS('2022'!$N:$N,'2022'!$E:$E,Trésorerie!I$4,'2022'!$F:$F,Trésorerie!$B15) -> 10692.8 | J15: =-SUMIFS('2022'!$M:$M,'2022'!$E:$E,Trésorerie!J$4,'2022'!$F:$F,Trésorerie!$B15)+SUMIFS('2022'!$N:$N,'2022'!$E:$E,Trésorerie!J$4,'2022'!$F:$F,Trésorerie!$B15) -> 14973.48 | K15: =-SUMIFS('2022'!$M:$M,'2022'!$E:$E,Trésorerie!K$4,'2022'!$F:$F,Trésorerie!$B15)+SUMIFS('2022'!$N:$N,'2022'!$E:$E,Trésorerie!K$4,'2022'!$F:$F,Trésorerie!$B15) -> 0 | L15: =-SUMIFS('2022'!$M:$M,'2022'!$E:$E,Trésorerie!L$4,'2022'!$F:$F,Trésorerie!$B15)+SUMIFS('2022'!$N:$N,'2022'!$E:$E,Trésorerie!L$4,'2022'!$F:$F,Trésorerie!$B15) -> 0 | ... P15: =-SUMIFS('2022'!$M:$M,'2022'!$E:$E,Trésorerie!P$4,'2022'!$F:$F,Trésorerie!$B15)+SUMIFS('2022'!$N:$N,'2022'!$E:$E,Trésorerie!P$4,'2022'!$F:$F,Trésorerie!$B15) -> 0 | R15: =-SUMIFS('2023-01'!$M:$M,'2023-01'!$E:$E,Trésorerie!R$4,'2023-01'!$F:$F,Trésorerie!$B15)+SUMIFS('2023-01'!$N:$N,'2023-01'!$E:$E,Trésorerie!R$4,'2023-01'!$F:$F,Trésorerie!$B15) -> 0 | S15: =-SUMIFS('2023-02'!$M:$M,'2023-02'!$E:$E,Trésorerie!S$4,'2023-02'!$F:$F,Trésorerie!$B15)+SUMIFS('2023-02'!$N:$N,'2023-02'!$E:$E,Trésorerie!S$4,'2023-02'!$F:$F,Trésorerie!$B15) -> 0 | T15: =-SUMIFS('2023-03'!$M:$M,'2023-03'!$E:$E,Trésorerie!T$4,'2023-03'!$F:$F,Trésorerie!$B15)+SUMIFS('2023-03'!$N:$N,'2023-03'!$E:$E,Trésorerie!T$4,'2023-03'!$F:$F,Trésorerie!$B15) -> 14695.16 | U15: =-SUMIFS('2023-04'!$M:$M,'2023-04'!$E:$E,Trésorerie!U$4,'2023-04'!$F:$F,Trésorerie!$B15)+SUMIFS('2023-04'!$N:$N,'2023-04'!$E:$E,Trésorerie!U$4,'2023-04'!$F:$F,Trésorerie!$B15) -> 0 | V15: =-SUMIFS('2023-05'!$M:$M,'2023-05'!$E:$E,Trésorerie!V$4,'2023-05'!$F:$F,Trésorerie!$B15)+SUMIFS('2023-05'!$N:$N,'2023-05'!$E:$E,Trésorerie!V$4,'2023-05'!$F:$F,Trésorerie!$B15) -> 0 | W15: =-SUMIFS('2023-06'!$M:$M,'2023-06'!$E:$E,Trésorerie!W$4,'2023-06'!$F:$F,Trésorerie!$B15)+SUMIFS('2023-06'!$N:$N,'2023-06'!$E:$E,Trésorerie!W$4,'2023-06'!$F:$F,Trésorerie!$B15) -> 6291.27 | X15: =-SUMIFS('2023-07'!$M:$M,'2023-07'!$E:$E,Trésorerie!X$4,'2023-07'!$F:$F,Trésorerie!$B15)+SUMIFS('2023-07'!$N:$N,'2023-07'!$E:$E,Trésorerie!X$4,'2023-07'!$F:$F,Trésorerie!$B15) -> 0 | Y15: =-SUMIFS('2023-08'!$M:$M,'2023-08'!$E:$E,Trésorerie!Y$4,'2023-08'!$F:$F,Trésorerie!$B15)+SUMIFS('2023-08'!$N:$N,'2023-08'!$E:$E,Trésorerie!Y$4,'2023-08'!$F:$F,Trésorerie!$B15) -> 0 | Z15: =-SUMIFS('2023-09'!$M:$M,'2023-09'!$E:$E,Trésorerie!Z$4,'2023-09'!$F:$F,Trésorerie!$B15)+SUMIFS('2023-09'!$N:$N,'2023-09'!$E:$E,Trésorerie!Z$4,'2023-09'!$F:$F,Trésorerie!$B15) -> 6111.21 | AA15: =-SUMIFS('2023-10'!$M:$M,'2023-10'!$E:$E,Trésorerie!AA$4,'2023-10'!$F:$F,Trésorerie!$B15)+SUMIFS('2023-10'!$N:$N,'2023-10'!$E:$E,Trésorerie!AA$4,'2023-10'!$F:$F,Trésorerie!$B15) -> 0 | AB15: =IF(SUM($E15:O15)>SUM($R15:AA15),SUM($E15:O15)-SUM($R15:AA15),0) -> 5074.36 | AC15: =IF(SUM($E15:P15)>SUM($R15:AB15),SUM($E15:P15)-SUM($R15:AB15),0) -> 0
A16: =SUM(E16:P16) -> 29719.63 | B16: 411100 | C16: COMPTE GESTION ADHERENTS | D16: Entrée | E16: =-SUMIFS('2022'!$M:$M,'2022'!$E:$E,Trésorerie!E$4,'2022'!$F:$F,Trésorerie!$B16)+SUMIFS('2022'!$N:$N,'2022'!$E:$E,Trésorerie!E$4,'2022'!$F:$F,Trésorerie!$B16) -> 2108.45 | F16: =-SUMIFS('2022'!$M:$M,'2022'!$E:$E,Trésorerie!F$4,'2022'!$F:$F,Trésorerie!$B16)+SUMIFS('2022'!$N:$N,'2022'!$E:$E,Trésorerie!F$4,'2022'!$F:$F,Trésorerie!$B16) -> 2682.07 | G16: =-SUMIFS('2022'!$M:$M,'2022'!$E:$E,Trésorerie!G$4,'2022'!$F:$F,Trésorerie!$B16)+SUMIFS('2022'!$N:$N,'2022'!$E:$E,Trésorerie!G$4,'2022'!$F:$F,Trésorerie!$B16) -> 2694.17 | H16: =-SUMIFS('2022'!$M:$M,'2022'!$E:$E,Trésorerie!H$4,'2022'!$F:$F,Trésorerie!$B16)+SUMIFS('2022'!$N:$N,'2022'!$E:$E,Trésorerie!H$4,'2022'!$F:$F,Trésorerie!$B16) -> 2398.68 | I16: =-SUMIFS('2022'!$M:$M,'2022'!$E:$E,Trésorerie!I$4,'2022'!$F:$F,Trésorerie!$B16)+SUMIFS('2022'!$N:$N,'2022'!$E:$E,Trésorerie!I$4,'2022'!$F:$F,Trésorerie!$B16) -> 1550.78 | J16: =-SUMIFS('2022'!$M:$M,'2022'!$E:$E,Trésorerie!J$4,'2022'!$F:$F,Trésorerie!$B16)+SUMIFS('2022'!$N:$N,'2022'!$E:$E,Trésorerie!J$4,'2022'!$F:$F,Trésorerie!$B16) -> 3974.71 | K16: =-SUMIFS('2022'!$M:$M,'2022'!$E:$E,Trésorerie!K$4,'2022'!$F:$F,Trésorerie!$B16)+SUMIFS('2022'!$N:$N,'2022'!$E:$E,Trésorerie!K$4,'2022'!$F:$F,Trésorerie!$B16) -> 2352.48 | L16: =-SUMIFS('2022'!$M:$M,'2022'!$E:$E,Trésorerie!L$4,'2022'!$F:$F,Trésorerie!$B16)+SUMIFS('2022'!$N:$N,'2022'!$E:$E,Trésorerie!L$4,'2022'!$F:$F,Trésorerie!$B16) -> 348.89 | ... P16: =-SUMIFS('2022'!$M:$M,'2022'!$E:$E,Trésorerie!P$4,'2022'!$F:$F,Trésorerie!$B16)+SUMIFS('2022'!$N:$N,'2022'!$E:$E,Trésorerie!P$4,'2022'!$F:$F,Trésorerie!$B16) -> 1070.39 | R16: =-SUMIFS('2023-01'!$M:$M,'2023-01'!$E:$E,Trésorerie!R$4,'2023-01'!$F:$F,Trésorerie!$B16)+SUMIFS('2023-01'!$N:$N,'2023-01'!$E:$E,Trésorerie!R$4,'2023-01'!$F:$F,Trésorerie!$B16) -> 4197.01 | S16: =-SUMIFS('2023-02'!$M:$M,'2023-02'!$E:$E,Trésorerie!S$4,'2023-02'!$F:$F,Trésorerie!$B16)+SUMIFS('2023-02'!$N:$N,'2023-02'!$E:$E,Trésorerie!S$4,'2023-02'!$F:$F,Trésorerie!$B16) -> 2177.34 | T16: =-SUMIFS('2023-03'!$M:$M,'2023-03'!$E:$E,Trésorerie!T$4,'2023-03'!$F:$F,Trésorerie!$B16)+SUMIFS('2023-03'!$N:$N,'2023-03'!$E:$E,Trésorerie!T$4,'2023-03'!$F:$F,Trésorerie!$B16) -> 4485.05 | U16: =-SUMIFS('2023-04'!$M:$M,'2023-04'!$E:$E,Trésorerie!U$4,'2023-04'!$F:$F,Trésorerie!$B16)+SUMIFS('2023-04'!$N:$N,'2023-04'!$E:$E,Trésorerie!U$4,'2023-04'!$F:$F,Trésorerie!$B16) -> 2003.89 | V16: =-SUMIFS('2023-05'!$M:$M,'2023-05'!$E:$E,Trésorerie!V$4,'2023-05'!$F:$F,Trésorerie!$B16)+SUMIFS('2023-05'!$N:$N,'2023-05'!$E:$E,Trésorerie!V$4,'2023-05'!$F:$F,Trésorerie!$B16) -> 1651.04 | W16: =-SUMIFS('2023-06'!$M:$M,'2023-06'!$E:$E,Trésorerie!W$4,'2023-06'!$F:$F,Trésorerie!$B16)+SUMIFS('2023-06'!$N:$N,'2023-06'!$E:$E,Trésorerie!W$4,'2023-06'!$F:$F,Trésorerie!$B16) -> 5835.53 | X16: =-SUMIFS('2023-07'!$M:$M,'2023-07'!$E:$E,Trésorerie!X$4,'2023-07'!$F:$F,Trésorerie!$B16)+SUMIFS('2023-07'!$N:$N,'2023-07'!$E:$E,Trésorerie!X$4,'2023-07'!$F:$F,Trésorerie!$B16) -> 3291.56 | Y16: =-SUMIFS('2023-08'!$M:$M,'2023-08'!$E:$E,Trésorerie!Y$4,'2023-08'!$F:$F,Trésorerie!$B16)+SUMIFS('2023-08'!$N:$N,'2023-08'!$E:$E,Trésorerie!Y$4,'2023-08'!$F:$F,Trésorerie!$B16) -> 735.86 | Z16: =-SUMIFS('2023-09'!$M:$M,'2023-09'!$E:$E,Trésorerie!Z$4,'2023-09'!$F:$F,Trésorerie!$B16)+SUMIFS('2023-09'!$N:$N,'2023-09'!$E:$E,Trésorerie!Z$4,'2023-09'!$F:$F,Trésorerie!$B16) -> 4975.37 | AA16: =-SUMIFS('2023-10'!$M:$M,'2023-10'!$E:$E,Trésorerie!AA$4,'2023-10'!$F:$F,Trésorerie!$B16)+SUMIFS('2023-10'!$N:$N,'2023-10'!$E:$E,Trésorerie!AA$4,'2023-10'!$F:$F,Trésorerie!$B16) -> 5709 | AB16: =IF(SUM($E16:O16)>SUM($R16:AA16),SUM($E16:O16)-SUM($R16:AA16),0) -> 0 | AC16: =IF(SUM($E16:P16)>SUM($R16:AB16),SUM($E16:P16)-SUM($R16:AB16),0) -> 0
... A18: =SUM(E18:P18) -> 26900 | B18: 445057 | C18: CAF AUTRES SUBVENTIONS | D18: Entrée | E18: =-SUMIFS('2022'!$M:$M,'2022'!$E:$E,Trésorerie!E$4,'2022'!$F:$F,Trésorerie!$B18)+SUMIFS('2022'!$N:$N,'2022'!$E:$E,Trésorerie!E$4,'2022'!$F:$F,Trésorerie!$B18) -> 0 | F18: =-SUMIFS('2022'!$M:$M,'2022'!$E:$E,Trésorerie!F$4,'2022'!$F:$F,Trésorerie!$B18)+SUMIFS('2022'!$N:$N,'2022'!$E:$E,Trésorerie!F$4,'2022'!$F:$F,Trésorerie!$B18) -> 0 | G18: =-SUMIFS('2022'!$M:$M,'2022'!$E:$E,Trésorerie!G$4,'2022'!$F:$F,Trésorerie!$B18)+SUMIFS('2022'!$N:$N,'2022'!$E:$E,Trésorerie!G$4,'2022'!$F:$F,Trésorerie!$B18) -> 0 | H18: =-SUMIFS('2022'!$M:$M,'2022'!$E:$E,Trésorerie!H$4,'2022'!$F:$F,Trésorerie!$B18)+SUMIFS('2022'!$N:$N,'2022'!$E:$E,Trésorerie!H$4,'2022'!$F:$F,Trésorerie!$B18) -> 6900 | I18: =-SUMIFS('2022'!$M:$M,'2022'!$E:$E,Trésorerie!I$4,'2022'!$F:$F,Trésorerie!$B18)+SUMIFS('2022'!$N:$N,'2022'!$E:$E,Trésorerie!I$4,'2022'!$F:$F,Trésorerie!$B18) -> 0 | J18: =-SUMIFS('2022'!$M:$M,'2022'!$E:$E,Trésorerie!J$4,'2022'!$F:$F,Trésorerie!$B18)+SUMIFS('2022'!$N:$N,'2022'!$E:$E,Trésorerie!J$4,'2022'!$F:$F,Trésorerie!$B18) -> 0 | K18: =-SUMIFS('2022'!$M:$M,'2022'!$E:$E,Trésorerie!K$4,'2022'!$F:$F,Trésorerie!$B18)+SUMIFS('2022'!$N:$N,'2022'!$E:$E,Trésorerie!K$4,'2022'!$F:$F,Trésorerie!$B18) -> 20000 | L18: =-SUMIFS('2022'!$M:$M,'2022'!$E:$E,Trésorerie!L$4,'2022'!$F:$F,Trésorerie!$B18)+SUMIFS('2022'!$N:$N,'2022'!$E:$E,Trésorerie!L$4,'2022'!$F:$F,Trésorerie!$B18) -> 0 | ... P18: =-SUMIFS('2022'!$M:$M,'2022'!$E:$E,Trésorerie!P$4,'2022'!$F:$F,Trésorerie!$B18)+SUMIFS('2022'!$N:$N,'2022'!$E:$E,Trésorerie!P$4,'2022'!$F:$F,Trésorerie!$B18) -> 0 | R18: =-SUMIFS('2023-01'!$M:$M,'2023-01'!$E:$E,Trésorerie!R$4,'2023-01'!$F:$F,Trésorerie!$B18)+SUMIFS('2023-01'!$N:$N,'2023-01'!$E:$E,Trésorerie!R$4,'2023-01'!$F:$F,Trésorerie!$B18) -> 0 | S18: =-SUMIFS('2023-02'!$M:$M,'2023-02'!$E:$E,Trésorerie!S$4,'2023-02'!$F:$F,Trésorerie!$B18)+SUMIFS('2023-02'!$N:$N,'2023-02'!$E:$E,Trésorerie!S$4,'2023-02'!$F:$F,Trésorerie!$B18) -> 0 | T18: =-SUMIFS('2023-03'!$M:$M,'2023-03'!$E:$E,Trésorerie!T$4,'2023-03'!$F:$F,Trésorerie!$B18)+SUMIFS('2023-03'!$N:$N,'2023-03'!$E:$E,Trésorerie!T$4,'2023-03'!$F:$F,Trésorerie!$B18) -> 0 | U18: =-SUMIFS('2023-04'!$M:$M,'2023-04'!$E:$E,Trésorerie!U$4,'2023-04'!$F:$F,Trésorerie!$B18)+SUMIFS('2023-04'!$N:$N,'2023-04'!$E:$E,Trésorerie!U$4,'2023-04'!$F:$F,Trésorerie!$B18) -> 0 | V18: =-SUMIFS('2023-05'!$M:$M,'2023-05'!$E:$E,Trésorerie!V$4,'2023-05'!$F:$F,Trésorerie!$B18)+SUMIFS('2023-05'!$N:$N,'2023-05'!$E:$E,Trésorerie!V$4,'2023-05'!$F:$F,Trésorerie!$B18) -> 0 | W18: =-SUMIFS('2023-06'!$M:$M,'2023-06'!$E:$E,Trésorerie!W$4,'2023-06'!$F:$F,Trésorerie!$B18)+SUMIFS('2023-06'!$N:$N,'2023-06'!$E:$E,Trésorerie!W$4,'2023-06'!$F:$F,Trésorerie!$B18) -> 0 | X18: =-SUMIFS('2023-07'!$M:$M,'2023-07'!$E:$E,Trésorerie!X$4,'2023-07'!$F:$F,Trésorerie!$B18)+SUMIFS('2023-07'!$N:$N,'2023-07'!$E:$E,Trésorerie!X$4,'2023-07'!$F:$F,Trésorerie!$B18) -> 0 | Y18: =-SUMIFS('2023-08'!$M:$M,'2023-08'!$E:$E,Trésorerie!Y$4,'2023-08'!$F:$F,Trésorerie!$B18)+SUMIFS('2023-08'!$N:$N,'2023-08'!$E:$E,Trésorerie!Y$4,'2023-08'!$F:$F,Trésorerie!$B18) -> 0 | Z18: =-SUMIFS('2023-09'!$M:$M,'2023-09'!$E:$E,Trésorerie!Z$4,'2023-09'!$F:$F,Trésorerie!$B18)+SUMIFS('2023-09'!$N:$N,'2023-09'!$E:$E,Trésorerie!Z$4,'2023-09'!$F:$F,Trésorerie!$B18) -> 0 | AA18: =-SUMIFS('2023-10'!$M:$M,'2023-10'!$E:$E,Trésorerie!AA$4,'2023-10'!$F:$F,Trésorerie!$B18)+SUMIFS('2023-10'!$N:$N,'2023-10'!$E:$E,Trésorerie!AA$4,'2023-10'!$F:$F,Trésorerie!$B18) -> 0 | AB18: =IF(SUM($E18:O18)>SUM($R18:AA18),SUM($E18:O18)-SUM($R18:AA18),0) -> 26900 | AC18: =IF(SUM($E18:P18)>SUM($R18:AB18),SUM($E18:P18)-SUM($R18:AB18),0) -> 0
A19: 0 | B19: 445040 | C19: CAF CTG | D19: Entrée | E19: 0 | F19: 0 | G19: 0 | H19: 0 | I19: 0 | J19: 0 | K19: 0 | L19: 0 | M19: 0 | N19: 0 | O19: 0 | P19: 0 | R19: =-SUMIFS('2023-01'!$M:$M,'2023-01'!$E:$E,Trésorerie!R$4,'2023-01'!$F:$F,Trésorerie!$B19)+SUMIFS('2023-01'!$N:$N,'2023-01'!$E:$E,Trésorerie!R$4,'2023-01'!$F:$F,Trésorerie!$B19) -> 0 | S19: =-SUMIFS('2023-02'!$M:$M,'2023-02'!$E:$E,Trésorerie!S$4,'2023-02'!$F:$F,Trésorerie!$B19)+SUMIFS('2023-02'!$N:$N,'2023-02'!$E:$E,Trésorerie!S$4,'2023-02'!$F:$F,Trésorerie!$B19) -> 0 | T19: =-SUMIFS('2023-03'!$M:$M,'2023-03'!$E:$E,Trésorerie!T$4,'2023-03'!$F:$F,Trésorerie!$B19)+SUMIFS('2023-03'!$N:$N,'2023-03'!$E:$E,Trésorerie!T$4,'2023-03'!$F:$F,Trésorerie!$B19) -> 0 | U19: =-SUMIFS('2023-04'!$M:$M,'2023-04'!$E:$E,Trésorerie!U$4,'2023-04'!$F:$F,Trésorerie!$B19)+SUMIFS('2023-04'!$N:$N,'2023-04'!$E:$E,Trésorerie!U$4,'2023-04'!$F:$F,Trésorerie!$B19) -> 0 | V19: =-SUMIFS('2023-05'!$M:$M,'2023-05'!$E:$E,Trésorerie!V$4,'2023-05'!$F:$F,Trésorerie!$B19)+SUMIFS('2023-05'!$N:$N,'2023-05'!$E:$E,Trésorerie!V$4,'2023-05'!$F:$F,Trésorerie!$B19) -> 0 | W19: =-SUMIFS('2023-06'!$M:$M,'2023-06'!$E:$E,Trésorerie!W$4,'2023-06'!$F:$F,Trésorerie!$B19)+SUMIFS('2023-06'!$N:$N,'2023-06'!$E:$E,Trésorerie!W$4,'2023-06'!$F:$F,Trésorerie!$B19) -> 0 | X19: =-SUMIFS('2023-07'!$M:$M,'2023-07'!$E:$E,Trésorerie!X$4,'2023-07'!$F:$F,Trésorerie!$B19)+SUMIFS('2023-07'!$N:$N,'2023-07'!$E:$E,Trésorerie!X$4,'2023-07'!$F:$F,Trésorerie!$B19) -> 0 | Y19: =-SUMIFS('2023-08'!$M:$M,'2023-08'!$E:$E,Trésorerie!Y$4,'2023-08'!$F:$F,Trésorerie!$B19)+SUMIFS('2023-08'!$N:$N,'2023-08'!$E:$E,Trésorerie!Y$4,'2023-08'!$F:$F,Trésorerie!$B19) -> 0 | Z19: =-SUMIFS('2023-09'!$M:$M,'2023-09'!$E:$E,Trésorerie!Z$4,'2023-09'!$F:$F,Trésorerie!$B19)+SUMIFS('2023-09'!$N:$N,'2023-09'!$E:$E,Trésorerie!Z$4,'2023-09'!$F:$F,Trésorerie!$B19) -> 17163.72 | AA19: =-SUMIFS('2023-10'!$M:$M,'2023-10'!$E:$E,Trésorerie!AA$4,'2023-10'!$F:$F,Trésorerie!$B19)+SUMIFS('2023-10'!$N:$N,'2023-10'!$E:$E,Trésorerie!AA$4,'2023-10'!$F:$F,Trésorerie!$B19) -> 0 | AB19: =IF(SUM($E19:O19)>SUM($R19:AA19),SUM($E19:O19)-SUM($R19:AA19),0) -> 0 | AC19: =IF(SUM($E19:P19)>SUM($R19:AB19),SUM($E19:P19)-SUM($R19:AB19),0) -> 0
A20: =SUM(E20:P20) -> 16596.45 | B20: 791100 | C20: TRANSFERT CHARGES UNIFORMATION | D20: Entrée | E20: =-SUMIFS('2022'!$M:$M,'2022'!$E:$E,Trésorerie!E$4,'2022'!$F:$F,Trésorerie!$B20)+SUMIFS('2022'!$N:$N,'2022'!$E:$E,Trésorerie!E$4,'2022'!$F:$F,Trésorerie!$B20) -> 0 | F20: =-SUMIFS('2022'!$M:$M,'2022'!$E:$E,Trésorerie!F$4,'2022'!$F:$F,Trésorerie!$B20)+SUMIFS('2022'!$N:$N,'2022'!$E:$E,Trésorerie!F$4,'2022'!$F:$F,Trésorerie!$B20) -> 0 | G20: =-SUMIFS('2022'!$M:$M,'2022'!$E:$E,Trésorerie!G$4,'2022'!$F:$F,Trésorerie!$B20)+SUMIFS('2022'!$N:$N,'2022'!$E:$E,Trésorerie!G$4,'2022'!$F:$F,Trésorerie!$B20) -> 3384 | H20: =-SUMIFS('2022'!$M:$M,'2022'!$E:$E,Trésorerie!H$4,'2022'!$F:$F,Trésorerie!$B20)+SUMIFS('2022'!$N:$N,'2022'!$E:$E,Trésorerie!H$4,'2022'!$F:$F,Trésorerie!$B20) -> 0 | I20: =-SUMIFS('2022'!$M:$M,'2022'!$E:$E,Trésorerie!I$4,'2022'!$F:$F,Trésorerie!$B20)+SUMIFS('2022'!$N:$N,'2022'!$E:$E,Trésorerie!I$4,'2022'!$F:$F,Trésorerie!$B20) -> 345 | J20: =-SUMIFS('2022'!$M:$M,'2022'!$E:$E,Trésorerie!J$4,'2022'!$F:$F,Trésorerie!$B20)+SUMIFS('2022'!$N:$N,'2022'!$E:$E,Trésorerie!J$4,'2022'!$F:$F,Trésorerie!$B20) -> 2399.45 | K20: =-SUMIFS('2022'!$M:$M,'2022'!$E:$E,Trésorerie!K$4,'2022'!$F:$F,Trésorerie!$B20)+SUMIFS('2022'!$N:$N,'2022'!$E:$E,Trésorerie!K$4,'2022'!$F:$F,Trésorerie!$B20) -> 1960 | L20: =-SUMIFS('2022'!$M:$M,'2022'!$E:$E,Trésorerie!L$4,'2022'!$F:$F,Trésorerie!$B20)+SUMIFS('2022'!$N:$N,'2022'!$E:$E,Trésorerie!L$4,'2022'!$F:$F,Trésorerie!$B20) -> 438 | ... P20: =-SUMIFS('2022'!$M:$M,'2022'!$E:$E,Trésorerie!P$4,'2022'!$F:$F,Trésorerie!$B20)+SUMIFS('2022'!$N:$N,'2022'!$E:$E,Trésorerie!P$4,'2022'!$F:$F,Trésorerie!$B20) -> 0 | R20: =-SUMIFS('2023-01'!$M:$M,'2023-01'!$E:$E,Trésorerie!R$4,'2023-01'!$F:$F,Trésorerie!$B20)+SUMIFS('2023-01'!$N:$N,'2023-01'!$E:$E,Trésorerie!R$4,'2023-01'!$F:$F,Trésorerie!$B20) -> 5076 | S20: =-SUMIFS('2023-02'!$M:$M,'2023-02'!$E:$E,Trésorerie!S$4,'2023-02'!$F:$F,Trésorerie!$B20)+SUMIFS('2023-02'!$N:$N,'2023-02'!$E:$E,Trésorerie!S$4,'2023-02'!$F:$F,Trésorerie!$B20) -> 0 | T20: =-SUMIFS('2023-03'!$M:$M,'2023-03'!$E:$E,Trésorerie!T$4,'2023-03'!$F:$F,Trésorerie!$B20)+SUMIFS('2023-03'!$N:$N,'2023-03'!$E:$E,Trésorerie!T$4,'2023-03'!$F:$F,Trésorerie!$B20) -> 4663 | U20: =-SUMIFS('2023-04'!$M:$M,'2023-04'!$E:$E,Trésorerie!U$4,'2023-04'!$F:$F,Trésorerie!$B20)+SUMIFS('2023-04'!$N:$N,'2023-04'!$E:$E,Trésorerie!U$4,'2023-04'!$F:$F,Trésorerie!$B20) -> 0 | V20: =-SUMIFS('2023-05'!$M:$M,'2023-05'!$E:$E,Trésorerie!V$4,'2023-05'!$F:$F,Trésorerie!$B20)+SUMIFS('2023-05'!$N:$N,'2023-05'!$E:$E,Trésorerie!V$4,'2023-05'!$F:$F,Trésorerie!$B20) -> 0 | W20: =-SUMIFS('2023-06'!$M:$M,'2023-06'!$E:$E,Trésorerie!W$4,'2023-06'!$F:$F,Trésorerie!$B20)+SUMIFS('2023-06'!$N:$N,'2023-06'!$E:$E,Trésorerie!W$4,'2023-06'!$F:$F,Trésorerie!$B20) -> 390 | X20: =-SUMIFS('2023-07'!$M:$M,'2023-07'!$E:$E,Trésorerie!X$4,'2023-07'!$F:$F,Trésorerie!$B20)+SUMIFS('2023-07'!$N:$N,'2023-07'!$E:$E,Trésorerie!X$4,'2023-07'!$F:$F,Trésorerie!$B20) -> 0 | Y20: =-SUMIFS('2023-08'!$M:$M,'2023-08'!$E:$E,Trésorerie!Y$4,'2023-08'!$F:$F,Trésorerie!$B20)+SUMIFS('2023-08'!$N:$N,'2023-08'!$E:$E,Trésorerie!Y$4,'2023-08'!$F:$F,Trésorerie!$B20) -> 0 | Z20: =-SUMIFS('2023-09'!$M:$M,'2023-09'!$E:$E,Trésorerie!Z$4,'2023-09'!$F:$F,Trésorerie!$B20)+SUMIFS('2023-09'!$N:$N,'2023-09'!$E:$E,Trésorerie!Z$4,'2023-09'!$F:$F,Trésorerie!$B20) -> 0 | AA20: =-SUMIFS('2023-10'!$M:$M,'2023-10'!$E:$E,Trésorerie!AA$4,'2023-10'!$F:$F,Trésorerie!$B20)+SUMIFS('2023-10'!$N:$N,'2023-10'!$E:$E,Trésorerie!AA$4,'2023-10'!$F:$F,Trésorerie!$B20) -> 0 | AB20: =IF(SUM($E20:O20)>SUM($R20:AA20),SUM($E20:O20)-SUM($R20:AA20),0) -> 6467.45 | AC20: =IF(SUM($E20:P20)>SUM($R20:AB20),SUM($E20:P20)-SUM($R20:AB20),0) -> 0
A21: =SUM(E21:P21) -> 9487.7 | B21: 411010 | C21: COLLECTIF CLIENTS BABILHOME | D21: Entrée | E21: =-SUMIFS('2022'!$M:$M,'2022'!$E:$E,Trésorerie!E$4,'2022'!$F:$F,Trésorerie!$B21)+SUMIFS('2022'!$N:$N,'2022'!$E:$E,Trésorerie!E$4,'2022'!$F:$F,Trésorerie!$B21) -> 537.28 | F21: =-SUMIFS('2022'!$M:$M,'2022'!$E:$E,Trésorerie!F$4,'2022'!$F:$F,Trésorerie!$B21)+SUMIFS('2022'!$N:$N,'2022'!$E:$E,Trésorerie!F$4,'2022'!$F:$F,Trésorerie!$B21) -> 854.38 | G21: =-SUMIFS('2022'!$M:$M,'2022'!$E:$E,Trésorerie!G$4,'2022'!$F:$F,Trésorerie!$B21)+SUMIFS('2022'!$N:$N,'2022'!$E:$E,Trésorerie!G$4,'2022'!$F:$F,Trésorerie!$B21) -> 765.8 | H21: =-SUMIFS('2022'!$M:$M,'2022'!$E:$E,Trésorerie!H$4,'2022'!$F:$F,Trésorerie!$B21)+SUMIFS('2022'!$N:$N,'2022'!$E:$E,Trésorerie!H$4,'2022'!$F:$F,Trésorerie!$B21) -> 1085.43 | I21: =-SUMIFS('2022'!$M:$M,'2022'!$E:$E,Trésorerie!I$4,'2022'!$F:$F,Trésorerie!$B21)+SUMIFS('2022'!$N:$N,'2022'!$E:$E,Trésorerie!I$4,'2022'!$F:$F,Trésorerie!$B21) -> 933.93 | J21: =-SUMIFS('2022'!$M:$M,'2022'!$E:$E,Trésorerie!J$4,'2022'!$F:$F,Trésorerie!$B21)+SUMIFS('2022'!$N:$N,'2022'!$E:$E,Trésorerie!J$4,'2022'!$F:$F,Trésorerie!$B21) -> 808.06 | K21: =-SUMIFS('2022'!$M:$M,'2022'!$E:$E,Trésorerie!K$4,'2022'!$F:$F,Trésorerie!$B21)+SUMIFS('2022'!$N:$N,'2022'!$E:$E,Trésorerie!K$4,'2022'!$F:$F,Trésorerie!$B21) -> 556.99 | L21: =-SUMIFS('2022'!$M:$M,'2022'!$E:$E,Trésorerie!L$4,'2022'!$F:$F,Trésorerie!$B21)+SUMIFS('2022'!$N:$N,'2022'!$E:$E,Trésorerie!L$4,'2022'!$F:$F,Trésorerie!$B21) -> 362 | ... P21: =-SUMIFS('2022'!$M:$M,'2022'!$E:$E,Trésorerie!P$4,'2022'!$F:$F,Trésorerie!$B21)+SUMIFS('2022'!$N:$N,'2022'!$E:$E,Trésorerie!P$4,'2022'!$F:$F,Trésorerie!$B21) -> 1392.31 | R21: =-SUMIFS('2023-01'!$M:$M,'2023-01'!$E:$E,Trésorerie!R$4,'2023-01'!$F:$F,Trésorerie!$B21)+SUMIFS('2023-01'!$N:$N,'2023-01'!$E:$E,Trésorerie!R$4,'2023-01'!$F:$F,Trésorerie!$B21) -> 1509.75 | S21: =-SUMIFS('2023-02'!$M:$M,'2023-02'!$E:$E,Trésorerie!S$4,'2023-02'!$F:$F,Trésorerie!$B21)+SUMIFS('2023-02'!$N:$N,'2023-02'!$E:$E,Trésorerie!S$4,'2023-02'!$F:$F,Trésorerie!$B21) -> 1269.76 | T21: =-SUMIFS('2023-03'!$M:$M,'2023-03'!$E:$E,Trésorerie!T$4,'2023-03'!$F:$F,Trésorerie!$B21)+SUMIFS('2023-03'!$N:$N,'2023-03'!$E:$E,Trésorerie!T$4,'2023-03'!$F:$F,Trésorerie!$B21) -> 842.76 | U21: =-SUMIFS('2023-04'!$M:$M,'2023-04'!$E:$E,Trésorerie!U$4,'2023-04'!$F:$F,Trésorerie!$B21)+SUMIFS('2023-04'!$N:$N,'2023-04'!$E:$E,Trésorerie!U$4,'2023-04'!$F:$F,Trésorerie!$B21) -> 2264.86 | V21: =-SUMIFS('2023-05'!$M:$M,'2023-05'!$E:$E,Trésorerie!V$4,'2023-05'!$F:$F,Trésorerie!$B21)+SUMIFS('2023-05'!$N:$N,'2023-05'!$E:$E,Trésorerie!V$4,'2023-05'!$F:$F,Trésorerie!$B21) -> 928.22 | W21: =-SUMIFS('2023-06'!$M:$M,'2023-06'!$E:$E,Trésorerie!W$4,'2023-06'!$F:$F,Trésorerie!$B21)+SUMIFS('2023-06'!$N:$N,'2023-06'!$E:$E,Trésorerie!W$4,'2023-06'!$F:$F,Trésorerie!$B21) -> 4158.73 | X21: =-SUMIFS('2023-07'!$M:$M,'2023-07'!$E:$E,Trésorerie!X$4,'2023-07'!$F:$F,Trésorerie!$B21)+SUMIFS('2023-07'!$N:$N,'2023-07'!$E:$E,Trésorerie!X$4,'2023-07'!$F:$F,Trésorerie!$B21) -> 1833.4 | Y21: =-SUMIFS('2023-08'!$M:$M,'2023-08'!$E:$E,Trésorerie!Y$4,'2023-08'!$F:$F,Trésorerie!$B21)+SUMIFS('2023-08'!$N:$N,'2023-08'!$E:$E,Trésorerie!Y$4,'2023-08'!$F:$F,Trésorerie!$B21) -> 1572.49 | Z21: =-SUMIFS('2023-09'!$M:$M,'2023-09'!$E:$E,Trésorerie!Z$4,'2023-09'!$F:$F,Trésorerie!$B21)+SUMIFS('2023-09'!$N:$N,'2023-09'!$E:$E,Trésorerie!Z$4,'2023-09'!$F:$F,Trésorerie!$B21) -> 815.68 | AA21: =-SUMIFS('2023-10'!$M:$M,'2023-10'!$E:$E,Trésorerie!AA$4,'2023-10'!$F:$F,Trésorerie!$B21)+SUMIFS('2023-10'!$N:$N,'2023-10'!$E:$E,Trésorerie!AA$4,'2023-10'!$F:$F,Trésorerie!$B21) -> 2167.14 | AB21: =IF(SUM($E21:O21)>SUM($R21:AA21),SUM($E21:O21)-SUM($R21:AA21),0) -> 0 | AC21: =IF(SUM($E21:P21)>SUM($R21:AB21),SUM($E21:P21)-SUM($R21:AB21),0) -> 0
A22: =SUM(E22:P22) -> 9150.67 | B22: 706237 | C22: CAF PS CLAS | D22: Entrée | E22: =-SUMIFS('2022'!$M:$M,'2022'!$E:$E,Trésorerie!E$4,'2022'!$F:$F,Trésorerie!$B22)+SUMIFS('2022'!$N:$N,'2022'!$E:$E,Trésorerie!E$4,'2022'!$F:$F,Trésorerie!$B22) -> 0 | F22: =-SUMIFS('2022'!$M:$M,'2022'!$E:$E,Trésorerie!F$4,'2022'!$F:$F,Trésorerie!$B22)+SUMIFS('2022'!$N:$N,'2022'!$E:$E,Trésorerie!F$4,'2022'!$F:$F,Trésorerie!$B22) -> 0 | G22: =-SUMIFS('2022'!$M:$M,'2022'!$E:$E,Trésorerie!G$4,'2022'!$F:$F,Trésorerie!$B22)+SUMIFS('2022'!$N:$N,'2022'!$E:$E,Trésorerie!G$4,'2022'!$F:$F,Trésorerie!$B22) -> 0 | H22: =-SUMIFS('2022'!$M:$M,'2022'!$E:$E,Trésorerie!H$4,'2022'!$F:$F,Trésorerie!$B22)+SUMIFS('2022'!$N:$N,'2022'!$E:$E,Trésorerie!H$4,'2022'!$F:$F,Trésorerie!$B22) -> 0 | I22: =-SUMIFS('2022'!$M:$M,'2022'!$E:$E,Trésorerie!I$4,'2022'!$F:$F,Trésorerie!$B22)+SUMIFS('2022'!$N:$N,'2022'!$E:$E,Trésorerie!I$4,'2022'!$F:$F,Trésorerie!$B22) -> 0 | J22: =-SUMIFS('2022'!$M:$M,'2022'!$E:$E,Trésorerie!J$4,'2022'!$F:$F,Trésorerie!$B22)+SUMIFS('2022'!$N:$N,'2022'!$E:$E,Trésorerie!J$4,'2022'!$F:$F,Trésorerie!$B22) -> 0 | K22: =-SUMIFS('2022'!$M:$M,'2022'!$E:$E,Trésorerie!K$4,'2022'!$F:$F,Trésorerie!$B22)+SUMIFS('2022'!$N:$N,'2022'!$E:$E,Trésorerie!K$4,'2022'!$F:$F,Trésorerie!$B22) -> 0 | L22: =-SUMIFS('2022'!$M:$M,'2022'!$E:$E,Trésorerie!L$4,'2022'!$F:$F,Trésorerie!$B22)+SUMIFS('2022'!$N:$N,'2022'!$E:$E,Trésorerie!L$4,'2022'!$F:$F,Trésorerie!$B22) -> 0 | ... P22: =-SUMIFS('2022'!$M:$M,'2022'!$E:$E,Trésorerie!P$4,'2022'!$F:$F,Trésorerie!$B22)+SUMIFS('2022'!$N:$N,'2022'!$E:$E,Trésorerie!P$4,'2022'!$F:$F,Trésorerie!$B22) -> 3211.74 | R22: =-SUMIFS('2023-01'!$M:$M,'2023-01'!$E:$E,Trésorerie!R$4,'2023-01'!$F:$F,Trésorerie!$B22)+SUMIFS('2023-01'!$N:$N,'2023-01'!$E:$E,Trésorerie!R$4,'2023-01'!$F:$F,Trésorerie!$B22) -> 0 | S22: =-SUMIFS('2023-02'!$M:$M,'2023-02'!$E:$E,Trésorerie!S$4,'2023-02'!$F:$F,Trésorerie!$B22)+SUMIFS('2023-02'!$N:$N,'2023-02'!$E:$E,Trésorerie!S$4,'2023-02'!$F:$F,Trésorerie!$B22) -> 4817.61 | T22: =-SUMIFS('2023-03'!$M:$M,'2023-03'!$E:$E,Trésorerie!T$4,'2023-03'!$F:$F,Trésorerie!$B22)+SUMIFS('2023-03'!$N:$N,'2023-03'!$E:$E,Trésorerie!T$4,'2023-03'!$F:$F,Trésorerie!$B22) -> 0 | U22: =-SUMIFS('2023-04'!$M:$M,'2023-04'!$E:$E,Trésorerie!U$4,'2023-04'!$F:$F,Trésorerie!$B22)+SUMIFS('2023-04'!$N:$N,'2023-04'!$E:$E,Trésorerie!U$4,'2023-04'!$F:$F,Trésorerie!$B22) -> 0 | V22: =-SUMIFS('2023-05'!$M:$M,'2023-05'!$E:$E,Trésorerie!V$4,'2023-05'!$F:$F,Trésorerie!$B22)+SUMIFS('2023-05'!$N:$N,'2023-05'!$E:$E,Trésorerie!V$4,'2023-05'!$F:$F,Trésorerie!$B22) -> 0 | W22: =-SUMIFS('2023-06'!$M:$M,'2023-06'!$E:$E,Trésorerie!W$4,'2023-06'!$F:$F,Trésorerie!$B22)+SUMIFS('2023-06'!$N:$N,'2023-06'!$E:$E,Trésorerie!W$4,'2023-06'!$F:$F,Trésorerie!$B22) -> 0 | X22: =-SUMIFS('2023-07'!$M:$M,'2023-07'!$E:$E,Trésorerie!X$4,'2023-07'!$F:$F,Trésorerie!$B22)+SUMIFS('2023-07'!$N:$N,'2023-07'!$E:$E,Trésorerie!X$4,'2023-07'!$F:$F,Trésorerie!$B22) -> 0 | Y22: =-SUMIFS('2023-08'!$M:$M,'2023-08'!$E:$E,Trésorerie!Y$4,'2023-08'!$F:$F,Trésorerie!$B22)+SUMIFS('2023-08'!$N:$N,'2023-08'!$E:$E,Trésorerie!Y$4,'2023-08'!$F:$F,Trésorerie!$B22) -> 0 | Z22: =-SUMIFS('2023-09'!$M:$M,'2023-09'!$E:$E,Trésorerie!Z$4,'2023-09'!$F:$F,Trésorerie!$B22)+SUMIFS('2023-09'!$N:$N,'2023-09'!$E:$E,Trésorerie!Z$4,'2023-09'!$F:$F,Trésorerie!$B22) -> 0 | AA22: =-SUMIFS('2023-10'!$M:$M,'2023-10'!$E:$E,Trésorerie!AA$4,'2023-10'!$F:$F,Trésorerie!$B22)+SUMIFS('2023-10'!$N:$N,'2023-10'!$E:$E,Trésorerie!AA$4,'2023-10'!$F:$F,Trésorerie!$B22) -> 3014.19 | AB22: =IF(SUM($E22:O22)>SUM($R22:AA22),SUM($E22:O22)-SUM($R22:AA22),0) -> 0 | AC22: =IF(SUM($E22:P22)>SUM($R22:AB22),SUM($E22:P22)-SUM($R22:AB22),0) -> 1318.87
A23: =SUM(E23:P23) -> 7115.26 | B23: 411020 | C23: COLLECTIF CLIENTS GRIBOUILLE | D23: Entrée | E23: =-SUMIFS('2022'!$M:$M,'2022'!$E:$E,Trésorerie!E$4,'2022'!$F:$F,Trésorerie!$B23)+SUMIFS('2022'!$N:$N,'2022'!$E:$E,Trésorerie!E$4,'2022'!$F:$F,Trésorerie!$B23) -> 580.95 | F23: =-SUMIFS('2022'!$M:$M,'2022'!$E:$E,Trésorerie!F$4,'2022'!$F:$F,Trésorerie!$B23)+SUMIFS('2022'!$N:$N,'2022'!$E:$E,Trésorerie!F$4,'2022'!$F:$F,Trésorerie!$B23) -> 805.56 | G23: =-SUMIFS('2022'!$M:$M,'2022'!$E:$E,Trésorerie!G$4,'2022'!$F:$F,Trésorerie!$B23)+SUMIFS('2022'!$N:$N,'2022'!$E:$E,Trésorerie!G$4,'2022'!$F:$F,Trésorerie!$B23) -> 711.9 | H23: =-SUMIFS('2022'!$M:$M,'2022'!$E:$E,Trésorerie!H$4,'2022'!$F:$F,Trésorerie!$B23)+SUMIFS('2022'!$N:$N,'2022'!$E:$E,Trésorerie!H$4,'2022'!$F:$F,Trésorerie!$B23) -> 583 | I23: =-SUMIFS('2022'!$M:$M,'2022'!$E:$E,Trésorerie!I$4,'2022'!$F:$F,Trésorerie!$B23)+SUMIFS('2022'!$N:$N,'2022'!$E:$E,Trésorerie!I$4,'2022'!$F:$F,Trésorerie!$B23) -> 491.9 | J23: =-SUMIFS('2022'!$M:$M,'2022'!$E:$E,Trésorerie!J$4,'2022'!$F:$F,Trésorerie!$B23)+SUMIFS('2022'!$N:$N,'2022'!$E:$E,Trésorerie!J$4,'2022'!$F:$F,Trésorerie!$B23) -> 681.69 | K23: =-SUMIFS('2022'!$M:$M,'2022'!$E:$E,Trésorerie!K$4,'2022'!$F:$F,Trésorerie!$B23)+SUMIFS('2022'!$N:$N,'2022'!$E:$E,Trésorerie!K$4,'2022'!$F:$F,Trésorerie!$B23) -> 906.5 | L23: =-SUMIFS('2022'!$M:$M,'2022'!$E:$E,Trésorerie!L$4,'2022'!$F:$F,Trésorerie!$B23)+SUMIFS('2022'!$N:$N,'2022'!$E:$E,Trésorerie!L$4,'2022'!$F:$F,Trésorerie!$B23) -> 0 | ... P23: =-SUMIFS('2022'!$M:$M,'2022'!$E:$E,Trésorerie!P$4,'2022'!$F:$F,Trésorerie!$B23)+SUMIFS('2022'!$N:$N,'2022'!$E:$E,Trésorerie!P$4,'2022'!$F:$F,Trésorerie!$B23) -> 620.86 | R23: =-SUMIFS('2023-01'!$M:$M,'2023-01'!$E:$E,Trésorerie!R$4,'2023-01'!$F:$F,Trésorerie!$B23)+SUMIFS('2023-01'!$N:$N,'2023-01'!$E:$E,Trésorerie!R$4,'2023-01'!$F:$F,Trésorerie!$B23) -> 481.47 | S23: =-SUMIFS('2023-02'!$M:$M,'2023-02'!$E:$E,Trésorerie!S$4,'2023-02'!$F:$F,Trésorerie!$B23)+SUMIFS('2023-02'!$N:$N,'2023-02'!$E:$E,Trésorerie!S$4,'2023-02'!$F:$F,Trésorerie!$B23) -> 373.07 | T23: =-SUMIFS('2023-03'!$M:$M,'2023-03'!$E:$E,Trésorerie!T$4,'2023-03'!$F:$F,Trésorerie!$B23)+SUMIFS('2023-03'!$N:$N,'2023-03'!$E:$E,Trésorerie!T$4,'2023-03'!$F:$F,Trésorerie!$B23) -> 958.8 | U23: =-SUMIFS('2023-04'!$M:$M,'2023-04'!$E:$E,Trésorerie!U$4,'2023-04'!$F:$F,Trésorerie!$B23)+SUMIFS('2023-04'!$N:$N,'2023-04'!$E:$E,Trésorerie!U$4,'2023-04'!$F:$F,Trésorerie!$B23) -> 496.59 | V23: =-SUMIFS('2023-05'!$M:$M,'2023-05'!$E:$E,Trésorerie!V$4,'2023-05'!$F:$F,Trésorerie!$B23)+SUMIFS('2023-05'!$N:$N,'2023-05'!$E:$E,Trésorerie!V$4,'2023-05'!$F:$F,Trésorerie!$B23) -> 871.88 | W23: =-SUMIFS('2023-06'!$M:$M,'2023-06'!$E:$E,Trésorerie!W$4,'2023-06'!$F:$F,Trésorerie!$B23)+SUMIFS('2023-06'!$N:$N,'2023-06'!$E:$E,Trésorerie!W$4,'2023-06'!$F:$F,Trésorerie!$B23) -> 531.47 | X23: =-SUMIFS('2023-07'!$M:$M,'2023-07'!$E:$E,Trésorerie!X$4,'2023-07'!$F:$F,Trésorerie!$B23)+SUMIFS('2023-07'!$N:$N,'2023-07'!$E:$E,Trésorerie!X$4,'2023-07'!$F:$F,Trésorerie!$B23) -> 405.66 | Y23: =-SUMIFS('2023-08'!$M:$M,'2023-08'!$E:$E,Trésorerie!Y$4,'2023-08'!$F:$F,Trésorerie!$B23)+SUMIFS('2023-08'!$N:$N,'2023-08'!$E:$E,Trésorerie!Y$4,'2023-08'!$F:$F,Trésorerie!$B23) -> 349.31 | Z23: =-SUMIFS('2023-09'!$M:$M,'2023-09'!$E:$E,Trésorerie!Z$4,'2023-09'!$F:$F,Trésorerie!$B23)+SUMIFS('2023-09'!$N:$N,'2023-09'!$E:$E,Trésorerie!Z$4,'2023-09'!$F:$F,Trésorerie!$B23) -> 496.01 | AA23: =-SUMIFS('2023-10'!$M:$M,'2023-10'!$E:$E,Trésorerie!AA$4,'2023-10'!$F:$F,Trésorerie!$B23)+SUMIFS('2023-10'!$N:$N,'2023-10'!$E:$E,Trésorerie!AA$4,'2023-10'!$F:$F,Trésorerie!$B23) -> 746.43 | AB23: =IF(SUM($E23:O23)>SUM($R23:AA23),SUM($E23:O23)-SUM($R23:AA23),0) -> 783.71 | AC23: =IF(SUM($E23:P23)>SUM($R23:AB23),SUM($E23:P23)-SUM($R23:AB23),0) -> 620.86
A24: =SUM(E24:P24) -> 6960.46 | B24: 445010 | C24: CAF PS PERISCO MERCREDIS CYP CFAL | D24: Entrée | E24: =-SUMIFS('2022'!$M:$M,'2022'!$E:$E,Trésorerie!E$4,'2022'!$F:$F,Trésorerie!$B24)+SUMIFS('2022'!$N:$N,'2022'!$E:$E,Trésorerie!E$4,'2022'!$F:$F,Trésorerie!$B24) -> 0 | F24: =-SUMIFS('2022'!$M:$M,'2022'!$E:$E,Trésorerie!F$4,'2022'!$F:$F,Trésorerie!$B24)+SUMIFS('2022'!$N:$N,'2022'!$E:$E,Trésorerie!F$4,'2022'!$F:$F,Trésorerie!$B24) -> 0 | G24: =-SUMIFS('2022'!$M:$M,'2022'!$E:$E,Trésorerie!G$4,'2022'!$F:$F,Trésorerie!$B24)+SUMIFS('2022'!$N:$N,'2022'!$E:$E,Trésorerie!G$4,'2022'!$F:$F,Trésorerie!$B24) -> 0 | H24: =-SUMIFS('2022'!$M:$M,'2022'!$E:$E,Trésorerie!H$4,'2022'!$F:$F,Trésorerie!$B24)+SUMIFS('2022'!$N:$N,'2022'!$E:$E,Trésorerie!H$4,'2022'!$F:$F,Trésorerie!$B24) -> 0 | I24: =-SUMIFS('2022'!$M:$M,'2022'!$E:$E,Trésorerie!I$4,'2022'!$F:$F,Trésorerie!$B24)+SUMIFS('2022'!$N:$N,'2022'!$E:$E,Trésorerie!I$4,'2022'!$F:$F,Trésorerie!$B24) -> 2329.83 | J24: =-SUMIFS('2022'!$M:$M,'2022'!$E:$E,Trésorerie!J$4,'2022'!$F:$F,Trésorerie!$B24)+SUMIFS('2022'!$N:$N,'2022'!$E:$E,Trésorerie!J$4,'2022'!$F:$F,Trésorerie!$B24) -> 3139.65 | K24: =-SUMIFS('2022'!$M:$M,'2022'!$E:$E,Trésorerie!K$4,'2022'!$F:$F,Trésorerie!$B24)+SUMIFS('2022'!$N:$N,'2022'!$E:$E,Trésorerie!K$4,'2022'!$F:$F,Trésorerie!$B24) -> 0 | L24: =-SUMIFS('2022'!$M:$M,'2022'!$E:$E,Trésorerie!L$4,'2022'!$F:$F,Trésorerie!$B24)+SUMIFS('2022'!$N:$N,'2022'!$E:$E,Trésorerie!L$4,'2022'!$F:$F,Trésorerie!$B24) -> 0 | ... P24: =-SUMIFS('2022'!$M:$M,'2022'!$E:$E,Trésorerie!P$4,'2022'!$F:$F,Trésorerie!$B24)+SUMIFS('2022'!$N:$N,'2022'!$E:$E,Trésorerie!P$4,'2022'!$F:$F,Trésorerie!$B24) -> 0 | R24: =-SUMIFS('2023-01'!$M:$M,'2023-01'!$E:$E,Trésorerie!R$4,'2023-01'!$F:$F,Trésorerie!$B24)+SUMIFS('2023-01'!$N:$N,'2023-01'!$E:$E,Trésorerie!R$4,'2023-01'!$F:$F,Trésorerie!$B24) -> 0 | S24: =-SUMIFS('2023-02'!$M:$M,'2023-02'!$E:$E,Trésorerie!S$4,'2023-02'!$F:$F,Trésorerie!$B24)+SUMIFS('2023-02'!$N:$N,'2023-02'!$E:$E,Trésorerie!S$4,'2023-02'!$F:$F,Trésorerie!$B24) -> 0 | T24: =-SUMIFS('2023-03'!$M:$M,'2023-03'!$E:$E,Trésorerie!T$4,'2023-03'!$F:$F,Trésorerie!$B24)+SUMIFS('2023-03'!$N:$N,'2023-03'!$E:$E,Trésorerie!T$4,'2023-03'!$F:$F,Trésorerie!$B24) -> 3808.48 | U24: =-SUMIFS('2023-04'!$M:$M,'2023-04'!$E:$E,Trésorerie!U$4,'2023-04'!$F:$F,Trésorerie!$B24)+SUMIFS('2023-04'!$N:$N,'2023-04'!$E:$E,Trésorerie!U$4,'2023-04'!$F:$F,Trésorerie!$B24) -> 0 | V24: =-SUMIFS('2023-05'!$M:$M,'2023-05'!$E:$E,Trésorerie!V$4,'2023-05'!$F:$F,Trésorerie!$B24)+SUMIFS('2023-05'!$N:$N,'2023-05'!$E:$E,Trésorerie!V$4,'2023-05'!$F:$F,Trésorerie!$B24) -> 0 | W24: =-SUMIFS('2023-06'!$M:$M,'2023-06'!$E:$E,Trésorerie!W$4,'2023-06'!$F:$F,Trésorerie!$B24)+SUMIFS('2023-06'!$N:$N,'2023-06'!$E:$E,Trésorerie!W$4,'2023-06'!$F:$F,Trésorerie!$B24) -> 2289.72 | X24: =-SUMIFS('2023-07'!$M:$M,'2023-07'!$E:$E,Trésorerie!X$4,'2023-07'!$F:$F,Trésorerie!$B24)+SUMIFS('2023-07'!$N:$N,'2023-07'!$E:$E,Trésorerie!X$4,'2023-07'!$F:$F,Trésorerie!$B24) -> 0 | Y24: =-SUMIFS('2023-08'!$M:$M,'2023-08'!$E:$E,Trésorerie!Y$4,'2023-08'!$F:$F,Trésorerie!$B24)+SUMIFS('2023-08'!$N:$N,'2023-08'!$E:$E,Trésorerie!Y$4,'2023-08'!$F:$F,Trésorerie!$B24) -> 0 | Z24: =-SUMIFS('2023-09'!$M:$M,'2023-09'!$E:$E,Trésorerie!Z$4,'2023-09'!$F:$F,Trésorerie!$B24)+SUMIFS('2023-09'!$N:$N,'2023-09'!$E:$E,Trésorerie!Z$4,'2023-09'!$F:$F,Trésorerie!$B24) -> 1979.42 | AA24: =-SUMIFS('2023-10'!$M:$M,'2023-10'!$E:$E,Trésorerie!AA$4,'2023-10'!$F:$F,Trésorerie!$B24)+SUMIFS('2023-10'!$N:$N,'2023-10'!$E:$E,Trésorerie!AA$4,'2023-10'!$F:$F,Trésorerie!$B24) -> 0 | AB24: =IF(SUM($E24:O24)>SUM($R24:AA24),SUM($E24:O24)-SUM($R24:AA24),0) -> 0 | AC24: =IF(SUM($E24:P24)>SUM($R24:AB24),SUM($E24:P24)-SUM($R24:AB24),0) -> 0
A25: =SUM(E25:P25) -> 4821 | B25: 445055 | C25: CAF V.F.S.SORTIES | D25: Entrée | E25: =-SUMIFS('2022'!$M:$M,'2022'!$E:$E,Trésorerie!E$4,'2022'!$F:$F,Trésorerie!$B25)+SUMIFS('2022'!$N:$N,'2022'!$E:$E,Trésorerie!E$4,'2022'!$F:$F,Trésorerie!$B25) -> 0 | F25: =-SUMIFS('2022'!$M:$M,'2022'!$E:$E,Trésorerie!F$4,'2022'!$F:$F,Trésorerie!$B25)+SUMIFS('2022'!$N:$N,'2022'!$E:$E,Trésorerie!F$4,'2022'!$F:$F,Trésorerie!$B25) -> 0 | G25: =-SUMIFS('2022'!$M:$M,'2022'!$E:$E,Trésorerie!G$4,'2022'!$F:$F,Trésorerie!$B25)+SUMIFS('2022'!$N:$N,'2022'!$E:$E,Trésorerie!G$4,'2022'!$F:$F,Trésorerie!$B25) -> 0 | H25: =-SUMIFS('2022'!$M:$M,'2022'!$E:$E,Trésorerie!H$4,'2022'!$F:$F,Trésorerie!$B25)+SUMIFS('2022'!$N:$N,'2022'!$E:$E,Trésorerie!H$4,'2022'!$F:$F,Trésorerie!$B25) -> 0 | I25: =-SUMIFS('2022'!$M:$M,'2022'!$E:$E,Trésorerie!I$4,'2022'!$F:$F,Trésorerie!$B25)+SUMIFS('2022'!$N:$N,'2022'!$E:$E,Trésorerie!I$4,'2022'!$F:$F,Trésorerie!$B25) -> 0 | J25: =-SUMIFS('2022'!$M:$M,'2022'!$E:$E,Trésorerie!J$4,'2022'!$F:$F,Trésorerie!$B25)+SUMIFS('2022'!$N:$N,'2022'!$E:$E,Trésorerie!J$4,'2022'!$F:$F,Trésorerie!$B25) -> 0 | K25: =-SUMIFS('2022'!$M:$M,'2022'!$E:$E,Trésorerie!K$4,'2022'!$F:$F,Trésorerie!$B25)+SUMIFS('2022'!$N:$N,'2022'!$E:$E,Trésorerie!K$4,'2022'!$F:$F,Trésorerie!$B25) -> 0 | L25: =-SUMIFS('2022'!$M:$M,'2022'!$E:$E,Trésorerie!L$4,'2022'!$F:$F,Trésorerie!$B25)+SUMIFS('2022'!$N:$N,'2022'!$E:$E,Trésorerie!L$4,'2022'!$F:$F,Trésorerie!$B25) -> 0 | ... P25: =-SUMIFS('2022'!$M:$M,'2022'!$E:$E,Trésorerie!P$4,'2022'!$F:$F,Trésorerie!$B25)+SUMIFS('2022'!$N:$N,'2022'!$E:$E,Trésorerie!P$4,'2022'!$F:$F,Trésorerie!$B25) -> 782 | R25: =-SUMIFS('2023-01'!$M:$M,'2023-01'!$E:$E,Trésorerie!R$4,'2023-01'!$F:$F,Trésorerie!$B25)+SUMIFS('2023-01'!$N:$N,'2023-01'!$E:$E,Trésorerie!R$4,'2023-01'!$F:$F,Trésorerie!$B25) -> 0 | S25: =-SUMIFS('2023-02'!$M:$M,'2023-02'!$E:$E,Trésorerie!S$4,'2023-02'!$F:$F,Trésorerie!$B25)+SUMIFS('2023-02'!$N:$N,'2023-02'!$E:$E,Trésorerie!S$4,'2023-02'!$F:$F,Trésorerie!$B25) -> 0 | T25: =-SUMIFS('2023-03'!$M:$M,'2023-03'!$E:$E,Trésorerie!T$4,'2023-03'!$F:$F,Trésorerie!$B25)+SUMIFS('2023-03'!$N:$N,'2023-03'!$E:$E,Trésorerie!T$4,'2023-03'!$F:$F,Trésorerie!$B25) -> 0 | U25: =-SUMIFS('2023-04'!$M:$M,'2023-04'!$E:$E,Trésorerie!U$4,'2023-04'!$F:$F,Trésorerie!$B25)+SUMIFS('2023-04'!$N:$N,'2023-04'!$E:$E,Trésorerie!U$4,'2023-04'!$F:$F,Trésorerie!$B25) -> 0 | V25: =-SUMIFS('2023-05'!$M:$M,'2023-05'!$E:$E,Trésorerie!V$4,'2023-05'!$F:$F,Trésorerie!$B25)+SUMIFS('2023-05'!$N:$N,'2023-05'!$E:$E,Trésorerie!V$4,'2023-05'!$F:$F,Trésorerie!$B25) -> 0 | W25: =-SUMIFS('2023-06'!$M:$M,'2023-06'!$E:$E,Trésorerie!W$4,'2023-06'!$F:$F,Trésorerie!$B25)+SUMIFS('2023-06'!$N:$N,'2023-06'!$E:$E,Trésorerie!W$4,'2023-06'!$F:$F,Trésorerie!$B25) -> 0 | X25: =-SUMIFS('2023-07'!$M:$M,'2023-07'!$E:$E,Trésorerie!X$4,'2023-07'!$F:$F,Trésorerie!$B25)+SUMIFS('2023-07'!$N:$N,'2023-07'!$E:$E,Trésorerie!X$4,'2023-07'!$F:$F,Trésorerie!$B25) -> 245 | Y25: =-SUMIFS('2023-08'!$M:$M,'2023-08'!$E:$E,Trésorerie!Y$4,'2023-08'!$F:$F,Trésorerie!$B25)+SUMIFS('2023-08'!$N:$N,'2023-08'!$E:$E,Trésorerie!Y$4,'2023-08'!$F:$F,Trésorerie!$B25) -> 0 | Z25: =-SUMIFS('2023-09'!$M:$M,'2023-09'!$E:$E,Trésorerie!Z$4,'2023-09'!$F:$F,Trésorerie!$B25)+SUMIFS('2023-09'!$N:$N,'2023-09'!$E:$E,Trésorerie!Z$4,'2023-09'!$F:$F,Trésorerie!$B25) -> 0 | AA25: =-SUMIFS('2023-10'!$M:$M,'2023-10'!$E:$E,Trésorerie!AA$4,'2023-10'!$F:$F,Trésorerie!$B25)+SUMIFS('2023-10'!$N:$N,'2023-10'!$E:$E,Trésorerie!AA$4,'2023-10'!$F:$F,Trésorerie!$B25) -> 0 | AB25: =IF(SUM($E25:O25)>SUM($R25:AA25),SUM($E25:O25)-SUM($R25:AA25),0) -> 3794 | AC25: =IF(SUM($E25:P25)>SUM($R25:AB25),SUM($E25:P25)-SUM($R25:AB25),0) -> 782
A26: =SUM(E26:P26) -> 0 | B26: 445035 | C26: X | D26: Entrée | E26: =-SUMIFS('2022'!$M:$M,'2022'!$E:$E,Trésorerie!E$4,'2022'!$F:$F,Trésorerie!$B26)+SUMIFS('2022'!$N:$N,'2022'!$E:$E,Trésorerie!E$4,'2022'!$F:$F,Trésorerie!$B26) -> 0 | F26: =-SUMIFS('2022'!$M:$M,'2022'!$E:$E,Trésorerie!F$4,'2022'!$F:$F,Trésorerie!$B26)+SUMIFS('2022'!$N:$N,'2022'!$E:$E,Trésorerie!F$4,'2022'!$F:$F,Trésorerie!$B26) -> 0 | G26: =-SUMIFS('2022'!$M:$M,'2022'!$E:$E,Trésorerie!G$4,'2022'!$F:$F,Trésorerie!$B26)+SUMIFS('2022'!$N:$N,'2022'!$E:$E,Trésorerie!G$4,'2022'!$F:$F,Trésorerie!$B26) -> 0 | H26: =-SUMIFS('2022'!$M:$M,'2022'!$E:$E,Trésorerie!H$4,'2022'!$F:$F,Trésorerie!$B26)+SUMIFS('2022'!$N:$N,'2022'!$E:$E,Trésorerie!H$4,'2022'!$F:$F,Trésorerie!$B26) -> 0 | I26: =-SUMIFS('2022'!$M:$M,'2022'!$E:$E,Trésorerie!I$4,'2022'!$F:$F,Trésorerie!$B26)+SUMIFS('2022'!$N:$N,'2022'!$E:$E,Trésorerie!I$4,'2022'!$F:$F,Trésorerie!$B26) -> 0 | J26: =-SUMIFS('2022'!$M:$M,'2022'!$E:$E,Trésorerie!J$4,'2022'!$F:$F,Trésorerie!$B26)+SUMIFS('2022'!$N:$N,'2022'!$E:$E,Trésorerie!J$4,'2022'!$F:$F,Trésorerie!$B26) -> 0 | K26: =-SUMIFS('2022'!$M:$M,'2022'!$E:$E,Trésorerie!K$4,'2022'!$F:$F,Trésorerie!$B26)+SUMIFS('2022'!$N:$N,'2022'!$E:$E,Trésorerie!K$4,'2022'!$F:$F,Trésorerie!$B26) -> 0 | L26: =-SUMIFS('2022'!$M:$M,'2022'!$E:$E,Trésorerie!L$4,'2022'!$F:$F,Trésorerie!$B26)+SUMIFS('2022'!$N:$N,'2022'!$E:$E,Trésorerie!L$4,'2022'!$F:$F,Trésorerie!$B26) -> 0 | ... P26: =-SUMIFS('2022'!$M:$M,'2022'!$E:$E,Trésorerie!P$4,'2022'!$F:$F,Trésorerie!$B26)+SUMIFS('2022'!$N:$N,'2022'!$E:$E,Trésorerie!P$4,'2022'!$F:$F,Trésorerie!$B26) -> 0 | R26: =-SUMIFS('2023-01'!$M:$M,'2023-01'!$E:$E,Trésorerie!R$4,'2023-01'!$F:$F,Trésorerie!$B26)+SUMIFS('2023-01'!$N:$N,'2023-01'!$E:$E,Trésorerie!R$4,'2023-01'!$F:$F,Trésorerie!$B26) -> 0 | S26: =-SUMIFS('2023-02'!$M:$M,'2023-02'!$E:$E,Trésorerie!S$4,'2023-02'!$F:$F,Trésorerie!$B26)+SUMIFS('2023-02'!$N:$N,'2023-02'!$E:$E,Trésorerie!S$4,'2023-02'!$F:$F,Trésorerie!$B26) -> 0 | T26: =-SUMIFS('2023-03'!$M:$M,'2023-03'!$E:$E,Trésorerie!T$4,'2023-03'!$F:$F,Trésorerie!$B26)+SUMIFS('2023-03'!$N:$N,'2023-03'!$E:$E,Trésorerie!T$4,'2023-03'!$F:$F,Trésorerie!$B26) -> 0 | U26: =-SUMIFS('2023-04'!$M:$M,'2023-04'!$E:$E,Trésorerie!U$4,'2023-04'!$F:$F,Trésorerie!$B26)+SUMIFS('2023-04'!$N:$N,'2023-04'!$E:$E,Trésorerie!U$4,'2023-04'!$F:$F,Trésorerie!$B26) -> 121.93 | V26: =-SUMIFS('2023-05'!$M:$M,'2023-05'!$E:$E,Trésorerie!V$4,'2023-05'!$F:$F,Trésorerie!$B26)+SUMIFS('2023-05'!$N:$N,'2023-05'!$E:$E,Trésorerie!V$4,'2023-05'!$F:$F,Trésorerie!$B26) -> 0 | W26: =-SUMIFS('2023-06'!$M:$M,'2023-06'!$E:$E,Trésorerie!W$4,'2023-06'!$F:$F,Trésorerie!$B26)+SUMIFS('2023-06'!$N:$N,'2023-06'!$E:$E,Trésorerie!W$4,'2023-06'!$F:$F,Trésorerie!$B26) -> 0 | X26: =-SUMIFS('2023-07'!$M:$M,'2023-07'!$E:$E,Trésorerie!X$4,'2023-07'!$F:$F,Trésorerie!$B26)+SUMIFS('2023-07'!$N:$N,'2023-07'!$E:$E,Trésorerie!X$4,'2023-07'!$F:$F,Trésorerie!$B26) -> 0 | Y26: =-SUMIFS('2023-08'!$M:$M,'2023-08'!$E:$E,Trésorerie!Y$4,'2023-08'!$F:$F,Trésorerie!$B26)+SUMIFS('2023-08'!$N:$N,'2023-08'!$E:$E,Trésorerie!Y$4,'2023-08'!$F:$F,Trésorerie!$B26) -> 0 | Z26: =-SUMIFS('2023-09'!$M:$M,'2023-09'!$E:$E,Trésorerie!Z$4,'2023-09'!$F:$F,Trésorerie!$B26)+SUMIFS('2023-09'!$N:$N,'2023-09'!$E:$E,Trésorerie!Z$4,'2023-09'!$F:$F,Trésorerie!$B26) -> 0 | AA26: =-SUMIFS('2023-10'!$M:$M,'2023-10'!$E:$E,Trésorerie!AA$4,'2023-10'!$F:$F,Trésorerie!$B26)+SUMIFS('2023-10'!$N:$N,'2023-10'!$E:$E,Trésorerie!AA$4,'2023-10'!$F:$F,Trésorerie!$B26) -> 0 | AB26: =IF(SUM($E26:O26)>SUM($R26:AA26),SUM($E26:O26)-SUM($R26:AA26),0) -> 0 | AC26: =IF(SUM($E26:P26)>SUM($R26:AB26),SUM($E26:P26)-SUM($R26:AB26),0) -> 0
A27: =SUM(E27:P27) -> 3770.2 | B27: 411000 | C27: COLLECTIF CLIENTS DIVERS | D27: Entrée | E27: =-SUMIFS('2022'!$M:$M,'2022'!$E:$E,Trésorerie!E$4,'2022'!$F:$F,Trésorerie!$B27)+SUMIFS('2022'!$N:$N,'2022'!$E:$E,Trésorerie!E$4,'2022'!$F:$F,Trésorerie!$B27) -> 407.1 | F27: =-SUMIFS('2022'!$M:$M,'2022'!$E:$E,Trésorerie!F$4,'2022'!$F:$F,Trésorerie!$B27)+SUMIFS('2022'!$N:$N,'2022'!$E:$E,Trésorerie!F$4,'2022'!$F:$F,Trésorerie!$B27) -> 557.66 | G27: =-SUMIFS('2022'!$M:$M,'2022'!$E:$E,Trésorerie!G$4,'2022'!$F:$F,Trésorerie!$B27)+SUMIFS('2022'!$N:$N,'2022'!$E:$E,Trésorerie!G$4,'2022'!$F:$F,Trésorerie!$B27) -> 910.63 | H27: =-SUMIFS('2022'!$M:$M,'2022'!$E:$E,Trésorerie!H$4,'2022'!$F:$F,Trésorerie!$B27)+SUMIFS('2022'!$N:$N,'2022'!$E:$E,Trésorerie!H$4,'2022'!$F:$F,Trésorerie!$B27) -> -30 | I27: =-SUMIFS('2022'!$M:$M,'2022'!$E:$E,Trésorerie!I$4,'2022'!$F:$F,Trésorerie!$B27)+SUMIFS('2022'!$N:$N,'2022'!$E:$E,Trésorerie!I$4,'2022'!$F:$F,Trésorerie!$B27) -> 61.4 | J27: =-SUMIFS('2022'!$M:$M,'2022'!$E:$E,Trésorerie!J$4,'2022'!$F:$F,Trésorerie!$B27)+SUMIFS('2022'!$N:$N,'2022'!$E:$E,Trésorerie!J$4,'2022'!$F:$F,Trésorerie!$B27) -> 588.88 | K27: =-SUMIFS('2022'!$M:$M,'2022'!$E:$E,Trésorerie!K$4,'2022'!$F:$F,Trésorerie!$B27)+SUMIFS('2022'!$N:$N,'2022'!$E:$E,Trésorerie!K$4,'2022'!$F:$F,Trésorerie!$B27) -> -13.47 | L27: =-SUMIFS('2022'!$M:$M,'2022'!$E:$E,Trésorerie!L$4,'2022'!$F:$F,Trésorerie!$B27)+SUMIFS('2022'!$N:$N,'2022'!$E:$E,Trésorerie!L$4,'2022'!$F:$F,Trésorerie!$B27) -> 0 | ... P27: =-SUMIFS('2022'!$M:$M,'2022'!$E:$E,Trésorerie!P$4,'2022'!$F:$F,Trésorerie!$B27)+SUMIFS('2022'!$N:$N,'2022'!$E:$E,Trésorerie!P$4,'2022'!$F:$F,Trésorerie!$B27) -> 721 | R27: =-SUMIFS('2023-01'!$M:$M,'2023-01'!$E:$E,Trésorerie!R$4,'2023-01'!$F:$F,Trésorerie!$B27)+SUMIFS('2023-01'!$N:$N,'2023-01'!$E:$E,Trésorerie!R$4,'2023-01'!$F:$F,Trésorerie!$B27) -> 849.83 | S27: =-SUMIFS('2023-02'!$M:$M,'2023-02'!$E:$E,Trésorerie!S$4,'2023-02'!$F:$F,Trésorerie!$B27)+SUMIFS('2023-02'!$N:$N,'2023-02'!$E:$E,Trésorerie!S$4,'2023-02'!$F:$F,Trésorerie!$B27) -> 24 | T27: =-SUMIFS('2023-03'!$M:$M,'2023-03'!$E:$E,Trésorerie!T$4,'2023-03'!$F:$F,Trésorerie!$B27)+SUMIFS('2023-03'!$N:$N,'2023-03'!$E:$E,Trésorerie!T$4,'2023-03'!$F:$F,Trésorerie!$B27) -> 189 | U27: =-SUMIFS('2023-04'!$M:$M,'2023-04'!$E:$E,Trésorerie!U$4,'2023-04'!$F:$F,Trésorerie!$B27)+SUMIFS('2023-04'!$N:$N,'2023-04'!$E:$E,Trésorerie!U$4,'2023-04'!$F:$F,Trésorerie!$B27) -> 48.37 | V27: =-SUMIFS('2023-05'!$M:$M,'2023-05'!$E:$E,Trésorerie!V$4,'2023-05'!$F:$F,Trésorerie!$B27)+SUMIFS('2023-05'!$N:$N,'2023-05'!$E:$E,Trésorerie!V$4,'2023-05'!$F:$F,Trésorerie!$B27) -> 10.5 | W27: =-SUMIFS('2023-06'!$M:$M,'2023-06'!$E:$E,Trésorerie!W$4,'2023-06'!$F:$F,Trésorerie!$B27)+SUMIFS('2023-06'!$N:$N,'2023-06'!$E:$E,Trésorerie!W$4,'2023-06'!$F:$F,Trésorerie!$B27) -> 239.9 | X27: =-SUMIFS('2023-07'!$M:$M,'2023-07'!$E:$E,Trésorerie!X$4,'2023-07'!$F:$F,Trésorerie!$B27)+SUMIFS('2023-07'!$N:$N,'2023-07'!$E:$E,Trésorerie!X$4,'2023-07'!$F:$F,Trésorerie!$B27) -> 371.6 | Y27: =-SUMIFS('2023-08'!$M:$M,'2023-08'!$E:$E,Trésorerie!Y$4,'2023-08'!$F:$F,Trésorerie!$B27)+SUMIFS('2023-08'!$N:$N,'2023-08'!$E:$E,Trésorerie!Y$4,'2023-08'!$F:$F,Trésorerie!$B27) -> 9.81 | Z27: =-SUMIFS('2023-09'!$M:$M,'2023-09'!$E:$E,Trésorerie!Z$4,'2023-09'!$F:$F,Trésorerie!$B27)+SUMIFS('2023-09'!$N:$N,'2023-09'!$E:$E,Trésorerie!Z$4,'2023-09'!$F:$F,Trésorerie!$B27) -> 385.42 | AA27: =-SUMIFS('2023-10'!$M:$M,'2023-10'!$E:$E,Trésorerie!AA$4,'2023-10'!$F:$F,Trésorerie!$B27)+SUMIFS('2023-10'!$N:$N,'2023-10'!$E:$E,Trésorerie!AA$4,'2023-10'!$F:$F,Trésorerie!$B27) -> 103.99 | AB27: =IF(SUM($E27:O27)>SUM($R27:AA27),SUM($E27:O27)-SUM($R27:AA27),0) -> 816.78 | AC27: =IF(SUM($E27:P27)>SUM($R27:AB27),SUM($E27:P27)-SUM($R27:AB27),0) -> 721
A28: =SUM(E28:P28) -> 3450 | B28: 511002 | C28: CHEQUES CRCESU DIFFERES | D28: Entrée | E28: =-SUMIFS('2022'!$M:$M,'2022'!$E:$E,Trésorerie!E$4,'2022'!$F:$F,Trésorerie!$B28)+SUMIFS('2022'!$N:$N,'2022'!$E:$E,Trésorerie!E$4,'2022'!$F:$F,Trésorerie!$B28) -> 0 | F28: =-SUMIFS('2022'!$M:$M,'2022'!$E:$E,Trésorerie!F$4,'2022'!$F:$F,Trésorerie!$B28)+SUMIFS('2022'!$N:$N,'2022'!$E:$E,Trésorerie!F$4,'2022'!$F:$F,Trésorerie!$B28) -> 0 | G28: =-SUMIFS('2022'!$M:$M,'2022'!$E:$E,Trésorerie!G$4,'2022'!$F:$F,Trésorerie!$B28)+SUMIFS('2022'!$N:$N,'2022'!$E:$E,Trésorerie!G$4,'2022'!$F:$F,Trésorerie!$B28) -> 0 | H28: =-SUMIFS('2022'!$M:$M,'2022'!$E:$E,Trésorerie!H$4,'2022'!$F:$F,Trésorerie!$B28)+SUMIFS('2022'!$N:$N,'2022'!$E:$E,Trésorerie!H$4,'2022'!$F:$F,Trésorerie!$B28) -> 0 | I28: =-SUMIFS('2022'!$M:$M,'2022'!$E:$E,Trésorerie!I$4,'2022'!$F:$F,Trésorerie!$B28)+SUMIFS('2022'!$N:$N,'2022'!$E:$E,Trésorerie!I$4,'2022'!$F:$F,Trésorerie!$B28) -> 0 | J28: =-SUMIFS('2022'!$M:$M,'2022'!$E:$E,Trésorerie!J$4,'2022'!$F:$F,Trésorerie!$B28)+SUMIFS('2022'!$N:$N,'2022'!$E:$E,Trésorerie!J$4,'2022'!$F:$F,Trésorerie!$B28) -> 0 | K28: =-SUMIFS('2022'!$M:$M,'2022'!$E:$E,Trésorerie!K$4,'2022'!$F:$F,Trésorerie!$B28)+SUMIFS('2022'!$N:$N,'2022'!$E:$E,Trésorerie!K$4,'2022'!$F:$F,Trésorerie!$B28) -> 0 | L28: =-SUMIFS('2022'!$M:$M,'2022'!$E:$E,Trésorerie!L$4,'2022'!$F:$F,Trésorerie!$B28)+SUMIFS('2022'!$N:$N,'2022'!$E:$E,Trésorerie!L$4,'2022'!$F:$F,Trésorerie!$B28) -> 2315 | ... P28: =-SUMIFS('2022'!$M:$M,'2022'!$E:$E,Trésorerie!P$4,'2022'!$F:$F,Trésorerie!$B28)+SUMIFS('2022'!$N:$N,'2022'!$E:$E,Trésorerie!P$4,'2022'!$F:$F,Trésorerie!$B28) -> 710 | R28: =-SUMIFS('2023-01'!$M:$M,'2023-01'!$E:$E,Trésorerie!R$4,'2023-01'!$F:$F,Trésorerie!$B28)+SUMIFS('2023-01'!$N:$N,'2023-01'!$E:$E,Trésorerie!R$4,'2023-01'!$F:$F,Trésorerie!$B28) -> 0 | S28: =-SUMIFS('2023-02'!$M:$M,'2023-02'!$E:$E,Trésorerie!S$4,'2023-02'!$F:$F,Trésorerie!$B28)+SUMIFS('2023-02'!$N:$N,'2023-02'!$E:$E,Trésorerie!S$4,'2023-02'!$F:$F,Trésorerie!$B28) -> 2235 | T28: =-SUMIFS('2023-03'!$M:$M,'2023-03'!$E:$E,Trésorerie!T$4,'2023-03'!$F:$F,Trésorerie!$B28)+SUMIFS('2023-03'!$N:$N,'2023-03'!$E:$E,Trésorerie!T$4,'2023-03'!$F:$F,Trésorerie!$B28) -> 1434.92 | U28: =-SUMIFS('2023-04'!$M:$M,'2023-04'!$E:$E,Trésorerie!U$4,'2023-04'!$F:$F,Trésorerie!$B28)+SUMIFS('2023-04'!$N:$N,'2023-04'!$E:$E,Trésorerie!U$4,'2023-04'!$F:$F,Trésorerie!$B28) -> 0 | V28: =-SUMIFS('2023-05'!$M:$M,'2023-05'!$E:$E,Trésorerie!V$4,'2023-05'!$F:$F,Trésorerie!$B28)+SUMIFS('2023-05'!$N:$N,'2023-05'!$E:$E,Trésorerie!V$4,'2023-05'!$F:$F,Trésorerie!$B28) -> 0 | W28: =-SUMIFS('2023-06'!$M:$M,'2023-06'!$E:$E,Trésorerie!W$4,'2023-06'!$F:$F,Trésorerie!$B28)+SUMIFS('2023-06'!$N:$N,'2023-06'!$E:$E,Trésorerie!W$4,'2023-06'!$F:$F,Trésorerie!$B28) -> 0 | X28: =-SUMIFS('2023-07'!$M:$M,'2023-07'!$E:$E,Trésorerie!X$4,'2023-07'!$F:$F,Trésorerie!$B28)+SUMIFS('2023-07'!$N:$N,'2023-07'!$E:$E,Trésorerie!X$4,'2023-07'!$F:$F,Trésorerie!$B28) -> 700 | Y28: =-SUMIFS('2023-08'!$M:$M,'2023-08'!$E:$E,Trésorerie!Y$4,'2023-08'!$F:$F,Trésorerie!$B28)+SUMIFS('2023-08'!$N:$N,'2023-08'!$E:$E,Trésorerie!Y$4,'2023-08'!$F:$F,Trésorerie!$B28) -> 0 | Z28: =-SUMIFS('2023-09'!$M:$M,'2023-09'!$E:$E,Trésorerie!Z$4,'2023-09'!$F:$F,Trésorerie!$B28)+SUMIFS('2023-09'!$N:$N,'2023-09'!$E:$E,Trésorerie!Z$4,'2023-09'!$F:$F,Trésorerie!$B28) -> 0 | AA28: =-SUMIFS('2023-10'!$M:$M,'2023-10'!$E:$E,Trésorerie!AA$4,'2023-10'!$F:$F,Trésorerie!$B28)+SUMIFS('2023-10'!$N:$N,'2023-10'!$E:$E,Trésorerie!AA$4,'2023-10'!$F:$F,Trésorerie!$B28) -> 0 | AB28: =IF(SUM($E28:O28)>SUM($R28:AA28),SUM($E28:O28)-SUM($R28:AA28),0) -> 0 | AC28: =IF(SUM($E28:P28)>SUM($R28:AB28),SUM($E28:P28)-SUM($R28:AB28),0) -> 0
A29: =SUM(E29:P29) -> 1889.72 | B29: 511001 | C29: CH ANCV DIFFERES | D29: Entrée | E29: =-SUMIFS('2022'!$M:$M,'2022'!$E:$E,Trésorerie!E$4,'2022'!$F:$F,Trésorerie!$B29)+SUMIFS('2022'!$N:$N,'2022'!$E:$E,Trésorerie!E$4,'2022'!$F:$F,Trésorerie!$B29) -> 0 | F29: =-SUMIFS('2022'!$M:$M,'2022'!$E:$E,Trésorerie!F$4,'2022'!$F:$F,Trésorerie!$B29)+SUMIFS('2022'!$N:$N,'2022'!$E:$E,Trésorerie!F$4,'2022'!$F:$F,Trésorerie!$B29) -> 0 | G29: =-SUMIFS('2022'!$M:$M,'2022'!$E:$E,Trésorerie!G$4,'2022'!$F:$F,Trésorerie!$B29)+SUMIFS('2022'!$N:$N,'2022'!$E:$E,Trésorerie!G$4,'2022'!$F:$F,Trésorerie!$B29) -> 200 | H29: =-SUMIFS('2022'!$M:$M,'2022'!$E:$E,Trésorerie!H$4,'2022'!$F:$F,Trésorerie!$B29)+SUMIFS('2022'!$N:$N,'2022'!$E:$E,Trésorerie!H$4,'2022'!$F:$F,Trésorerie!$B29) -> 0 | I29: =-SUMIFS('2022'!$M:$M,'2022'!$E:$E,Trésorerie!I$4,'2022'!$F:$F,Trésorerie!$B29)+SUMIFS('2022'!$N:$N,'2022'!$E:$E,Trésorerie!I$4,'2022'!$F:$F,Trésorerie!$B29) -> 0 | J29: =-SUMIFS('2022'!$M:$M,'2022'!$E:$E,Trésorerie!J$4,'2022'!$F:$F,Trésorerie!$B29)+SUMIFS('2022'!$N:$N,'2022'!$E:$E,Trésorerie!J$4,'2022'!$F:$F,Trésorerie!$B29) -> 1149.72 | K29: =-SUMIFS('2022'!$M:$M,'2022'!$E:$E,Trésorerie!K$4,'2022'!$F:$F,Trésorerie!$B29)+SUMIFS('2022'!$N:$N,'2022'!$E:$E,Trésorerie!K$4,'2022'!$F:$F,Trésorerie!$B29) -> 0 | L29: =-SUMIFS('2022'!$M:$M,'2022'!$E:$E,Trésorerie!L$4,'2022'!$F:$F,Trésorerie!$B29)+SUMIFS('2022'!$N:$N,'2022'!$E:$E,Trésorerie!L$4,'2022'!$F:$F,Trésorerie!$B29) -> 0 | ... P29: =-SUMIFS('2022'!$M:$M,'2022'!$E:$E,Trésorerie!P$4,'2022'!$F:$F,Trésorerie!$B29)+SUMIFS('2022'!$N:$N,'2022'!$E:$E,Trésorerie!P$4,'2022'!$F:$F,Trésorerie!$B29) -> 0 | R29: =-SUMIFS('2023-01'!$M:$M,'2023-01'!$E:$E,Trésorerie!R$4,'2023-01'!$F:$F,Trésorerie!$B29)+SUMIFS('2023-01'!$N:$N,'2023-01'!$E:$E,Trésorerie!R$4,'2023-01'!$F:$F,Trésorerie!$B29) -> 0 | S29: =-SUMIFS('2023-02'!$M:$M,'2023-02'!$E:$E,Trésorerie!S$4,'2023-02'!$F:$F,Trésorerie!$B29)+SUMIFS('2023-02'!$N:$N,'2023-02'!$E:$E,Trésorerie!S$4,'2023-02'!$F:$F,Trésorerie!$B29) -> 0 | T29: =-SUMIFS('2023-03'!$M:$M,'2023-03'!$E:$E,Trésorerie!T$4,'2023-03'!$F:$F,Trésorerie!$B29)+SUMIFS('2023-03'!$N:$N,'2023-03'!$E:$E,Trésorerie!T$4,'2023-03'!$F:$F,Trésorerie!$B29) -> 460 | U29: =-SUMIFS('2023-04'!$M:$M,'2023-04'!$E:$E,Trésorerie!U$4,'2023-04'!$F:$F,Trésorerie!$B29)+SUMIFS('2023-04'!$N:$N,'2023-04'!$E:$E,Trésorerie!U$4,'2023-04'!$F:$F,Trésorerie!$B29) -> 0 | V29: =-SUMIFS('2023-05'!$M:$M,'2023-05'!$E:$E,Trésorerie!V$4,'2023-05'!$F:$F,Trésorerie!$B29)+SUMIFS('2023-05'!$N:$N,'2023-05'!$E:$E,Trésorerie!V$4,'2023-05'!$F:$F,Trésorerie!$B29) -> 0 | W29: =-SUMIFS('2023-06'!$M:$M,'2023-06'!$E:$E,Trésorerie!W$4,'2023-06'!$F:$F,Trésorerie!$B29)+SUMIFS('2023-06'!$N:$N,'2023-06'!$E:$E,Trésorerie!W$4,'2023-06'!$F:$F,Trésorerie!$B29) -> 0 | X29: =-SUMIFS('2023-07'!$M:$M,'2023-07'!$E:$E,Trésorerie!X$4,'2023-07'!$F:$F,Trésorerie!$B29)+SUMIFS('2023-07'!$N:$N,'2023-07'!$E:$E,Trésorerie!X$4,'2023-07'!$F:$F,Trésorerie!$B29) -> 1799 | Y29: =-SUMIFS('2023-08'!$M:$M,'2023-08'!$E:$E,Trésorerie!Y$4,'2023-08'!$F:$F,Trésorerie!$B29)+SUMIFS('2023-08'!$N:$N,'2023-08'!$E:$E,Trésorerie!Y$4,'2023-08'!$F:$F,Trésorerie!$B29) -> 0 | Z29: =-SUMIFS('2023-09'!$M:$M,'2023-09'!$E:$E,Trésorerie!Z$4,'2023-09'!$F:$F,Trésorerie!$B29)+SUMIFS('2023-09'!$N:$N,'2023-09'!$E:$E,Trésorerie!Z$4,'2023-09'!$F:$F,Trésorerie!$B29) -> 0 | AA29: =-SUMIFS('2023-10'!$M:$M,'2023-10'!$E:$E,Trésorerie!AA$4,'2023-10'!$F:$F,Trésorerie!$B29)+SUMIFS('2023-10'!$N:$N,'2023-10'!$E:$E,Trésorerie!AA$4,'2023-10'!$F:$F,Trésorerie!$B29) -> 1600 | AB29: =IF(SUM($E29:O29)>SUM($R29:AA29),SUM($E29:O29)-SUM($R29:AA29),0) -> 0 | AC29: =IF(SUM($E29:P29)>SUM($R29:AB29),SUM($E29:P29)-SUM($R29:AB29),0) -> 0
A30: =SUM(E30:P30) -> 1648.17 | B30: 771300 | C30: PRODUITS EXCEPT. DE GESTION | D30: Entrée | E30: =-SUMIFS('2022'!$M:$M,'2022'!$E:$E,Trésorerie!E$4,'2022'!$F:$F,Trésorerie!$B30)+SUMIFS('2022'!$N:$N,'2022'!$E:$E,Trésorerie!E$4,'2022'!$F:$F,Trésorerie!$B30) -> 0 | F30: =-SUMIFS('2022'!$M:$M,'2022'!$E:$E,Trésorerie!F$4,'2022'!$F:$F,Trésorerie!$B30)+SUMIFS('2022'!$N:$N,'2022'!$E:$E,Trésorerie!F$4,'2022'!$F:$F,Trésorerie!$B30) -> 0 | G30: =-SUMIFS('2022'!$M:$M,'2022'!$E:$E,Trésorerie!G$4,'2022'!$F:$F,Trésorerie!$B30)+SUMIFS('2022'!$N:$N,'2022'!$E:$E,Trésorerie!G$4,'2022'!$F:$F,Trésorerie!$B30) -> 0 | H30: =-SUMIFS('2022'!$M:$M,'2022'!$E:$E,Trésorerie!H$4,'2022'!$F:$F,Trésorerie!$B30)+SUMIFS('2022'!$N:$N,'2022'!$E:$E,Trésorerie!H$4,'2022'!$F:$F,Trésorerie!$B30) -> 648.17 | I30: =-SUMIFS('2022'!$M:$M,'2022'!$E:$E,Trésorerie!I$4,'2022'!$F:$F,Trésorerie!$B30)+SUMIFS('2022'!$N:$N,'2022'!$E:$E,Trésorerie!I$4,'2022'!$F:$F,Trésorerie!$B30) -> 1000 | J30: =-SUMIFS('2022'!$M:$M,'2022'!$E:$E,Trésorerie!J$4,'2022'!$F:$F,Trésorerie!$B30)+SUMIFS('2022'!$N:$N,'2022'!$E:$E,Trésorerie!J$4,'2022'!$F:$F,Trésorerie!$B30) -> 0 | K30: =-SUMIFS('2022'!$M:$M,'2022'!$E:$E,Trésorerie!K$4,'2022'!$F:$F,Trésorerie!$B30)+SUMIFS('2022'!$N:$N,'2022'!$E:$E,Trésorerie!K$4,'2022'!$F:$F,Trésorerie!$B30) -> 0 | L30: =-SUMIFS('2022'!$M:$M,'2022'!$E:$E,Trésorerie!L$4,'2022'!$F:$F,Trésorerie!$B30)+SUMIFS('2022'!$N:$N,'2022'!$E:$E,Trésorerie!L$4,'2022'!$F:$F,Trésorerie!$B30) -> 0 | ... P30: =-SUMIFS('2022'!$M:$M,'2022'!$E:$E,Trésorerie!P$4,'2022'!$F:$F,Trésorerie!$B30)+SUMIFS('2022'!$N:$N,'2022'!$E:$E,Trésorerie!P$4,'2022'!$F:$F,Trésorerie!$B30) -> 0 | R30: =-SUMIFS('2023-01'!$M:$M,'2023-01'!$E:$E,Trésorerie!R$4,'2023-01'!$F:$F,Trésorerie!$B30)+SUMIFS('2023-01'!$N:$N,'2023-01'!$E:$E,Trésorerie!R$4,'2023-01'!$F:$F,Trésorerie!$B30) -> 0 | S30: =-SUMIFS('2023-02'!$M:$M,'2023-02'!$E:$E,Trésorerie!S$4,'2023-02'!$F:$F,Trésorerie!$B30)+SUMIFS('2023-02'!$N:$N,'2023-02'!$E:$E,Trésorerie!S$4,'2023-02'!$F:$F,Trésorerie!$B30) -> 0 | T30: =-SUMIFS('2023-03'!$M:$M,'2023-03'!$E:$E,Trésorerie!T$4,'2023-03'!$F:$F,Trésorerie!$B30)+SUMIFS('2023-03'!$N:$N,'2023-03'!$E:$E,Trésorerie!T$4,'2023-03'!$F:$F,Trésorerie!$B30) -> 0 | U30: =-SUMIFS('2023-04'!$M:$M,'2023-04'!$E:$E,Trésorerie!U$4,'2023-04'!$F:$F,Trésorerie!$B30)+SUMIFS('2023-04'!$N:$N,'2023-04'!$E:$E,Trésorerie!U$4,'2023-04'!$F:$F,Trésorerie!$B30) -> 0 | V30: =-SUMIFS('2023-05'!$M:$M,'2023-05'!$E:$E,Trésorerie!V$4,'2023-05'!$F:$F,Trésorerie!$B30)+SUMIFS('2023-05'!$N:$N,'2023-05'!$E:$E,Trésorerie!V$4,'2023-05'!$F:$F,Trésorerie!$B30) -> 0 | W30: =-SUMIFS('2023-06'!$M:$M,'2023-06'!$E:$E,Trésorerie!W$4,'2023-06'!$F:$F,Trésorerie!$B30)+SUMIFS('2023-06'!$N:$N,'2023-06'!$E:$E,Trésorerie!W$4,'2023-06'!$F:$F,Trésorerie!$B30) -> 0 | X30: =-SUMIFS('2023-07'!$M:$M,'2023-07'!$E:$E,Trésorerie!X$4,'2023-07'!$F:$F,Trésorerie!$B30)+SUMIFS('2023-07'!$N:$N,'2023-07'!$E:$E,Trésorerie!X$4,'2023-07'!$F:$F,Trésorerie!$B30) -> 0 | Y30: =-SUMIFS('2023-08'!$M:$M,'2023-08'!$E:$E,Trésorerie!Y$4,'2023-08'!$F:$F,Trésorerie!$B30)+SUMIFS('2023-08'!$N:$N,'2023-08'!$E:$E,Trésorerie!Y$4,'2023-08'!$F:$F,Trésorerie!$B30) -> 0 | Z30: =-SUMIFS('2023-09'!$M:$M,'2023-09'!$E:$E,Trésorerie!Z$4,'2023-09'!$F:$F,Trésorerie!$B30)+SUMIFS('2023-09'!$N:$N,'2023-09'!$E:$E,Trésorerie!Z$4,'2023-09'!$F:$F,Trésorerie!$B30) -> 0 | AA30: =-SUMIFS('2023-10'!$M:$M,'2023-10'!$E:$E,Trésorerie!AA$4,'2023-10'!$F:$F,Trésorerie!$B30)+SUMIFS('2023-10'!$N:$N,'2023-10'!$E:$E,Trésorerie!AA$4,'2023-10'!$F:$F,Trésorerie!$B30) -> 2103.01 | AB30: =IF(SUM($E30:O30)>SUM($R30:AA30),SUM($E30:O30)-SUM($R30:AA30),0) -> 0 | AC30: =IF(SUM($E30:P30)>SUM($R30:AB30),SUM($E30:P30)-SUM($R30:AB30),0) -> 0
A31: =SUM(E31:P31) -> 1466.5 | B31: 706105 | C31: PART. USAGERS HORS FACTURATION. | D31: Entrée | E31: =-SUMIFS('2022'!$M:$M,'2022'!$E:$E,Trésorerie!E$4,'2022'!$F:$F,Trésorerie!$B31)+SUMIFS('2022'!$N:$N,'2022'!$E:$E,Trésorerie!E$4,'2022'!$F:$F,Trésorerie!$B31) -> 0 | F31: =-SUMIFS('2022'!$M:$M,'2022'!$E:$E,Trésorerie!F$4,'2022'!$F:$F,Trésorerie!$B31)+SUMIFS('2022'!$N:$N,'2022'!$E:$E,Trésorerie!F$4,'2022'!$F:$F,Trésorerie!$B31) -> 0 | G31: =-SUMIFS('2022'!$M:$M,'2022'!$E:$E,Trésorerie!G$4,'2022'!$F:$F,Trésorerie!$B31)+SUMIFS('2022'!$N:$N,'2022'!$E:$E,Trésorerie!G$4,'2022'!$F:$F,Trésorerie!$B31) -> 0 | H31: =-SUMIFS('2022'!$M:$M,'2022'!$E:$E,Trésorerie!H$4,'2022'!$F:$F,Trésorerie!$B31)+SUMIFS('2022'!$N:$N,'2022'!$E:$E,Trésorerie!H$4,'2022'!$F:$F,Trésorerie!$B31) -> 0 | I31: =-SUMIFS('2022'!$M:$M,'2022'!$E:$E,Trésorerie!I$4,'2022'!$F:$F,Trésorerie!$B31)+SUMIFS('2022'!$N:$N,'2022'!$E:$E,Trésorerie!I$4,'2022'!$F:$F,Trésorerie!$B31) -> 736.5 | J31: =-SUMIFS('2022'!$M:$M,'2022'!$E:$E,Trésorerie!J$4,'2022'!$F:$F,Trésorerie!$B31)+SUMIFS('2022'!$N:$N,'2022'!$E:$E,Trésorerie!J$4,'2022'!$F:$F,Trésorerie!$B31) -> 0 | K31: =-SUMIFS('2022'!$M:$M,'2022'!$E:$E,Trésorerie!K$4,'2022'!$F:$F,Trésorerie!$B31)+SUMIFS('2022'!$N:$N,'2022'!$E:$E,Trésorerie!K$4,'2022'!$F:$F,Trésorerie!$B31) -> 730 | L31: =-SUMIFS('2022'!$M:$M,'2022'!$E:$E,Trésorerie!L$4,'2022'!$F:$F,Trésorerie!$B31)+SUMIFS('2022'!$N:$N,'2022'!$E:$E,Trésorerie!L$4,'2022'!$F:$F,Trésorerie!$B31) -> 0 | ... P31: =-SUMIFS('2022'!$M:$M,'2022'!$E:$E,Trésorerie!P$4,'2022'!$F:$F,Trésorerie!$B31)+SUMIFS('2022'!$N:$N,'2022'!$E:$E,Trésorerie!P$4,'2022'!$F:$F,Trésorerie!$B31) -> 0 | R31: =-SUMIFS('2023-01'!$M:$M,'2023-01'!$E:$E,Trésorerie!R$4,'2023-01'!$F:$F,Trésorerie!$B31)+SUMIFS('2023-01'!$N:$N,'2023-01'!$E:$E,Trésorerie!R$4,'2023-01'!$F:$F,Trésorerie!$B31) -> 0 | S31: =-SUMIFS('2023-02'!$M:$M,'2023-02'!$E:$E,Trésorerie!S$4,'2023-02'!$F:$F,Trésorerie!$B31)+SUMIFS('2023-02'!$N:$N,'2023-02'!$E:$E,Trésorerie!S$4,'2023-02'!$F:$F,Trésorerie!$B31) -> 0 | T31: =-SUMIFS('2023-03'!$M:$M,'2023-03'!$E:$E,Trésorerie!T$4,'2023-03'!$F:$F,Trésorerie!$B31)+SUMIFS('2023-03'!$N:$N,'2023-03'!$E:$E,Trésorerie!T$4,'2023-03'!$F:$F,Trésorerie!$B31) -> 0 | U31: =-SUMIFS('2023-04'!$M:$M,'2023-04'!$E:$E,Trésorerie!U$4,'2023-04'!$F:$F,Trésorerie!$B31)+SUMIFS('2023-04'!$N:$N,'2023-04'!$E:$E,Trésorerie!U$4,'2023-04'!$F:$F,Trésorerie!$B31) -> 0 | V31: =-SUMIFS('2023-05'!$M:$M,'2023-05'!$E:$E,Trésorerie!V$4,'2023-05'!$F:$F,Trésorerie!$B31)+SUMIFS('2023-05'!$N:$N,'2023-05'!$E:$E,Trésorerie!V$4,'2023-05'!$F:$F,Trésorerie!$B31) -> 0 | W31: =-SUMIFS('2023-06'!$M:$M,'2023-06'!$E:$E,Trésorerie!W$4,'2023-06'!$F:$F,Trésorerie!$B31)+SUMIFS('2023-06'!$N:$N,'2023-06'!$E:$E,Trésorerie!W$4,'2023-06'!$F:$F,Trésorerie!$B31) -> 307 | X31: =-SUMIFS('2023-07'!$M:$M,'2023-07'!$E:$E,Trésorerie!X$4,'2023-07'!$F:$F,Trésorerie!$B31)+SUMIFS('2023-07'!$N:$N,'2023-07'!$E:$E,Trésorerie!X$4,'2023-07'!$F:$F,Trésorerie!$B31) -> 357 | Y31: =-SUMIFS('2023-08'!$M:$M,'2023-08'!$E:$E,Trésorerie!Y$4,'2023-08'!$F:$F,Trésorerie!$B31)+SUMIFS('2023-08'!$N:$N,'2023-08'!$E:$E,Trésorerie!Y$4,'2023-08'!$F:$F,Trésorerie!$B31) -> 0 | Z31: =-SUMIFS('2023-09'!$M:$M,'2023-09'!$E:$E,Trésorerie!Z$4,'2023-09'!$F:$F,Trésorerie!$B31)+SUMIFS('2023-09'!$N:$N,'2023-09'!$E:$E,Trésorerie!Z$4,'2023-09'!$F:$F,Trésorerie!$B31) -> -300 | AA31: =-SUMIFS('2023-10'!$M:$M,'2023-10'!$E:$E,Trésorerie!AA$4,'2023-10'!$F:$F,Trésorerie!$B31)+SUMIFS('2023-10'!$N:$N,'2023-10'!$E:$E,Trésorerie!AA$4,'2023-10'!$F:$F,Trésorerie!$B31) -> 264.88 | AB31: =IF(SUM($E31:O31)>SUM($R31:AA31),SUM($E31:O31)-SUM($R31:AA31),0) -> 837.62 | AC31: =IF(SUM($E31:P31)>SUM($R31:AB31),SUM($E31:P31)-SUM($R31:AB31),0) -> 0
... A33: =SUM(E33:P33) -> 963.27 | B33: 791400 | C33: INDEMNITE ACTIVITE PARTIELLE | D33: Entrée | E33: =-SUMIFS('2022'!$M:$M,'2022'!$E:$E,Trésorerie!E$4,'2022'!$F:$F,Trésorerie!$B33)+SUMIFS('2022'!$N:$N,'2022'!$E:$E,Trésorerie!E$4,'2022'!$F:$F,Trésorerie!$B33) -> 963.27 | F33: =-SUMIFS('2022'!$M:$M,'2022'!$E:$E,Trésorerie!F$4,'2022'!$F:$F,Trésorerie!$B33)+SUMIFS('2022'!$N:$N,'2022'!$E:$E,Trésorerie!F$4,'2022'!$F:$F,Trésorerie!$B33) -> 0 | G33: =-SUMIFS('2022'!$M:$M,'2022'!$E:$E,Trésorerie!G$4,'2022'!$F:$F,Trésorerie!$B33)+SUMIFS('2022'!$N:$N,'2022'!$E:$E,Trésorerie!G$4,'2022'!$F:$F,Trésorerie!$B33) -> 0 | H33: =-SUMIFS('2022'!$M:$M,'2022'!$E:$E,Trésorerie!H$4,'2022'!$F:$F,Trésorerie!$B33)+SUMIFS('2022'!$N:$N,'2022'!$E:$E,Trésorerie!H$4,'2022'!$F:$F,Trésorerie!$B33) -> 0 | I33: =-SUMIFS('2022'!$M:$M,'2022'!$E:$E,Trésorerie!I$4,'2022'!$F:$F,Trésorerie!$B33)+SUMIFS('2022'!$N:$N,'2022'!$E:$E,Trésorerie!I$4,'2022'!$F:$F,Trésorerie!$B33) -> 0 | J33: =-SUMIFS('2022'!$M:$M,'2022'!$E:$E,Trésorerie!J$4,'2022'!$F:$F,Trésorerie!$B33)+SUMIFS('2022'!$N:$N,'2022'!$E:$E,Trésorerie!J$4,'2022'!$F:$F,Trésorerie!$B33) -> 0 | K33: =-SUMIFS('2022'!$M:$M,'2022'!$E:$E,Trésorerie!K$4,'2022'!$F:$F,Trésorerie!$B33)+SUMIFS('2022'!$N:$N,'2022'!$E:$E,Trésorerie!K$4,'2022'!$F:$F,Trésorerie!$B33) -> 0 | L33: =-SUMIFS('2022'!$M:$M,'2022'!$E:$E,Trésorerie!L$4,'2022'!$F:$F,Trésorerie!$B33)+SUMIFS('2022'!$N:$N,'2022'!$E:$E,Trésorerie!L$4,'2022'!$F:$F,Trésorerie!$B33) -> 0 | ... P33: =-SUMIFS('2022'!$M:$M,'2022'!$E:$E,Trésorerie!P$4,'2022'!$F:$F,Trésorerie!$B33)+SUMIFS('2022'!$N:$N,'2022'!$E:$E,Trésorerie!P$4,'2022'!$F:$F,Trésorerie!$B33) -> 0 | R33: =-SUMIFS('2023-01'!$M:$M,'2023-01'!$E:$E,Trésorerie!R$4,'2023-01'!$F:$F,Trésorerie!$B33)+SUMIFS('2023-01'!$N:$N,'2023-01'!$E:$E,Trésorerie!R$4,'2023-01'!$F:$F,Trésorerie!$B33) -> 0 | S33: =-SUMIFS('2023-02'!$M:$M,'2023-02'!$E:$E,Trésorerie!S$4,'2023-02'!$F:$F,Trésorerie!$B33)+SUMIFS('2023-02'!$N:$N,'2023-02'!$E:$E,Trésorerie!S$4,'2023-02'!$F:$F,Trésorerie!$B33) -> 0 | T33: =-SUMIFS('2023-03'!$M:$M,'2023-03'!$E:$E,Trésorerie!T$4,'2023-03'!$F:$F,Trésorerie!$B33)+SUMIFS('2023-03'!$N:$N,'2023-03'!$E:$E,Trésorerie!T$4,'2023-03'!$F:$F,Trésorerie!$B33) -> 0 | U33: =-SUMIFS('2023-04'!$M:$M,'2023-04'!$E:$E,Trésorerie!U$4,'2023-04'!$F:$F,Trésorerie!$B33)+SUMIFS('2023-04'!$N:$N,'2023-04'!$E:$E,Trésorerie!U$4,'2023-04'!$F:$F,Trésorerie!$B33) -> 0 | V33: =-SUMIFS('2023-05'!$M:$M,'2023-05'!$E:$E,Trésorerie!V$4,'2023-05'!$F:$F,Trésorerie!$B33)+SUMIFS('2023-05'!$N:$N,'2023-05'!$E:$E,Trésorerie!V$4,'2023-05'!$F:$F,Trésorerie!$B33) -> 0 | W33: =-SUMIFS('2023-06'!$M:$M,'2023-06'!$E:$E,Trésorerie!W$4,'2023-06'!$F:$F,Trésorerie!$B33)+SUMIFS('2023-06'!$N:$N,'2023-06'!$E:$E,Trésorerie!W$4,'2023-06'!$F:$F,Trésorerie!$B33) -> 0 | X33: =-SUMIFS('2023-07'!$M:$M,'2023-07'!$E:$E,Trésorerie!X$4,'2023-07'!$F:$F,Trésorerie!$B33)+SUMIFS('2023-07'!$N:$N,'2023-07'!$E:$E,Trésorerie!X$4,'2023-07'!$F:$F,Trésorerie!$B33) -> 0 | Y33: =-SUMIFS('2023-08'!$M:$M,'2023-08'!$E:$E,Trésorerie!Y$4,'2023-08'!$F:$F,Trésorerie!$B33)+SUMIFS('2023-08'!$N:$N,'2023-08'!$E:$E,Trésorerie!Y$4,'2023-08'!$F:$F,Trésorerie!$B33) -> 0 | Z33: =-SUMIFS('2023-09'!$M:$M,'2023-09'!$E:$E,Trésorerie!Z$4,'2023-09'!$F:$F,Trésorerie!$B33)+SUMIFS('2023-09'!$N:$N,'2023-09'!$E:$E,Trésorerie!Z$4,'2023-09'!$F:$F,Trésorerie!$B33) -> 0 | AA33: =-SUMIFS('2023-10'!$M:$M,'2023-10'!$E:$E,Trésorerie!AA$4,'2023-10'!$F:$F,Trésorerie!$B33)+SUMIFS('2023-10'!$N:$N,'2023-10'!$E:$E,Trésorerie!AA$4,'2023-10'!$F:$F,Trésorerie!$B33) -> 0 | AB33: =IF(SUM($E33:O33)>SUM($R33:AA33),SUM($E33:O33)-SUM($R33:AA33),0) -> 963.27 | AC33: =IF(SUM($E33:P33)>SUM($R33:AB33),SUM($E33:P33)-SUM($R33:AB33),0) -> 0
A34: =SUM(E34:P34) -> 0 | B34: 706100 | D34: Entrée | E34: =-SUMIFS('2022'!$M:$M,'2022'!$E:$E,Trésorerie!E$4,'2022'!$F:$F,Trésorerie!$B34)+SUMIFS('2022'!$N:$N,'2022'!$E:$E,Trésorerie!E$4,'2022'!$F:$F,Trésorerie!$B34) -> 0 | F34: =-SUMIFS('2022'!$M:$M,'2022'!$E:$E,Trésorerie!F$4,'2022'!$F:$F,Trésorerie!$B34)+SUMIFS('2022'!$N:$N,'2022'!$E:$E,Trésorerie!F$4,'2022'!$F:$F,Trésorerie!$B34) -> 0 | G34: =-SUMIFS('2022'!$M:$M,'2022'!$E:$E,Trésorerie!G$4,'2022'!$F:$F,Trésorerie!$B34)+SUMIFS('2022'!$N:$N,'2022'!$E:$E,Trésorerie!G$4,'2022'!$F:$F,Trésorerie!$B34) -> 0 | H34: =-SUMIFS('2022'!$M:$M,'2022'!$E:$E,Trésorerie!H$4,'2022'!$F:$F,Trésorerie!$B34)+SUMIFS('2022'!$N:$N,'2022'!$E:$E,Trésorerie!H$4,'2022'!$F:$F,Trésorerie!$B34) -> 0 | I34: =-SUMIFS('2022'!$M:$M,'2022'!$E:$E,Trésorerie!I$4,'2022'!$F:$F,Trésorerie!$B34)+SUMIFS('2022'!$N:$N,'2022'!$E:$E,Trésorerie!I$4,'2022'!$F:$F,Trésorerie!$B34) -> 0 | J34: =-SUMIFS('2022'!$M:$M,'2022'!$E:$E,Trésorerie!J$4,'2022'!$F:$F,Trésorerie!$B34)+SUMIFS('2022'!$N:$N,'2022'!$E:$E,Trésorerie!J$4,'2022'!$F:$F,Trésorerie!$B34) -> 0 | K34: =-SUMIFS('2022'!$M:$M,'2022'!$E:$E,Trésorerie!K$4,'2022'!$F:$F,Trésorerie!$B34)+SUMIFS('2022'!$N:$N,'2022'!$E:$E,Trésorerie!K$4,'2022'!$F:$F,Trésorerie!$B34) -> 0 | L34: =-SUMIFS('2022'!$M:$M,'2022'!$E:$E,Trésorerie!L$4,'2022'!$F:$F,Trésorerie!$B34)+SUMIFS('2022'!$N:$N,'2022'!$E:$E,Trésorerie!L$4,'2022'!$F:$F,Trésorerie!$B34) -> 0 | ... P34: =-SUMIFS('2022'!$M:$M,'2022'!$E:$E,Trésorerie!P$4,'2022'!$F:$F,Trésorerie!$B34)+SUMIFS('2022'!$N:$N,'2022'!$E:$E,Trésorerie!P$4,'2022'!$F:$F,Trésorerie!$B34) -> 0 | R34: =-SUMIFS('2023-01'!$M:$M,'2023-01'!$E:$E,Trésorerie!R$4,'2023-01'!$F:$F,Trésorerie!$B34)+SUMIFS('2023-01'!$N:$N,'2023-01'!$E:$E,Trésorerie!R$4,'2023-01'!$F:$F,Trésorerie!$B34) -> 0 | S34: =-SUMIFS('2023-02'!$M:$M,'2023-02'!$E:$E,Trésorerie!S$4,'2023-02'!$F:$F,Trésorerie!$B34)+SUMIFS('2023-02'!$N:$N,'2023-02'!$E:$E,Trésorerie!S$4,'2023-02'!$F:$F,Trésorerie!$B34) -> 0 | T34: =-SUMIFS('2023-03'!$M:$M,'2023-03'!$E:$E,Trésorerie!T$4,'2023-03'!$F:$F,Trésorerie!$B34)+SUMIFS('2023-03'!$N:$N,'2023-03'!$E:$E,Trésorerie!T$4,'2023-03'!$F:$F,Trésorerie!$B34) -> 0 | U34: =-SUMIFS('2023-04'!$M:$M,'2023-04'!$E:$E,Trésorerie!U$4,'2023-04'!$F:$F,Trésorerie!$B34)+SUMIFS('2023-04'!$N:$N,'2023-04'!$E:$E,Trésorerie!U$4,'2023-04'!$F:$F,Trésorerie!$B34) -> 0 | V34: =-SUMIFS('2023-05'!$M:$M,'2023-05'!$E:$E,Trésorerie!V$4,'2023-05'!$F:$F,Trésorerie!$B34)+SUMIFS('2023-05'!$N:$N,'2023-05'!$E:$E,Trésorerie!V$4,'2023-05'!$F:$F,Trésorerie!$B34) -> 0 | W34: =-SUMIFS('2023-06'!$M:$M,'2023-06'!$E:$E,Trésorerie!W$4,'2023-06'!$F:$F,Trésorerie!$B34)+SUMIFS('2023-06'!$N:$N,'2023-06'!$E:$E,Trésorerie!W$4,'2023-06'!$F:$F,Trésorerie!$B34) -> 720 | X34: =-SUMIFS('2023-07'!$M:$M,'2023-07'!$E:$E,Trésorerie!X$4,'2023-07'!$F:$F,Trésorerie!$B34)+SUMIFS('2023-07'!$N:$N,'2023-07'!$E:$E,Trésorerie!X$4,'2023-07'!$F:$F,Trésorerie!$B34) -> 0 | Y34: =-SUMIFS('2023-08'!$M:$M,'2023-08'!$E:$E,Trésorerie!Y$4,'2023-08'!$F:$F,Trésorerie!$B34)+SUMIFS('2023-08'!$N:$N,'2023-08'!$E:$E,Trésorerie!Y$4,'2023-08'!$F:$F,Trésorerie!$B34) -> 0 | Z34: =-SUMIFS('2023-09'!$M:$M,'2023-09'!$E:$E,Trésorerie!Z$4,'2023-09'!$F:$F,Trésorerie!$B34)+SUMIFS('2023-09'!$N:$N,'2023-09'!$E:$E,Trésorerie!Z$4,'2023-09'!$F:$F,Trésorerie!$B34) -> 0 | AA34: =-SUMIFS('2023-10'!$M:$M,'2023-10'!$E:$E,Trésorerie!AA$4,'2023-10'!$F:$F,Trésorerie!$B34)+SUMIFS('2023-10'!$N:$N,'2023-10'!$E:$E,Trésorerie!AA$4,'2023-10'!$F:$F,Trésorerie!$B34) -> 0 | AB34: =IF(SUM($E34:O34)>SUM($R34:AA34),SUM($E34:O34)-SUM($R34:AA34),0) -> 0 | AC34: =IF(SUM($E34:P34)>SUM($R34:AB34),SUM($E34:P34)-SUM($R34:AB34),0) -> 0
A35: =SUM(E35:P35) -> 0 | B35: 791200 | C35: CHORUM PREVOYANCE C+NC | D35: Entrée | E35: =-SUMIFS('2022'!$M:$M,'2022'!$E:$E,Trésorerie!E$4,'2022'!$F:$F,Trésorerie!$B35)+SUMIFS('2022'!$N:$N,'2022'!$E:$E,Trésorerie!E$4,'2022'!$F:$F,Trésorerie!$B35) -> 0 | F35: =-SUMIFS('2022'!$M:$M,'2022'!$E:$E,Trésorerie!F$4,'2022'!$F:$F,Trésorerie!$B35)+SUMIFS('2022'!$N:$N,'2022'!$E:$E,Trésorerie!F$4,'2022'!$F:$F,Trésorerie!$B35) -> 0 | G35: =-SUMIFS('2022'!$M:$M,'2022'!$E:$E,Trésorerie!G$4,'2022'!$F:$F,Trésorerie!$B35)+SUMIFS('2022'!$N:$N,'2022'!$E:$E,Trésorerie!G$4,'2022'!$F:$F,Trésorerie!$B35) -> 0 | H35: =-SUMIFS('2022'!$M:$M,'2022'!$E:$E,Trésorerie!H$4,'2022'!$F:$F,Trésorerie!$B35)+SUMIFS('2022'!$N:$N,'2022'!$E:$E,Trésorerie!H$4,'2022'!$F:$F,Trésorerie!$B35) -> 0 | I35: =-SUMIFS('2022'!$M:$M,'2022'!$E:$E,Trésorerie!I$4,'2022'!$F:$F,Trésorerie!$B35)+SUMIFS('2022'!$N:$N,'2022'!$E:$E,Trésorerie!I$4,'2022'!$F:$F,Trésorerie!$B35) -> 0 | J35: =-SUMIFS('2022'!$M:$M,'2022'!$E:$E,Trésorerie!J$4,'2022'!$F:$F,Trésorerie!$B35)+SUMIFS('2022'!$N:$N,'2022'!$E:$E,Trésorerie!J$4,'2022'!$F:$F,Trésorerie!$B35) -> 0 | K35: =-SUMIFS('2022'!$M:$M,'2022'!$E:$E,Trésorerie!K$4,'2022'!$F:$F,Trésorerie!$B35)+SUMIFS('2022'!$N:$N,'2022'!$E:$E,Trésorerie!K$4,'2022'!$F:$F,Trésorerie!$B35) -> 0 | L35: =-SUMIFS('2022'!$M:$M,'2022'!$E:$E,Trésorerie!L$4,'2022'!$F:$F,Trésorerie!$B35)+SUMIFS('2022'!$N:$N,'2022'!$E:$E,Trésorerie!L$4,'2022'!$F:$F,Trésorerie!$B35) -> 0 | ... P35: =-SUMIFS('2022'!$M:$M,'2022'!$E:$E,Trésorerie!P$4,'2022'!$F:$F,Trésorerie!$B35)+SUMIFS('2022'!$N:$N,'2022'!$E:$E,Trésorerie!P$4,'2022'!$F:$F,Trésorerie!$B35) -> 0 | R35: =-SUMIFS('2023-01'!$M:$M,'2023-01'!$E:$E,Trésorerie!R$4,'2023-01'!$F:$F,Trésorerie!$B35)+SUMIFS('2023-01'!$N:$N,'2023-01'!$E:$E,Trésorerie!R$4,'2023-01'!$F:$F,Trésorerie!$B35) -> 0 | S35: =-SUMIFS('2023-02'!$M:$M,'2023-02'!$E:$E,Trésorerie!S$4,'2023-02'!$F:$F,Trésorerie!$B35)+SUMIFS('2023-02'!$N:$N,'2023-02'!$E:$E,Trésorerie!S$4,'2023-02'!$F:$F,Trésorerie!$B35) -> 0 | T35: =-SUMIFS('2023-03'!$M:$M,'2023-03'!$E:$E,Trésorerie!T$4,'2023-03'!$F:$F,Trésorerie!$B35)+SUMIFS('2023-03'!$N:$N,'2023-03'!$E:$E,Trésorerie!T$4,'2023-03'!$F:$F,Trésorerie!$B35) -> 0 | U35: =-SUMIFS('2023-04'!$M:$M,'2023-04'!$E:$E,Trésorerie!U$4,'2023-04'!$F:$F,Trésorerie!$B35)+SUMIFS('2023-04'!$N:$N,'2023-04'!$E:$E,Trésorerie!U$4,'2023-04'!$F:$F,Trésorerie!$B35) -> 0 | V35: =-SUMIFS('2023-05'!$M:$M,'2023-05'!$E:$E,Trésorerie!V$4,'2023-05'!$F:$F,Trésorerie!$B35)+SUMIFS('2023-05'!$N:$N,'2023-05'!$E:$E,Trésorerie!V$4,'2023-05'!$F:$F,Trésorerie!$B35) -> 0 | W35: =-SUMIFS('2023-06'!$M:$M,'2023-06'!$E:$E,Trésorerie!W$4,'2023-06'!$F:$F,Trésorerie!$B35)+SUMIFS('2023-06'!$N:$N,'2023-06'!$E:$E,Trésorerie!W$4,'2023-06'!$F:$F,Trésorerie!$B35) -> 0 | X35: =-SUMIFS('2023-07'!$M:$M,'2023-07'!$E:$E,Trésorerie!X$4,'2023-07'!$F:$F,Trésorerie!$B35)+SUMIFS('2023-07'!$N:$N,'2023-07'!$E:$E,Trésorerie!X$4,'2023-07'!$F:$F,Trésorerie!$B35) -> 0 | Y35: =-SUMIFS('2023-08'!$M:$M,'2023-08'!$E:$E,Trésorerie!Y$4,'2023-08'!$F:$F,Trésorerie!$B35)+SUMIFS('2023-08'!$N:$N,'2023-08'!$E:$E,Trésorerie!Y$4,'2023-08'!$F:$F,Trésorerie!$B35) -> 0 | Z35: =-SUMIFS('2023-09'!$M:$M,'2023-09'!$E:$E,Trésorerie!Z$4,'2023-09'!$F:$F,Trésorerie!$B35)+SUMIFS('2023-09'!$N:$N,'2023-09'!$E:$E,Trésorerie!Z$4,'2023-09'!$F:$F,Trésorerie!$B35) -> 0 | AA35: =-SUMIFS('2023-10'!$M:$M,'2023-10'!$E:$E,Trésorerie!AA$4,'2023-10'!$F:$F,Trésorerie!$B35)+SUMIFS('2023-10'!$N:$N,'2023-10'!$E:$E,Trésorerie!AA$4,'2023-10'!$F:$F,Trésorerie!$B35) -> 0 | AB35: =IF(SUM($E35:O35)>SUM($R35:AA35),SUM($E35:O35)-SUM($R35:AA35),0) -> 0 | AC35: =IF(SUM($E35:P35)>SUM($R35:AB35),SUM($E35:P35)-SUM($R35:AB35),0) -> 0
A36: =SUM(E36:P36) -> 0 | B36: 791000 | C36: X | D36: Entrée | E36: =-SUMIFS('2022'!$M:$M,'2022'!$E:$E,Trésorerie!E$4,'2022'!$F:$F,Trésorerie!$B36)+SUMIFS('2022'!$N:$N,'2022'!$E:$E,Trésorerie!E$4,'2022'!$F:$F,Trésorerie!$B36) -> 0 | F36: =-SUMIFS('2022'!$M:$M,'2022'!$E:$E,Trésorerie!F$4,'2022'!$F:$F,Trésorerie!$B36)+SUMIFS('2022'!$N:$N,'2022'!$E:$E,Trésorerie!F$4,'2022'!$F:$F,Trésorerie!$B36) -> 0 | G36: =-SUMIFS('2022'!$M:$M,'2022'!$E:$E,Trésorerie!G$4,'2022'!$F:$F,Trésorerie!$B36)+SUMIFS('2022'!$N:$N,'2022'!$E:$E,Trésorerie!G$4,'2022'!$F:$F,Trésorerie!$B36) -> 0 | H36: =-SUMIFS('2022'!$M:$M,'2022'!$E:$E,Trésorerie!H$4,'2022'!$F:$F,Trésorerie!$B36)+SUMIFS('2022'!$N:$N,'2022'!$E:$E,Trésorerie!H$4,'2022'!$F:$F,Trésorerie!$B36) -> 0 | I36: =-SUMIFS('2022'!$M:$M,'2022'!$E:$E,Trésorerie!I$4,'2022'!$F:$F,Trésorerie!$B36)+SUMIFS('2022'!$N:$N,'2022'!$E:$E,Trésorerie!I$4,'2022'!$F:$F,Trésorerie!$B36) -> 0 | J36: =-SUMIFS('2022'!$M:$M,'2022'!$E:$E,Trésorerie!J$4,'2022'!$F:$F,Trésorerie!$B36)+SUMIFS('2022'!$N:$N,'2022'!$E:$E,Trésorerie!J$4,'2022'!$F:$F,Trésorerie!$B36) -> 0 | K36: =-SUMIFS('2022'!$M:$M,'2022'!$E:$E,Trésorerie!K$4,'2022'!$F:$F,Trésorerie!$B36)+SUMIFS('2022'!$N:$N,'2022'!$E:$E,Trésorerie!K$4,'2022'!$F:$F,Trésorerie!$B36) -> 0 | L36: =-SUMIFS('2022'!$M:$M,'2022'!$E:$E,Trésorerie!L$4,'2022'!$F:$F,Trésorerie!$B36)+SUMIFS('2022'!$N:$N,'2022'!$E:$E,Trésorerie!L$4,'2022'!$F:$F,Trésorerie!$B36) -> 0 | ... P36: =-SUMIFS('2022'!$M:$M,'2022'!$E:$E,Trésorerie!P$4,'2022'!$F:$F,Trésorerie!$B36)+SUMIFS('2022'!$N:$N,'2022'!$E:$E,Trésorerie!P$4,'2022'!$F:$F,Trésorerie!$B36) -> 0 | R36: =-SUMIFS('2023-01'!$M:$M,'2023-01'!$E:$E,Trésorerie!R$4,'2023-01'!$F:$F,Trésorerie!$B36)+SUMIFS('2023-01'!$N:$N,'2023-01'!$E:$E,Trésorerie!R$4,'2023-01'!$F:$F,Trésorerie!$B36) -> 0 | S36: =-SUMIFS('2023-02'!$M:$M,'2023-02'!$E:$E,Trésorerie!S$4,'2023-02'!$F:$F,Trésorerie!$B36)+SUMIFS('2023-02'!$N:$N,'2023-02'!$E:$E,Trésorerie!S$4,'2023-02'!$F:$F,Trésorerie!$B36) -> 0 | T36: =-SUMIFS('2023-03'!$M:$M,'2023-03'!$E:$E,Trésorerie!T$4,'2023-03'!$F:$F,Trésorerie!$B36)+SUMIFS('2023-03'!$N:$N,'2023-03'!$E:$E,Trésorerie!T$4,'2023-03'!$F:$F,Trésorerie!$B36) -> 0 | U36: =-SUMIFS('2023-04'!$M:$M,'2023-04'!$E:$E,Trésorerie!U$4,'2023-04'!$F:$F,Trésorerie!$B36)+SUMIFS('2023-04'!$N:$N,'2023-04'!$E:$E,Trésorerie!U$4,'2023-04'!$F:$F,Trésorerie!$B36) -> 0 | V36: =-SUMIFS('2023-05'!$M:$M,'2023-05'!$E:$E,Trésorerie!V$4,'2023-05'!$F:$F,Trésorerie!$B36)+SUMIFS('2023-05'!$N:$N,'2023-05'!$E:$E,Trésorerie!V$4,'2023-05'!$F:$F,Trésorerie!$B36) -> 875 | W36: =-SUMIFS('2023-06'!$M:$M,'2023-06'!$E:$E,Trésorerie!W$4,'2023-06'!$F:$F,Trésorerie!$B36)+SUMIFS('2023-06'!$N:$N,'2023-06'!$E:$E,Trésorerie!W$4,'2023-06'!$F:$F,Trésorerie!$B36) -> 0 | X36: =-SUMIFS('2023-07'!$M:$M,'2023-07'!$E:$E,Trésorerie!X$4,'2023-07'!$F:$F,Trésorerie!$B36)+SUMIFS('2023-07'!$N:$N,'2023-07'!$E:$E,Trésorerie!X$4,'2023-07'!$F:$F,Trésorerie!$B36) -> 0 | Y36: =-SUMIFS('2023-08'!$M:$M,'2023-08'!$E:$E,Trésorerie!Y$4,'2023-08'!$F:$F,Trésorerie!$B36)+SUMIFS('2023-08'!$N:$N,'2023-08'!$E:$E,Trésorerie!Y$4,'2023-08'!$F:$F,Trésorerie!$B36) -> 0 | Z36: =-SUMIFS('2023-09'!$M:$M,'2023-09'!$E:$E,Trésorerie!Z$4,'2023-09'!$F:$F,Trésorerie!$B36)+SUMIFS('2023-09'!$N:$N,'2023-09'!$E:$E,Trésorerie!Z$4,'2023-09'!$F:$F,Trésorerie!$B36) -> 0 | AA36: =-SUMIFS('2023-10'!$M:$M,'2023-10'!$E:$E,Trésorerie!AA$4,'2023-10'!$F:$F,Trésorerie!$B36)+SUMIFS('2023-10'!$N:$N,'2023-10'!$E:$E,Trésorerie!AA$4,'2023-10'!$F:$F,Trésorerie!$B36) -> 0 | AB36: =IF(SUM($E36:O36)>SUM($R36:AA36),SUM($E36:O36)-SUM($R36:AA36),0) -> 0 | AC36: =IF(SUM($E36:P36)>SUM($R36:AB36),SUM($E36:P36)-SUM($R36:AB36),0) -> 0
A37: =SUM(E37:P37) -> 750 | B37: 468780 | C37: CARSAT | D37: Entrée | E37: =-SUMIFS('2022'!$M:$M,'2022'!$E:$E,Trésorerie!E$4,'2022'!$F:$F,Trésorerie!$B37)+SUMIFS('2022'!$N:$N,'2022'!$E:$E,Trésorerie!E$4,'2022'!$F:$F,Trésorerie!$B37) -> 0 | F37: =-SUMIFS('2022'!$M:$M,'2022'!$E:$E,Trésorerie!F$4,'2022'!$F:$F,Trésorerie!$B37)+SUMIFS('2022'!$N:$N,'2022'!$E:$E,Trésorerie!F$4,'2022'!$F:$F,Trésorerie!$B37) -> 0 | G37: =-SUMIFS('2022'!$M:$M,'2022'!$E:$E,Trésorerie!G$4,'2022'!$F:$F,Trésorerie!$B37)+SUMIFS('2022'!$N:$N,'2022'!$E:$E,Trésorerie!G$4,'2022'!$F:$F,Trésorerie!$B37) -> 0 | H37: =-SUMIFS('2022'!$M:$M,'2022'!$E:$E,Trésorerie!H$4,'2022'!$F:$F,Trésorerie!$B37)+SUMIFS('2022'!$N:$N,'2022'!$E:$E,Trésorerie!H$4,'2022'!$F:$F,Trésorerie!$B37) -> 0 | I37: =-SUMIFS('2022'!$M:$M,'2022'!$E:$E,Trésorerie!I$4,'2022'!$F:$F,Trésorerie!$B37)+SUMIFS('2022'!$N:$N,'2022'!$E:$E,Trésorerie!I$4,'2022'!$F:$F,Trésorerie!$B37) -> 0 | J37: =-SUMIFS('2022'!$M:$M,'2022'!$E:$E,Trésorerie!J$4,'2022'!$F:$F,Trésorerie!$B37)+SUMIFS('2022'!$N:$N,'2022'!$E:$E,Trésorerie!J$4,'2022'!$F:$F,Trésorerie!$B37) -> 0 | K37: =-SUMIFS('2022'!$M:$M,'2022'!$E:$E,Trésorerie!K$4,'2022'!$F:$F,Trésorerie!$B37)+SUMIFS('2022'!$N:$N,'2022'!$E:$E,Trésorerie!K$4,'2022'!$F:$F,Trésorerie!$B37) -> 0 | L37: =-SUMIFS('2022'!$M:$M,'2022'!$E:$E,Trésorerie!L$4,'2022'!$F:$F,Trésorerie!$B37)+SUMIFS('2022'!$N:$N,'2022'!$E:$E,Trésorerie!L$4,'2022'!$F:$F,Trésorerie!$B37) -> 0 | ... P37: =-SUMIFS('2022'!$M:$M,'2022'!$E:$E,Trésorerie!P$4,'2022'!$F:$F,Trésorerie!$B37)+SUMIFS('2022'!$N:$N,'2022'!$E:$E,Trésorerie!P$4,'2022'!$F:$F,Trésorerie!$B37) -> 0 | R37: =-SUMIFS('2023-01'!$M:$M,'2023-01'!$E:$E,Trésorerie!R$4,'2023-01'!$F:$F,Trésorerie!$B37)+SUMIFS('2023-01'!$N:$N,'2023-01'!$E:$E,Trésorerie!R$4,'2023-01'!$F:$F,Trésorerie!$B37) -> 0 | S37: =-SUMIFS('2023-02'!$M:$M,'2023-02'!$E:$E,Trésorerie!S$4,'2023-02'!$F:$F,Trésorerie!$B37)+SUMIFS('2023-02'!$N:$N,'2023-02'!$E:$E,Trésorerie!S$4,'2023-02'!$F:$F,Trésorerie!$B37) -> 0 | T37: =-SUMIFS('2023-03'!$M:$M,'2023-03'!$E:$E,Trésorerie!T$4,'2023-03'!$F:$F,Trésorerie!$B37)+SUMIFS('2023-03'!$N:$N,'2023-03'!$E:$E,Trésorerie!T$4,'2023-03'!$F:$F,Trésorerie!$B37) -> 0 | U37: =-SUMIFS('2023-04'!$M:$M,'2023-04'!$E:$E,Trésorerie!U$4,'2023-04'!$F:$F,Trésorerie!$B37)+SUMIFS('2023-04'!$N:$N,'2023-04'!$E:$E,Trésorerie!U$4,'2023-04'!$F:$F,Trésorerie!$B37) -> 0 | V37: =-SUMIFS('2023-05'!$M:$M,'2023-05'!$E:$E,Trésorerie!V$4,'2023-05'!$F:$F,Trésorerie!$B37)+SUMIFS('2023-05'!$N:$N,'2023-05'!$E:$E,Trésorerie!V$4,'2023-05'!$F:$F,Trésorerie!$B37) -> 0 | W37: =-SUMIFS('2023-06'!$M:$M,'2023-06'!$E:$E,Trésorerie!W$4,'2023-06'!$F:$F,Trésorerie!$B37)+SUMIFS('2023-06'!$N:$N,'2023-06'!$E:$E,Trésorerie!W$4,'2023-06'!$F:$F,Trésorerie!$B37) -> 0 | X37: =-SUMIFS('2023-07'!$M:$M,'2023-07'!$E:$E,Trésorerie!X$4,'2023-07'!$F:$F,Trésorerie!$B37)+SUMIFS('2023-07'!$N:$N,'2023-07'!$E:$E,Trésorerie!X$4,'2023-07'!$F:$F,Trésorerie!$B37) -> 0 | Y37: =-SUMIFS('2023-08'!$M:$M,'2023-08'!$E:$E,Trésorerie!Y$4,'2023-08'!$F:$F,Trésorerie!$B37)+SUMIFS('2023-08'!$N:$N,'2023-08'!$E:$E,Trésorerie!Y$4,'2023-08'!$F:$F,Trésorerie!$B37) -> 0 | Z37: =-SUMIFS('2023-09'!$M:$M,'2023-09'!$E:$E,Trésorerie!Z$4,'2023-09'!$F:$F,Trésorerie!$B37)+SUMIFS('2023-09'!$N:$N,'2023-09'!$E:$E,Trésorerie!Z$4,'2023-09'!$F:$F,Trésorerie!$B37) -> 0 | AA37: =-SUMIFS('2023-10'!$M:$M,'2023-10'!$E:$E,Trésorerie!AA$4,'2023-10'!$F:$F,Trésorerie!$B37)+SUMIFS('2023-10'!$N:$N,'2023-10'!$E:$E,Trésorerie!AA$4,'2023-10'!$F:$F,Trésorerie!$B37) -> 0 | AB37: =IF(SUM($E37:O37)>SUM($R37:AA37),SUM($E37:O37)-SUM($R37:AA37),0) -> 750 | AC37: =IF(SUM($E37:P37)>SUM($R37:AB37),SUM($E37:P37)-SUM($R37:AB37),0) -> 0
A38: =SUM(E38:P38) -> 373.49 | B38: 468736 | C38: FORUM REFUGIE | D38: Entrée | E38: =-SUMIFS('2022'!$M:$M,'2022'!$E:$E,Trésorerie!E$4,'2022'!$F:$F,Trésorerie!$B38)+SUMIFS('2022'!$N:$N,'2022'!$E:$E,Trésorerie!E$4,'2022'!$F:$F,Trésorerie!$B38) -> 0 | F38: =-SUMIFS('2022'!$M:$M,'2022'!$E:$E,Trésorerie!F$4,'2022'!$F:$F,Trésorerie!$B38)+SUMIFS('2022'!$N:$N,'2022'!$E:$E,Trésorerie!F$4,'2022'!$F:$F,Trésorerie!$B38) -> 31.57 | G38: =-SUMIFS('2022'!$M:$M,'2022'!$E:$E,Trésorerie!G$4,'2022'!$F:$F,Trésorerie!$B38)+SUMIFS('2022'!$N:$N,'2022'!$E:$E,Trésorerie!G$4,'2022'!$F:$F,Trésorerie!$B38) -> 0 | H38: =-SUMIFS('2022'!$M:$M,'2022'!$E:$E,Trésorerie!H$4,'2022'!$F:$F,Trésorerie!$B38)+SUMIFS('2022'!$N:$N,'2022'!$E:$E,Trésorerie!H$4,'2022'!$F:$F,Trésorerie!$B38) -> 133.41 | I38: =-SUMIFS('2022'!$M:$M,'2022'!$E:$E,Trésorerie!I$4,'2022'!$F:$F,Trésorerie!$B38)+SUMIFS('2022'!$N:$N,'2022'!$E:$E,Trésorerie!I$4,'2022'!$F:$F,Trésorerie!$B38) -> 0 | J38: =-SUMIFS('2022'!$M:$M,'2022'!$E:$E,Trésorerie!J$4,'2022'!$F:$F,Trésorerie!$B38)+SUMIFS('2022'!$N:$N,'2022'!$E:$E,Trésorerie!J$4,'2022'!$F:$F,Trésorerie!$B38) -> 66.01 | K38: =-SUMIFS('2022'!$M:$M,'2022'!$E:$E,Trésorerie!K$4,'2022'!$F:$F,Trésorerie!$B38)+SUMIFS('2022'!$N:$N,'2022'!$E:$E,Trésorerie!K$4,'2022'!$F:$F,Trésorerie!$B38) -> 0 | L38: =-SUMIFS('2022'!$M:$M,'2022'!$E:$E,Trésorerie!L$4,'2022'!$F:$F,Trésorerie!$B38)+SUMIFS('2022'!$N:$N,'2022'!$E:$E,Trésorerie!L$4,'2022'!$F:$F,Trésorerie!$B38) -> 0 | ... P38: =-SUMIFS('2022'!$M:$M,'2022'!$E:$E,Trésorerie!P$4,'2022'!$F:$F,Trésorerie!$B38)+SUMIFS('2022'!$N:$N,'2022'!$E:$E,Trésorerie!P$4,'2022'!$F:$F,Trésorerie!$B38) -> 0 | R38: =-SUMIFS('2023-01'!$M:$M,'2023-01'!$E:$E,Trésorerie!R$4,'2023-01'!$F:$F,Trésorerie!$B38)+SUMIFS('2023-01'!$N:$N,'2023-01'!$E:$E,Trésorerie!R$4,'2023-01'!$F:$F,Trésorerie!$B38) -> 0 | S38: =-SUMIFS('2023-02'!$M:$M,'2023-02'!$E:$E,Trésorerie!S$4,'2023-02'!$F:$F,Trésorerie!$B38)+SUMIFS('2023-02'!$N:$N,'2023-02'!$E:$E,Trésorerie!S$4,'2023-02'!$F:$F,Trésorerie!$B38) -> 0 | T38: =-SUMIFS('2023-03'!$M:$M,'2023-03'!$E:$E,Trésorerie!T$4,'2023-03'!$F:$F,Trésorerie!$B38)+SUMIFS('2023-03'!$N:$N,'2023-03'!$E:$E,Trésorerie!T$4,'2023-03'!$F:$F,Trésorerie!$B38) -> 0 | U38: =-SUMIFS('2023-04'!$M:$M,'2023-04'!$E:$E,Trésorerie!U$4,'2023-04'!$F:$F,Trésorerie!$B38)+SUMIFS('2023-04'!$N:$N,'2023-04'!$E:$E,Trésorerie!U$4,'2023-04'!$F:$F,Trésorerie!$B38) -> 0 | V38: =-SUMIFS('2023-05'!$M:$M,'2023-05'!$E:$E,Trésorerie!V$4,'2023-05'!$F:$F,Trésorerie!$B38)+SUMIFS('2023-05'!$N:$N,'2023-05'!$E:$E,Trésorerie!V$4,'2023-05'!$F:$F,Trésorerie!$B38) -> 102 | W38: =-SUMIFS('2023-06'!$M:$M,'2023-06'!$E:$E,Trésorerie!W$4,'2023-06'!$F:$F,Trésorerie!$B38)+SUMIFS('2023-06'!$N:$N,'2023-06'!$E:$E,Trésorerie!W$4,'2023-06'!$F:$F,Trésorerie!$B38) -> 0 | X38: =-SUMIFS('2023-07'!$M:$M,'2023-07'!$E:$E,Trésorerie!X$4,'2023-07'!$F:$F,Trésorerie!$B38)+SUMIFS('2023-07'!$N:$N,'2023-07'!$E:$E,Trésorerie!X$4,'2023-07'!$F:$F,Trésorerie!$B38) -> 0 | Y38: =-SUMIFS('2023-08'!$M:$M,'2023-08'!$E:$E,Trésorerie!Y$4,'2023-08'!$F:$F,Trésorerie!$B38)+SUMIFS('2023-08'!$N:$N,'2023-08'!$E:$E,Trésorerie!Y$4,'2023-08'!$F:$F,Trésorerie!$B38) -> 0 | Z38: =-SUMIFS('2023-09'!$M:$M,'2023-09'!$E:$E,Trésorerie!Z$4,'2023-09'!$F:$F,Trésorerie!$B38)+SUMIFS('2023-09'!$N:$N,'2023-09'!$E:$E,Trésorerie!Z$4,'2023-09'!$F:$F,Trésorerie!$B38) -> 300 | AA38: =-SUMIFS('2023-10'!$M:$M,'2023-10'!$E:$E,Trésorerie!AA$4,'2023-10'!$F:$F,Trésorerie!$B38)+SUMIFS('2023-10'!$N:$N,'2023-10'!$E:$E,Trésorerie!AA$4,'2023-10'!$F:$F,Trésorerie!$B38) -> 0 | AB38: =IF(SUM($E38:O38)>SUM($R38:AA38),SUM($E38:O38)-SUM($R38:AA38),0) -> 0 | AC38: =IF(SUM($E38:P38)>SUM($R38:AB38),SUM($E38:P38)-SUM($R38:AB38),0) -> 0
A39: =SUM(E39:P39) -> 326.42 | B39: 758000 | C39: PDTS DIV.DE GESTION COURANTE | D39: Entrée | E39: =-SUMIFS('2022'!$M:$M,'2022'!$E:$E,Trésorerie!E$4,'2022'!$F:$F,Trésorerie!$B39)+SUMIFS('2022'!$N:$N,'2022'!$E:$E,Trésorerie!E$4,'2022'!$F:$F,Trésorerie!$B39) -> 0 | F39: =-SUMIFS('2022'!$M:$M,'2022'!$E:$E,Trésorerie!F$4,'2022'!$F:$F,Trésorerie!$B39)+SUMIFS('2022'!$N:$N,'2022'!$E:$E,Trésorerie!F$4,'2022'!$F:$F,Trésorerie!$B39) -> 0 | G39: =-SUMIFS('2022'!$M:$M,'2022'!$E:$E,Trésorerie!G$4,'2022'!$F:$F,Trésorerie!$B39)+SUMIFS('2022'!$N:$N,'2022'!$E:$E,Trésorerie!G$4,'2022'!$F:$F,Trésorerie!$B39) -> 0 | H39: =-SUMIFS('2022'!$M:$M,'2022'!$E:$E,Trésorerie!H$4,'2022'!$F:$F,Trésorerie!$B39)+SUMIFS('2022'!$N:$N,'2022'!$E:$E,Trésorerie!H$4,'2022'!$F:$F,Trésorerie!$B39) -> 0 | I39: =-SUMIFS('2022'!$M:$M,'2022'!$E:$E,Trésorerie!I$4,'2022'!$F:$F,Trésorerie!$B39)+SUMIFS('2022'!$N:$N,'2022'!$E:$E,Trésorerie!I$4,'2022'!$F:$F,Trésorerie!$B39) -> 0 | J39: =-SUMIFS('2022'!$M:$M,'2022'!$E:$E,Trésorerie!J$4,'2022'!$F:$F,Trésorerie!$B39)+SUMIFS('2022'!$N:$N,'2022'!$E:$E,Trésorerie!J$4,'2022'!$F:$F,Trésorerie!$B39) -> 0 | K39: =-SUMIFS('2022'!$M:$M,'2022'!$E:$E,Trésorerie!K$4,'2022'!$F:$F,Trésorerie!$B39)+SUMIFS('2022'!$N:$N,'2022'!$E:$E,Trésorerie!K$4,'2022'!$F:$F,Trésorerie!$B39) -> 0 | L39: =-SUMIFS('2022'!$M:$M,'2022'!$E:$E,Trésorerie!L$4,'2022'!$F:$F,Trésorerie!$B39)+SUMIFS('2022'!$N:$N,'2022'!$E:$E,Trésorerie!L$4,'2022'!$F:$F,Trésorerie!$B39) -> 0 | ... P39: =-SUMIFS('2022'!$M:$M,'2022'!$E:$E,Trésorerie!P$4,'2022'!$F:$F,Trésorerie!$B39)+SUMIFS('2022'!$N:$N,'2022'!$E:$E,Trésorerie!P$4,'2022'!$F:$F,Trésorerie!$B39) -> 326.42 | R39: =-SUMIFS('2023-01'!$M:$M,'2023-01'!$E:$E,Trésorerie!R$4,'2023-01'!$F:$F,Trésorerie!$B39)+SUMIFS('2023-01'!$N:$N,'2023-01'!$E:$E,Trésorerie!R$4,'2023-01'!$F:$F,Trésorerie!$B39) -> 0 | S39: =-SUMIFS('2023-02'!$M:$M,'2023-02'!$E:$E,Trésorerie!S$4,'2023-02'!$F:$F,Trésorerie!$B39)+SUMIFS('2023-02'!$N:$N,'2023-02'!$E:$E,Trésorerie!S$4,'2023-02'!$F:$F,Trésorerie!$B39) -> 0 | T39: =-SUMIFS('2023-03'!$M:$M,'2023-03'!$E:$E,Trésorerie!T$4,'2023-03'!$F:$F,Trésorerie!$B39)+SUMIFS('2023-03'!$N:$N,'2023-03'!$E:$E,Trésorerie!T$4,'2023-03'!$F:$F,Trésorerie!$B39) -> 0 | U39: =-SUMIFS('2023-04'!$M:$M,'2023-04'!$E:$E,Trésorerie!U$4,'2023-04'!$F:$F,Trésorerie!$B39)+SUMIFS('2023-04'!$N:$N,'2023-04'!$E:$E,Trésorerie!U$4,'2023-04'!$F:$F,Trésorerie!$B39) -> 0 | V39: =-SUMIFS('2023-05'!$M:$M,'2023-05'!$E:$E,Trésorerie!V$4,'2023-05'!$F:$F,Trésorerie!$B39)+SUMIFS('2023-05'!$N:$N,'2023-05'!$E:$E,Trésorerie!V$4,'2023-05'!$F:$F,Trésorerie!$B39) -> 0 | W39: =-SUMIFS('2023-06'!$M:$M,'2023-06'!$E:$E,Trésorerie!W$4,'2023-06'!$F:$F,Trésorerie!$B39)+SUMIFS('2023-06'!$N:$N,'2023-06'!$E:$E,Trésorerie!W$4,'2023-06'!$F:$F,Trésorerie!$B39) -> 20 | X39: =-SUMIFS('2023-07'!$M:$M,'2023-07'!$E:$E,Trésorerie!X$4,'2023-07'!$F:$F,Trésorerie!$B39)+SUMIFS('2023-07'!$N:$N,'2023-07'!$E:$E,Trésorerie!X$4,'2023-07'!$F:$F,Trésorerie!$B39) -> 0 | Y39: =-SUMIFS('2023-08'!$M:$M,'2023-08'!$E:$E,Trésorerie!Y$4,'2023-08'!$F:$F,Trésorerie!$B39)+SUMIFS('2023-08'!$N:$N,'2023-08'!$E:$E,Trésorerie!Y$4,'2023-08'!$F:$F,Trésorerie!$B39) -> 0 | Z39: =-SUMIFS('2023-09'!$M:$M,'2023-09'!$E:$E,Trésorerie!Z$4,'2023-09'!$F:$F,Trésorerie!$B39)+SUMIFS('2023-09'!$N:$N,'2023-09'!$E:$E,Trésorerie!Z$4,'2023-09'!$F:$F,Trésorerie!$B39) -> 0 | AA39: =-SUMIFS('2023-10'!$M:$M,'2023-10'!$E:$E,Trésorerie!AA$4,'2023-10'!$F:$F,Trésorerie!$B39)+SUMIFS('2023-10'!$N:$N,'2023-10'!$E:$E,Trésorerie!AA$4,'2023-10'!$F:$F,Trésorerie!$B39) -> 0 | AB39: =IF(SUM($E39:O39)>SUM($R39:AA39),SUM($E39:O39)-SUM($R39:AA39),0) -> 0 | AC39: =IF(SUM($E39:P39)>SUM($R39:AB39),SUM($E39:P39)-SUM($R39:AB39),0) -> 306.42
A40: =SUM(E40:P40) -> 129.38 | B40: 468735 | C40: PRE | D40: Entrée | E40: =-SUMIFS('2022'!$M:$M,'2022'!$E:$E,Trésorerie!E$4,'2022'!$F:$F,Trésorerie!$B40)+SUMIFS('2022'!$N:$N,'2022'!$E:$E,Trésorerie!E$4,'2022'!$F:$F,Trésorerie!$B40) -> 78.35 | F40: =-SUMIFS('2022'!$M:$M,'2022'!$E:$E,Trésorerie!F$4,'2022'!$F:$F,Trésorerie!$B40)+SUMIFS('2022'!$N:$N,'2022'!$E:$E,Trésorerie!F$4,'2022'!$F:$F,Trésorerie!$B40) -> 0 | G40: =-SUMIFS('2022'!$M:$M,'2022'!$E:$E,Trésorerie!G$4,'2022'!$F:$F,Trésorerie!$B40)+SUMIFS('2022'!$N:$N,'2022'!$E:$E,Trésorerie!G$4,'2022'!$F:$F,Trésorerie!$B40) -> 24.3 | H40: =-SUMIFS('2022'!$M:$M,'2022'!$E:$E,Trésorerie!H$4,'2022'!$F:$F,Trésorerie!$B40)+SUMIFS('2022'!$N:$N,'2022'!$E:$E,Trésorerie!H$4,'2022'!$F:$F,Trésorerie!$B40) -> 0 | I40: =-SUMIFS('2022'!$M:$M,'2022'!$E:$E,Trésorerie!I$4,'2022'!$F:$F,Trésorerie!$B40)+SUMIFS('2022'!$N:$N,'2022'!$E:$E,Trésorerie!I$4,'2022'!$F:$F,Trésorerie!$B40) -> 0 | J40: =-SUMIFS('2022'!$M:$M,'2022'!$E:$E,Trésorerie!J$4,'2022'!$F:$F,Trésorerie!$B40)+SUMIFS('2022'!$N:$N,'2022'!$E:$E,Trésorerie!J$4,'2022'!$F:$F,Trésorerie!$B40) -> 0 | K40: =-SUMIFS('2022'!$M:$M,'2022'!$E:$E,Trésorerie!K$4,'2022'!$F:$F,Trésorerie!$B40)+SUMIFS('2022'!$N:$N,'2022'!$E:$E,Trésorerie!K$4,'2022'!$F:$F,Trésorerie!$B40) -> 0 | L40: =-SUMIFS('2022'!$M:$M,'2022'!$E:$E,Trésorerie!L$4,'2022'!$F:$F,Trésorerie!$B40)+SUMIFS('2022'!$N:$N,'2022'!$E:$E,Trésorerie!L$4,'2022'!$F:$F,Trésorerie!$B40) -> 0 | ... P40: =-SUMIFS('2022'!$M:$M,'2022'!$E:$E,Trésorerie!P$4,'2022'!$F:$F,Trésorerie!$B40)+SUMIFS('2022'!$N:$N,'2022'!$E:$E,Trésorerie!P$4,'2022'!$F:$F,Trésorerie!$B40) -> 0 | R40: =-SUMIFS('2023-01'!$M:$M,'2023-01'!$E:$E,Trésorerie!R$4,'2023-01'!$F:$F,Trésorerie!$B40)+SUMIFS('2023-01'!$N:$N,'2023-01'!$E:$E,Trésorerie!R$4,'2023-01'!$F:$F,Trésorerie!$B40) -> 0 | S40: =-SUMIFS('2023-02'!$M:$M,'2023-02'!$E:$E,Trésorerie!S$4,'2023-02'!$F:$F,Trésorerie!$B40)+SUMIFS('2023-02'!$N:$N,'2023-02'!$E:$E,Trésorerie!S$4,'2023-02'!$F:$F,Trésorerie!$B40) -> 0 | T40: =-SUMIFS('2023-03'!$M:$M,'2023-03'!$E:$E,Trésorerie!T$4,'2023-03'!$F:$F,Trésorerie!$B40)+SUMIFS('2023-03'!$N:$N,'2023-03'!$E:$E,Trésorerie!T$4,'2023-03'!$F:$F,Trésorerie!$B40) -> 0 | U40: =-SUMIFS('2023-04'!$M:$M,'2023-04'!$E:$E,Trésorerie!U$4,'2023-04'!$F:$F,Trésorerie!$B40)+SUMIFS('2023-04'!$N:$N,'2023-04'!$E:$E,Trésorerie!U$4,'2023-04'!$F:$F,Trésorerie!$B40) -> 0 | V40: =-SUMIFS('2023-05'!$M:$M,'2023-05'!$E:$E,Trésorerie!V$4,'2023-05'!$F:$F,Trésorerie!$B40)+SUMIFS('2023-05'!$N:$N,'2023-05'!$E:$E,Trésorerie!V$4,'2023-05'!$F:$F,Trésorerie!$B40) -> 0 | W40: =-SUMIFS('2023-06'!$M:$M,'2023-06'!$E:$E,Trésorerie!W$4,'2023-06'!$F:$F,Trésorerie!$B40)+SUMIFS('2023-06'!$N:$N,'2023-06'!$E:$E,Trésorerie!W$4,'2023-06'!$F:$F,Trésorerie!$B40) -> 0 | X40: =-SUMIFS('2023-07'!$M:$M,'2023-07'!$E:$E,Trésorerie!X$4,'2023-07'!$F:$F,Trésorerie!$B40)+SUMIFS('2023-07'!$N:$N,'2023-07'!$E:$E,Trésorerie!X$4,'2023-07'!$F:$F,Trésorerie!$B40) -> 0 | Y40: =-SUMIFS('2023-08'!$M:$M,'2023-08'!$E:$E,Trésorerie!Y$4,'2023-08'!$F:$F,Trésorerie!$B40)+SUMIFS('2023-08'!$N:$N,'2023-08'!$E:$E,Trésorerie!Y$4,'2023-08'!$F:$F,Trésorerie!$B40) -> 0 | Z40: =-SUMIFS('2023-09'!$M:$M,'2023-09'!$E:$E,Trésorerie!Z$4,'2023-09'!$F:$F,Trésorerie!$B40)+SUMIFS('2023-09'!$N:$N,'2023-09'!$E:$E,Trésorerie!Z$4,'2023-09'!$F:$F,Trésorerie!$B40) -> 0 | AA40: =-SUMIFS('2023-10'!$M:$M,'2023-10'!$E:$E,Trésorerie!AA$4,'2023-10'!$F:$F,Trésorerie!$B40)+SUMIFS('2023-10'!$N:$N,'2023-10'!$E:$E,Trésorerie!AA$4,'2023-10'!$F:$F,Trésorerie!$B40) -> 0 | AB40: =IF(SUM($E40:O40)>SUM($R40:AA40),SUM($E40:O40)-SUM($R40:AA40),0) -> 129.38 | AC40: =IF(SUM($E40:P40)>SUM($R40:AB40),SUM($E40:P40)-SUM($R40:AB40),0) -> 0
A41: =SUM(E41:P41) -> 0 | B41: 468750 | C41: FSE | D41: Entrée | E41: =-SUMIFS('2022'!$M:$M,'2022'!$E:$E,Trésorerie!E$4,'2022'!$F:$F,Trésorerie!$B41)+SUMIFS('2022'!$N:$N,'2022'!$E:$E,Trésorerie!E$4,'2022'!$F:$F,Trésorerie!$B41) -> 0 | F41: =-SUMIFS('2022'!$M:$M,'2022'!$E:$E,Trésorerie!F$4,'2022'!$F:$F,Trésorerie!$B41)+SUMIFS('2022'!$N:$N,'2022'!$E:$E,Trésorerie!F$4,'2022'!$F:$F,Trésorerie!$B41) -> 0 | G41: =-SUMIFS('2022'!$M:$M,'2022'!$E:$E,Trésorerie!G$4,'2022'!$F:$F,Trésorerie!$B41)+SUMIFS('2022'!$N:$N,'2022'!$E:$E,Trésorerie!G$4,'2022'!$F:$F,Trésorerie!$B41) -> 0 | H41: =-SUMIFS('2022'!$M:$M,'2022'!$E:$E,Trésorerie!H$4,'2022'!$F:$F,Trésorerie!$B41)+SUMIFS('2022'!$N:$N,'2022'!$E:$E,Trésorerie!H$4,'2022'!$F:$F,Trésorerie!$B41) -> 0 | I41: =-SUMIFS('2022'!$M:$M,'2022'!$E:$E,Trésorerie!I$4,'2022'!$F:$F,Trésorerie!$B41)+SUMIFS('2022'!$N:$N,'2022'!$E:$E,Trésorerie!I$4,'2022'!$F:$F,Trésorerie!$B41) -> 0 | J41: =-SUMIFS('2022'!$M:$M,'2022'!$E:$E,Trésorerie!J$4,'2022'!$F:$F,Trésorerie!$B41)+SUMIFS('2022'!$N:$N,'2022'!$E:$E,Trésorerie!J$4,'2022'!$F:$F,Trésorerie!$B41) -> 0 | K41: =-SUMIFS('2022'!$M:$M,'2022'!$E:$E,Trésorerie!K$4,'2022'!$F:$F,Trésorerie!$B41)+SUMIFS('2022'!$N:$N,'2022'!$E:$E,Trésorerie!K$4,'2022'!$F:$F,Trésorerie!$B41) -> 0 | L41: =-SUMIFS('2022'!$M:$M,'2022'!$E:$E,Trésorerie!L$4,'2022'!$F:$F,Trésorerie!$B41)+SUMIFS('2022'!$N:$N,'2022'!$E:$E,Trésorerie!L$4,'2022'!$F:$F,Trésorerie!$B41) -> 0 | ... P41: =-SUMIFS('2022'!$M:$M,'2022'!$E:$E,Trésorerie!P$4,'2022'!$F:$F,Trésorerie!$B41)+SUMIFS('2022'!$N:$N,'2022'!$E:$E,Trésorerie!P$4,'2022'!$F:$F,Trésorerie!$B41) -> 0 | R41: =-SUMIFS('2023-01'!$M:$M,'2023-01'!$E:$E,Trésorerie!R$4,'2023-01'!$F:$F,Trésorerie!$B41)+SUMIFS('2023-01'!$N:$N,'2023-01'!$E:$E,Trésorerie!R$4,'2023-01'!$F:$F,Trésorerie!$B41) -> 0 | S41: =-SUMIFS('2023-02'!$M:$M,'2023-02'!$E:$E,Trésorerie!S$4,'2023-02'!$F:$F,Trésorerie!$B41)+SUMIFS('2023-02'!$N:$N,'2023-02'!$E:$E,Trésorerie!S$4,'2023-02'!$F:$F,Trésorerie!$B41) -> 0 | T41: =-SUMIFS('2023-03'!$M:$M,'2023-03'!$E:$E,Trésorerie!T$4,'2023-03'!$F:$F,Trésorerie!$B41)+SUMIFS('2023-03'!$N:$N,'2023-03'!$E:$E,Trésorerie!T$4,'2023-03'!$F:$F,Trésorerie!$B41) -> 8861.58 | U41: =-SUMIFS('2023-04'!$M:$M,'2023-04'!$E:$E,Trésorerie!U$4,'2023-04'!$F:$F,Trésorerie!$B41)+SUMIFS('2023-04'!$N:$N,'2023-04'!$E:$E,Trésorerie!U$4,'2023-04'!$F:$F,Trésorerie!$B41) -> 0 | V41: =-SUMIFS('2023-05'!$M:$M,'2023-05'!$E:$E,Trésorerie!V$4,'2023-05'!$F:$F,Trésorerie!$B41)+SUMIFS('2023-05'!$N:$N,'2023-05'!$E:$E,Trésorerie!V$4,'2023-05'!$F:$F,Trésorerie!$B41) -> 0 | W41: =-SUMIFS('2023-06'!$M:$M,'2023-06'!$E:$E,Trésorerie!W$4,'2023-06'!$F:$F,Trésorerie!$B41)+SUMIFS('2023-06'!$N:$N,'2023-06'!$E:$E,Trésorerie!W$4,'2023-06'!$F:$F,Trésorerie!$B41) -> 0 | X41: =-SUMIFS('2023-07'!$M:$M,'2023-07'!$E:$E,Trésorerie!X$4,'2023-07'!$F:$F,Trésorerie!$B41)+SUMIFS('2023-07'!$N:$N,'2023-07'!$E:$E,Trésorerie!X$4,'2023-07'!$F:$F,Trésorerie!$B41) -> 25200 | Y41: =-SUMIFS('2023-08'!$M:$M,'2023-08'!$E:$E,Trésorerie!Y$4,'2023-08'!$F:$F,Trésorerie!$B41)+SUMIFS('2023-08'!$N:$N,'2023-08'!$E:$E,Trésorerie!Y$4,'2023-08'!$F:$F,Trésorerie!$B41) -> 0 | Z41: =-SUMIFS('2023-09'!$M:$M,'2023-09'!$E:$E,Trésorerie!Z$4,'2023-09'!$F:$F,Trésorerie!$B41)+SUMIFS('2023-09'!$N:$N,'2023-09'!$E:$E,Trésorerie!Z$4,'2023-09'!$F:$F,Trésorerie!$B41) -> 0 | AA41: =-SUMIFS('2023-10'!$M:$M,'2023-10'!$E:$E,Trésorerie!AA$4,'2023-10'!$F:$F,Trésorerie!$B41)+SUMIFS('2023-10'!$N:$N,'2023-10'!$E:$E,Trésorerie!AA$4,'2023-10'!$F:$F,Trésorerie!$B41) -> 0 | AB41: =IF(SUM($E41:O41)>SUM($R41:AA41),SUM($E41:O41)-SUM($R41:AA41),0) -> 0 | AC41: =IF(SUM($E41:P41)>SUM($R41:AB41),SUM($E41:P41)-SUM($R41:AB41),0) -> 0
A42: =SUM(E42:P42) -> 28.5 | B42: 708220 | C42: MISE A DISPOS.PONCT. SALLE | D42: Entrée | E42: =-SUMIFS('2022'!$M:$M,'2022'!$E:$E,Trésorerie!E$4,'2022'!$F:$F,Trésorerie!$B42)+SUMIFS('2022'!$N:$N,'2022'!$E:$E,Trésorerie!E$4,'2022'!$F:$F,Trésorerie!$B42) -> 0 | F42: =-SUMIFS('2022'!$M:$M,'2022'!$E:$E,Trésorerie!F$4,'2022'!$F:$F,Trésorerie!$B42)+SUMIFS('2022'!$N:$N,'2022'!$E:$E,Trésorerie!F$4,'2022'!$F:$F,Trésorerie!$B42) -> 28.5 | G42: =-SUMIFS('2022'!$M:$M,'2022'!$E:$E,Trésorerie!G$4,'2022'!$F:$F,Trésorerie!$B42)+SUMIFS('2022'!$N:$N,'2022'!$E:$E,Trésorerie!G$4,'2022'!$F:$F,Trésorerie!$B42) -> 0 | H42: =-SUMIFS('2022'!$M:$M,'2022'!$E:$E,Trésorerie!H$4,'2022'!$F:$F,Trésorerie!$B42)+SUMIFS('2022'!$N:$N,'2022'!$E:$E,Trésorerie!H$4,'2022'!$F:$F,Trésorerie!$B42) -> 0 | I42: =-SUMIFS('2022'!$M:$M,'2022'!$E:$E,Trésorerie!I$4,'2022'!$F:$F,Trésorerie!$B42)+SUMIFS('2022'!$N:$N,'2022'!$E:$E,Trésorerie!I$4,'2022'!$F:$F,Trésorerie!$B42) -> 0 | J42: =-SUMIFS('2022'!$M:$M,'2022'!$E:$E,Trésorerie!J$4,'2022'!$F:$F,Trésorerie!$B42)+SUMIFS('2022'!$N:$N,'2022'!$E:$E,Trésorerie!J$4,'2022'!$F:$F,Trésorerie!$B42) -> 0 | K42: =-SUMIFS('2022'!$M:$M,'2022'!$E:$E,Trésorerie!K$4,'2022'!$F:$F,Trésorerie!$B42)+SUMIFS('2022'!$N:$N,'2022'!$E:$E,Trésorerie!K$4,'2022'!$F:$F,Trésorerie!$B42) -> 0 | L42: =-SUMIFS('2022'!$M:$M,'2022'!$E:$E,Trésorerie!L$4,'2022'!$F:$F,Trésorerie!$B42)+SUMIFS('2022'!$N:$N,'2022'!$E:$E,Trésorerie!L$4,'2022'!$F:$F,Trésorerie!$B42) -> 0 | ... P42: =-SUMIFS('2022'!$M:$M,'2022'!$E:$E,Trésorerie!P$4,'2022'!$F:$F,Trésorerie!$B42)+SUMIFS('2022'!$N:$N,'2022'!$E:$E,Trésorerie!P$4,'2022'!$F:$F,Trésorerie!$B42) -> 0 | R42: =-SUMIFS('2023-01'!$M:$M,'2023-01'!$E:$E,Trésorerie!R$4,'2023-01'!$F:$F,Trésorerie!$B42)+SUMIFS('2023-01'!$N:$N,'2023-01'!$E:$E,Trésorerie!R$4,'2023-01'!$F:$F,Trésorerie!$B42) -> 0 | S42: =-SUMIFS('2023-02'!$M:$M,'2023-02'!$E:$E,Trésorerie!S$4,'2023-02'!$F:$F,Trésorerie!$B42)+SUMIFS('2023-02'!$N:$N,'2023-02'!$E:$E,Trésorerie!S$4,'2023-02'!$F:$F,Trésorerie!$B42) -> 0 | T42: =-SUMIFS('2023-03'!$M:$M,'2023-03'!$E:$E,Trésorerie!T$4,'2023-03'!$F:$F,Trésorerie!$B42)+SUMIFS('2023-03'!$N:$N,'2023-03'!$E:$E,Trésorerie!T$4,'2023-03'!$F:$F,Trésorerie!$B42) -> 0 | U42: =-SUMIFS('2023-04'!$M:$M,'2023-04'!$E:$E,Trésorerie!U$4,'2023-04'!$F:$F,Trésorerie!$B42)+SUMIFS('2023-04'!$N:$N,'2023-04'!$E:$E,Trésorerie!U$4,'2023-04'!$F:$F,Trésorerie!$B42) -> 0 | V42: =-SUMIFS('2023-05'!$M:$M,'2023-05'!$E:$E,Trésorerie!V$4,'2023-05'!$F:$F,Trésorerie!$B42)+SUMIFS('2023-05'!$N:$N,'2023-05'!$E:$E,Trésorerie!V$4,'2023-05'!$F:$F,Trésorerie!$B42) -> 0 | W42: =-SUMIFS('2023-06'!$M:$M,'2023-06'!$E:$E,Trésorerie!W$4,'2023-06'!$F:$F,Trésorerie!$B42)+SUMIFS('2023-06'!$N:$N,'2023-06'!$E:$E,Trésorerie!W$4,'2023-06'!$F:$F,Trésorerie!$B42) -> 0 | X42: =-SUMIFS('2023-07'!$M:$M,'2023-07'!$E:$E,Trésorerie!X$4,'2023-07'!$F:$F,Trésorerie!$B42)+SUMIFS('2023-07'!$N:$N,'2023-07'!$E:$E,Trésorerie!X$4,'2023-07'!$F:$F,Trésorerie!$B42) -> 0 | Y42: =-SUMIFS('2023-08'!$M:$M,'2023-08'!$E:$E,Trésorerie!Y$4,'2023-08'!$F:$F,Trésorerie!$B42)+SUMIFS('2023-08'!$N:$N,'2023-08'!$E:$E,Trésorerie!Y$4,'2023-08'!$F:$F,Trésorerie!$B42) -> 0 | Z42: =-SUMIFS('2023-09'!$M:$M,'2023-09'!$E:$E,Trésorerie!Z$4,'2023-09'!$F:$F,Trésorerie!$B42)+SUMIFS('2023-09'!$N:$N,'2023-09'!$E:$E,Trésorerie!Z$4,'2023-09'!$F:$F,Trésorerie!$B42) -> 0 | AA42: =-SUMIFS('2023-10'!$M:$M,'2023-10'!$E:$E,Trésorerie!AA$4,'2023-10'!$F:$F,Trésorerie!$B42)+SUMIFS('2023-10'!$N:$N,'2023-10'!$E:$E,Trésorerie!AA$4,'2023-10'!$F:$F,Trésorerie!$B42) -> 0 | AB42: =IF(SUM($E42:O42)>SUM($R42:AA42),SUM($E42:O42)-SUM($R42:AA42),0) -> 28.5 | AC42: =IF(SUM($E42:P42)>SUM($R42:AB42),SUM($E42:P42)-SUM($R42:AB42),0) -> 0
D43: SOUS TOTAL | E43: =SUM(E5:E42) -> 20329.7 | F43: =SUM(F5:F42) -> 197648.95 | G43: =SUM(G5:G42) -> 207396.32 | H43: =SUM(H5:H42) -> 58977.41 | I43: =SUM(I5:I42) -> 191729.39 | J43: =SUM(J5:J42) -> 186198.59 | K43: =SUM(K5:K42) -> 108136.74 | L43: =SUM(L5:L42) -> 66530.98 | ... P43: =SUM(P5:P42) -> 25762.46 | R43: =SUM(R5:R42) -> 24327.5 | S43: =SUM(S5:S42) -> 32813.47 | T43: =SUM(T5:T42) -> 429413.41 | U43: =SUM(U5:U42) -> 140816.58 | V43: =SUM(V5:V42) -> 37328.03 | W43: =SUM(W5:W42) -> 131472.05 | X43: =SUM(X5:X42) -> 194798.58 | Y43: =SUM(Y5:Y42) -> 23427.23 | ... AC43: =SUM(AC5:AC42) -> 18716.44
A44: =SUM(E44:P44) -> -808208 | B44: 421000 | C44: REMUNERATIONS DUES | D44: Sortie | E44: =-SUMIFS('2022'!$M:$M,'2022'!$E:$E,Trésorerie!E$4,'2022'!$F:$F,Trésorerie!$B44)+SUMIFS('2022'!$N:$N,'2022'!$E:$E,Trésorerie!E$4,'2022'!$F:$F,Trésorerie!$B44) -> -58061.74 | F44: =-SUMIFS('2022'!$M:$M,'2022'!$E:$E,Trésorerie!F$4,'2022'!$F:$F,Trésorerie!$B44)+SUMIFS('2022'!$N:$N,'2022'!$E:$E,Trésorerie!F$4,'2022'!$F:$F,Trésorerie!$B44) -> -61636.56 | G44: =-SUMIFS('2022'!$M:$M,'2022'!$E:$E,Trésorerie!G$4,'2022'!$F:$F,Trésorerie!$B44)+SUMIFS('2022'!$N:$N,'2022'!$E:$E,Trésorerie!G$4,'2022'!$F:$F,Trésorerie!$B44) -> -66542.7 | H44: =-SUMIFS('2022'!$M:$M,'2022'!$E:$E,Trésorerie!H$4,'2022'!$F:$F,Trésorerie!$B44)+SUMIFS('2022'!$N:$N,'2022'!$E:$E,Trésorerie!H$4,'2022'!$F:$F,Trésorerie!$B44) -> -56284.36 | I44: =-SUMIFS('2022'!$M:$M,'2022'!$E:$E,Trésorerie!I$4,'2022'!$F:$F,Trésorerie!$B44)+SUMIFS('2022'!$N:$N,'2022'!$E:$E,Trésorerie!I$4,'2022'!$F:$F,Trésorerie!$B44) -> -67441.24 | J44: =-SUMIFS('2022'!$M:$M,'2022'!$E:$E,Trésorerie!J$4,'2022'!$F:$F,Trésorerie!$B44)+SUMIFS('2022'!$N:$N,'2022'!$E:$E,Trésorerie!J$4,'2022'!$F:$F,Trésorerie!$B44) -> -68878.79 | K44: =-SUMIFS('2022'!$M:$M,'2022'!$E:$E,Trésorerie!K$4,'2022'!$F:$F,Trésorerie!$B44)+SUMIFS('2022'!$N:$N,'2022'!$E:$E,Trésorerie!K$4,'2022'!$F:$F,Trésorerie!$B44) -> -80774.13 | L44: =-SUMIFS('2022'!$M:$M,'2022'!$E:$E,Trésorerie!L$4,'2022'!$F:$F,Trésorerie!$B44)+SUMIFS('2022'!$N:$N,'2022'!$E:$E,Trésorerie!L$4,'2022'!$F:$F,Trésorerie!$B44) -> -76513.47 | ... P44: =-SUMIFS('2022'!$M:$M,'2022'!$E:$E,Trésorerie!P$4,'2022'!$F:$F,Trésorerie!$B44)+SUMIFS('2022'!$N:$N,'2022'!$E:$E,Trésorerie!P$4,'2022'!$F:$F,Trésorerie!$B44) -> -79332.86 | R44: =-SUMIFS('2023-01'!$M:$M,'2023-01'!$E:$E,Trésorerie!R$4,'2023-01'!$F:$F,Trésorerie!$B44)+SUMIFS('2023-01'!$N:$N,'2023-01'!$E:$E,Trésorerie!R$4,'2023-01'!$F:$F,Trésorerie!$B44) -> -57174.54 | S44: =-SUMIFS('2023-02'!$M:$M,'2023-02'!$E:$E,Trésorerie!S$4,'2023-02'!$F:$F,Trésorerie!$B44)+SUMIFS('2023-02'!$N:$N,'2023-02'!$E:$E,Trésorerie!S$4,'2023-02'!$F:$F,Trésorerie!$B44) -> -61788.74 | T44: =-SUMIFS('2023-03'!$M:$M,'2023-03'!$E:$E,Trésorerie!T$4,'2023-03'!$F:$F,Trésorerie!$B44)+SUMIFS('2023-03'!$N:$N,'2023-03'!$E:$E,Trésorerie!T$4,'2023-03'!$F:$F,Trésorerie!$B44) -> -58754.33 | U44: =-SUMIFS('2023-04'!$M:$M,'2023-04'!$E:$E,Trésorerie!U$4,'2023-04'!$F:$F,Trésorerie!$B44)+SUMIFS('2023-04'!$N:$N,'2023-04'!$E:$E,Trésorerie!U$4,'2023-04'!$F:$F,Trésorerie!$B44) -> -64999.04 | V44: =-SUMIFS('2023-05'!$M:$M,'2023-05'!$E:$E,Trésorerie!V$4,'2023-05'!$F:$F,Trésorerie!$B44)+SUMIFS('2023-05'!$N:$N,'2023-05'!$E:$E,Trésorerie!V$4,'2023-05'!$F:$F,Trésorerie!$B44) -> -474.83 | W44: =-SUMIFS('2023-06'!$M:$M,'2023-06'!$E:$E,Trésorerie!W$4,'2023-06'!$F:$F,Trésorerie!$B44)+SUMIFS('2023-06'!$N:$N,'2023-06'!$E:$E,Trésorerie!W$4,'2023-06'!$F:$F,Trésorerie!$B44) -> -60431.22 | X44: =-SUMIFS('2023-07'!$M:$M,'2023-07'!$E:$E,Trésorerie!X$4,'2023-07'!$F:$F,Trésorerie!$B44)+SUMIFS('2023-07'!$N:$N,'2023-07'!$E:$E,Trésorerie!X$4,'2023-07'!$F:$F,Trésorerie!$B44) -> -73981.1 | Y44: =-SUMIFS('2023-08'!$M:$M,'2023-08'!$E:$E,Trésorerie!Y$4,'2023-08'!$F:$F,Trésorerie!$B44)+SUMIFS('2023-08'!$N:$N,'2023-08'!$E:$E,Trésorerie!Y$4,'2023-08'!$F:$F,Trésorerie!$B44) -> -77212.55 | Z44: =-SUMIFS('2023-09'!$M:$M,'2023-09'!$E:$E,Trésorerie!Z$4,'2023-09'!$F:$F,Trésorerie!$B44)+SUMIFS('2023-09'!$N:$N,'2023-09'!$E:$E,Trésorerie!Z$4,'2023-09'!$F:$F,Trésorerie!$B44) -> -49777.61 | AA44: =-SUMIFS('2023-10'!$M:$M,'2023-10'!$E:$E,Trésorerie!AA$4,'2023-10'!$F:$F,Trésorerie!$B44)+SUMIFS('2023-10'!$N:$N,'2023-10'!$E:$E,Trésorerie!AA$4,'2023-10'!$F:$F,Trésorerie!$B44) -> -51337.03 | AB44: =IF(SUM($E44:O44)<SUM($R44:AA44),SUM($E44:O44)-SUM($R44:AA44),0) -> -172944.15 | AC44: =IF(SUM($E44:P44)<SUM($R44:AB44),SUM($E44:P44)-SUM($R44:AB44),0) -> -79332.86
A45: =SUM(E45:P45) -> -380747.5 | B45: 401000 | C45: COLLECTIF FOURNISSEURS | D45: Sortie | E45: =-SUMIFS('2022'!$M:$M,'2022'!$E:$E,Trésorerie!E$4,'2022'!$F:$F,Trésorerie!$B45)+SUMIFS('2022'!$N:$N,'2022'!$E:$E,Trésorerie!E$4,'2022'!$F:$F,Trésorerie!$B45) -> -31493.89 | F45: =-SUMIFS('2022'!$M:$M,'2022'!$E:$E,Trésorerie!F$4,'2022'!$F:$F,Trésorerie!$B45)+SUMIFS('2022'!$N:$N,'2022'!$E:$E,Trésorerie!F$4,'2022'!$F:$F,Trésorerie!$B45) -> -43204.02 | G45: =-SUMIFS('2022'!$M:$M,'2022'!$E:$E,Trésorerie!G$4,'2022'!$F:$F,Trésorerie!$B45)+SUMIFS('2022'!$N:$N,'2022'!$E:$E,Trésorerie!G$4,'2022'!$F:$F,Trésorerie!$B45) -> -25576.88 | H45: =-SUMIFS('2022'!$M:$M,'2022'!$E:$E,Trésorerie!H$4,'2022'!$F:$F,Trésorerie!$B45)+SUMIFS('2022'!$N:$N,'2022'!$E:$E,Trésorerie!H$4,'2022'!$F:$F,Trésorerie!$B45) -> -30863.34 | I45: =-SUMIFS('2022'!$M:$M,'2022'!$E:$E,Trésorerie!I$4,'2022'!$F:$F,Trésorerie!$B45)+SUMIFS('2022'!$N:$N,'2022'!$E:$E,Trésorerie!I$4,'2022'!$F:$F,Trésorerie!$B45) -> -34031.54 | J45: =-SUMIFS('2022'!$M:$M,'2022'!$E:$E,Trésorerie!J$4,'2022'!$F:$F,Trésorerie!$B45)+SUMIFS('2022'!$N:$N,'2022'!$E:$E,Trésorerie!J$4,'2022'!$F:$F,Trésorerie!$B45) -> -43453.39 | K45: =-SUMIFS('2022'!$M:$M,'2022'!$E:$E,Trésorerie!K$4,'2022'!$F:$F,Trésorerie!$B45)+SUMIFS('2022'!$N:$N,'2022'!$E:$E,Trésorerie!K$4,'2022'!$F:$F,Trésorerie!$B45) -> -48014.63 | L45: =-SUMIFS('2022'!$M:$M,'2022'!$E:$E,Trésorerie!L$4,'2022'!$F:$F,Trésorerie!$B45)+SUMIFS('2022'!$N:$N,'2022'!$E:$E,Trésorerie!L$4,'2022'!$F:$F,Trésorerie!$B45) -> -28478.48 | ... P45: =-SUMIFS('2022'!$M:$M,'2022'!$E:$E,Trésorerie!P$4,'2022'!$F:$F,Trésorerie!$B45)+SUMIFS('2022'!$N:$N,'2022'!$E:$E,Trésorerie!P$4,'2022'!$F:$F,Trésorerie!$B45) -> -25016.49 | R45: =-SUMIFS('2023-01'!$M:$M,'2023-01'!$E:$E,Trésorerie!R$4,'2023-01'!$F:$F,Trésorerie!$B45)+SUMIFS('2023-01'!$N:$N,'2023-01'!$E:$E,Trésorerie!R$4,'2023-01'!$F:$F,Trésorerie!$B45) -> -36419.16 | S45: =-SUMIFS('2023-02'!$M:$M,'2023-02'!$E:$E,Trésorerie!S$4,'2023-02'!$F:$F,Trésorerie!$B45)+SUMIFS('2023-02'!$N:$N,'2023-02'!$E:$E,Trésorerie!S$4,'2023-02'!$F:$F,Trésorerie!$B45) -> -12399.89 | T45: =-SUMIFS('2023-03'!$M:$M,'2023-03'!$E:$E,Trésorerie!T$4,'2023-03'!$F:$F,Trésorerie!$B45)+SUMIFS('2023-03'!$N:$N,'2023-03'!$E:$E,Trésorerie!T$4,'2023-03'!$F:$F,Trésorerie!$B45) -> -37454.32 | U45: =-SUMIFS('2023-04'!$M:$M,'2023-04'!$E:$E,Trésorerie!U$4,'2023-04'!$F:$F,Trésorerie!$B45)+SUMIFS('2023-04'!$N:$N,'2023-04'!$E:$E,Trésorerie!U$4,'2023-04'!$F:$F,Trésorerie!$B45) -> -16355.98 | V45: =-SUMIFS('2023-05'!$M:$M,'2023-05'!$E:$E,Trésorerie!V$4,'2023-05'!$F:$F,Trésorerie!$B45)+SUMIFS('2023-05'!$N:$N,'2023-05'!$E:$E,Trésorerie!V$4,'2023-05'!$F:$F,Trésorerie!$B45) -> -20958.73 | W45: =-SUMIFS('2023-06'!$M:$M,'2023-06'!$E:$E,Trésorerie!W$4,'2023-06'!$F:$F,Trésorerie!$B45)+SUMIFS('2023-06'!$N:$N,'2023-06'!$E:$E,Trésorerie!W$4,'2023-06'!$F:$F,Trésorerie!$B45) -> -44307.19 | X45: =-SUMIFS('2023-07'!$M:$M,'2023-07'!$E:$E,Trésorerie!X$4,'2023-07'!$F:$F,Trésorerie!$B45)+SUMIFS('2023-07'!$N:$N,'2023-07'!$E:$E,Trésorerie!X$4,'2023-07'!$F:$F,Trésorerie!$B45) -> -22943.51 | Y45: =-SUMIFS('2023-08'!$M:$M,'2023-08'!$E:$E,Trésorerie!Y$4,'2023-08'!$F:$F,Trésorerie!$B45)+SUMIFS('2023-08'!$N:$N,'2023-08'!$E:$E,Trésorerie!Y$4,'2023-08'!$F:$F,Trésorerie!$B45) -> -17794.92 | Z45: =-SUMIFS('2023-09'!$M:$M,'2023-09'!$E:$E,Trésorerie!Z$4,'2023-09'!$F:$F,Trésorerie!$B45)+SUMIFS('2023-09'!$N:$N,'2023-09'!$E:$E,Trésorerie!Z$4,'2023-09'!$F:$F,Trésorerie!$B45) -> -29044.34 | AA45: =-SUMIFS('2023-10'!$M:$M,'2023-10'!$E:$E,Trésorerie!AA$4,'2023-10'!$F:$F,Trésorerie!$B45)+SUMIFS('2023-10'!$N:$N,'2023-10'!$E:$E,Trésorerie!AA$4,'2023-10'!$F:$F,Trésorerie!$B45) -> -21573.47 | AB45: =IF(SUM($E45:O45)<SUM($R45:AA45),SUM($E45:O45)-SUM($R45:AA45),0) -> -96479.5 | AC45: =IF(SUM($E45:P45)<SUM($R45:AB45),SUM($E45:P45)-SUM($R45:AB45),0) -> -25016.49
A46: =SUM(E46:P46) -> -354945 | B46: 431000 | C46: URSSAF/POLE EMPLOI | D46: Sortie | E46: =-SUMIFS('2022'!$M:$M,'2022'!$E:$E,Trésorerie!E$4,'2022'!$F:$F,Trésorerie!$B46)+SUMIFS('2022'!$N:$N,'2022'!$E:$E,Trésorerie!E$4,'2022'!$F:$F,Trésorerie!$B46) -> -25092 | F46: =-SUMIFS('2022'!$M:$M,'2022'!$E:$E,Trésorerie!F$4,'2022'!$F:$F,Trésorerie!$B46)+SUMIFS('2022'!$N:$N,'2022'!$E:$E,Trésorerie!F$4,'2022'!$F:$F,Trésorerie!$B46) -> -26901 | G46: =-SUMIFS('2022'!$M:$M,'2022'!$E:$E,Trésorerie!G$4,'2022'!$F:$F,Trésorerie!$B46)+SUMIFS('2022'!$N:$N,'2022'!$E:$E,Trésorerie!G$4,'2022'!$F:$F,Trésorerie!$B46) -> -30881 | H46: =-SUMIFS('2022'!$M:$M,'2022'!$E:$E,Trésorerie!H$4,'2022'!$F:$F,Trésorerie!$B46)+SUMIFS('2022'!$N:$N,'2022'!$E:$E,Trésorerie!H$4,'2022'!$F:$F,Trésorerie!$B46) -> -29085 | I46: =-SUMIFS('2022'!$M:$M,'2022'!$E:$E,Trésorerie!I$4,'2022'!$F:$F,Trésorerie!$B46)+SUMIFS('2022'!$N:$N,'2022'!$E:$E,Trésorerie!I$4,'2022'!$F:$F,Trésorerie!$B46) -> -26634 | J46: =-SUMIFS('2022'!$M:$M,'2022'!$E:$E,Trésorerie!J$4,'2022'!$F:$F,Trésorerie!$B46)+SUMIFS('2022'!$N:$N,'2022'!$E:$E,Trésorerie!J$4,'2022'!$F:$F,Trésorerie!$B46) -> -25265 | K46: =-SUMIFS('2022'!$M:$M,'2022'!$E:$E,Trésorerie!K$4,'2022'!$F:$F,Trésorerie!$B46)+SUMIFS('2022'!$N:$N,'2022'!$E:$E,Trésorerie!K$4,'2022'!$F:$F,Trésorerie!$B46) -> -33772 | L46: =-SUMIFS('2022'!$M:$M,'2022'!$E:$E,Trésorerie!L$4,'2022'!$F:$F,Trésorerie!$B46)+SUMIFS('2022'!$N:$N,'2022'!$E:$E,Trésorerie!L$4,'2022'!$F:$F,Trésorerie!$B46) -> -44733 | ... P46: =-SUMIFS('2022'!$M:$M,'2022'!$E:$E,Trésorerie!P$4,'2022'!$F:$F,Trésorerie!$B46)+SUMIFS('2022'!$N:$N,'2022'!$E:$E,Trésorerie!P$4,'2022'!$F:$F,Trésorerie!$B46) -> -27800 | R46: =-SUMIFS('2023-01'!$M:$M,'2023-01'!$E:$E,Trésorerie!R$4,'2023-01'!$F:$F,Trésorerie!$B46)+SUMIFS('2023-01'!$N:$N,'2023-01'!$E:$E,Trésorerie!R$4,'2023-01'!$F:$F,Trésorerie!$B46) -> -43230 | S46: =-SUMIFS('2023-02'!$M:$M,'2023-02'!$E:$E,Trésorerie!S$4,'2023-02'!$F:$F,Trésorerie!$B46)+SUMIFS('2023-02'!$N:$N,'2023-02'!$E:$E,Trésorerie!S$4,'2023-02'!$F:$F,Trésorerie!$B46) -> -26552 | T46: =-SUMIFS('2023-03'!$M:$M,'2023-03'!$E:$E,Trésorerie!T$4,'2023-03'!$F:$F,Trésorerie!$B46)+SUMIFS('2023-03'!$N:$N,'2023-03'!$E:$E,Trésorerie!T$4,'2023-03'!$F:$F,Trésorerie!$B46) -> -25573 | U46: =-SUMIFS('2023-04'!$M:$M,'2023-04'!$E:$E,Trésorerie!U$4,'2023-04'!$F:$F,Trésorerie!$B46)+SUMIFS('2023-04'!$N:$N,'2023-04'!$E:$E,Trésorerie!U$4,'2023-04'!$F:$F,Trésorerie!$B46) -> -28363 | V46: =-SUMIFS('2023-05'!$M:$M,'2023-05'!$E:$E,Trésorerie!V$4,'2023-05'!$F:$F,Trésorerie!$B46)+SUMIFS('2023-05'!$N:$N,'2023-05'!$E:$E,Trésorerie!V$4,'2023-05'!$F:$F,Trésorerie!$B46) -> -28716 | W46: =-SUMIFS('2023-06'!$M:$M,'2023-06'!$E:$E,Trésorerie!W$4,'2023-06'!$F:$F,Trésorerie!$B46)+SUMIFS('2023-06'!$N:$N,'2023-06'!$E:$E,Trésorerie!W$4,'2023-06'!$F:$F,Trésorerie!$B46) -> -27170 | X46: =-SUMIFS('2023-07'!$M:$M,'2023-07'!$E:$E,Trésorerie!X$4,'2023-07'!$F:$F,Trésorerie!$B46)+SUMIFS('2023-07'!$N:$N,'2023-07'!$E:$E,Trésorerie!X$4,'2023-07'!$F:$F,Trésorerie!$B46) -> -30592 | Y46: =-SUMIFS('2023-08'!$M:$M,'2023-08'!$E:$E,Trésorerie!Y$4,'2023-08'!$F:$F,Trésorerie!$B46)+SUMIFS('2023-08'!$N:$N,'2023-08'!$E:$E,Trésorerie!Y$4,'2023-08'!$F:$F,Trésorerie!$B46) -> -40329 | Z46: =-SUMIFS('2023-09'!$M:$M,'2023-09'!$E:$E,Trésorerie!Z$4,'2023-09'!$F:$F,Trésorerie!$B46)+SUMIFS('2023-09'!$N:$N,'2023-09'!$E:$E,Trésorerie!Z$4,'2023-09'!$F:$F,Trésorerie!$B46) -> -32388 | AA46: =-SUMIFS('2023-10'!$M:$M,'2023-10'!$E:$E,Trésorerie!AA$4,'2023-10'!$F:$F,Trésorerie!$B46)+SUMIFS('2023-10'!$N:$N,'2023-10'!$E:$E,Trésorerie!AA$4,'2023-10'!$F:$F,Trésorerie!$B46) -> -24658 | AB46: =IF(SUM($E46:O46)<SUM($R46:AA46),SUM($E46:O46)-SUM($R46:AA46),0) -> -19574 | AC46: =IF(SUM($E46:P46)<SUM($R46:AB46),SUM($E46:P46)-SUM($R46:AB46),0) -> -27800
A47: =SUM(E47:P47) -> -75370.68 | B47: 433000 | C47: APICIL | D47: Sortie | E47: =-SUMIFS('2022'!$M:$M,'2022'!$E:$E,Trésorerie!E$4,'2022'!$F:$F,Trésorerie!$B47)+SUMIFS('2022'!$N:$N,'2022'!$E:$E,Trésorerie!E$4,'2022'!$F:$F,Trésorerie!$B47) -> -5907.98 | F47: =-SUMIFS('2022'!$M:$M,'2022'!$E:$E,Trésorerie!F$4,'2022'!$F:$F,Trésorerie!$B47)+SUMIFS('2022'!$N:$N,'2022'!$E:$E,Trésorerie!F$4,'2022'!$F:$F,Trésorerie!$B47) -> -5092.45 | G47: =-SUMIFS('2022'!$M:$M,'2022'!$E:$E,Trésorerie!G$4,'2022'!$F:$F,Trésorerie!$B47)+SUMIFS('2022'!$N:$N,'2022'!$E:$E,Trésorerie!G$4,'2022'!$F:$F,Trésorerie!$B47) -> -7272.22 | H47: =-SUMIFS('2022'!$M:$M,'2022'!$E:$E,Trésorerie!H$4,'2022'!$F:$F,Trésorerie!$B47)+SUMIFS('2022'!$N:$N,'2022'!$E:$E,Trésorerie!H$4,'2022'!$F:$F,Trésorerie!$B47) -> -5605.89 | I47: =-SUMIFS('2022'!$M:$M,'2022'!$E:$E,Trésorerie!I$4,'2022'!$F:$F,Trésorerie!$B47)+SUMIFS('2022'!$N:$N,'2022'!$E:$E,Trésorerie!I$4,'2022'!$F:$F,Trésorerie!$B47) -> -5967.75 | J47: =-SUMIFS('2022'!$M:$M,'2022'!$E:$E,Trésorerie!J$4,'2022'!$F:$F,Trésorerie!$B47)+SUMIFS('2022'!$N:$N,'2022'!$E:$E,Trésorerie!J$4,'2022'!$F:$F,Trésorerie!$B47) -> -4898.15 | K47: =-SUMIFS('2022'!$M:$M,'2022'!$E:$E,Trésorerie!K$4,'2022'!$F:$F,Trésorerie!$B47)+SUMIFS('2022'!$N:$N,'2022'!$E:$E,Trésorerie!K$4,'2022'!$F:$F,Trésorerie!$B47) -> -6832.92 | L47: =-SUMIFS('2022'!$M:$M,'2022'!$E:$E,Trésorerie!L$4,'2022'!$F:$F,Trésorerie!$B47)+SUMIFS('2022'!$N:$N,'2022'!$E:$E,Trésorerie!L$4,'2022'!$F:$F,Trésorerie!$B47) -> -10818.08 | ... P47: =-SUMIFS('2022'!$M:$M,'2022'!$E:$E,Trésorerie!P$4,'2022'!$F:$F,Trésorerie!$B47)+SUMIFS('2022'!$N:$N,'2022'!$E:$E,Trésorerie!P$4,'2022'!$F:$F,Trésorerie!$B47) -> -6154.77 | R47: =-SUMIFS('2023-01'!$M:$M,'2023-01'!$E:$E,Trésorerie!R$4,'2023-01'!$F:$F,Trésorerie!$B47)+SUMIFS('2023-01'!$N:$N,'2023-01'!$E:$E,Trésorerie!R$4,'2023-01'!$F:$F,Trésorerie!$B47) -> -11508.12 | S47: =-SUMIFS('2023-02'!$M:$M,'2023-02'!$E:$E,Trésorerie!S$4,'2023-02'!$F:$F,Trésorerie!$B47)+SUMIFS('2023-02'!$N:$N,'2023-02'!$E:$E,Trésorerie!S$4,'2023-02'!$F:$F,Trésorerie!$B47) -> 0 | T47: =-SUMIFS('2023-03'!$M:$M,'2023-03'!$E:$E,Trésorerie!T$4,'2023-03'!$F:$F,Trésorerie!$B47)+SUMIFS('2023-03'!$N:$N,'2023-03'!$E:$E,Trésorerie!T$4,'2023-03'!$F:$F,Trésorerie!$B47) -> -11346.48 | U47: =-SUMIFS('2023-04'!$M:$M,'2023-04'!$E:$E,Trésorerie!U$4,'2023-04'!$F:$F,Trésorerie!$B47)+SUMIFS('2023-04'!$N:$N,'2023-04'!$E:$E,Trésorerie!U$4,'2023-04'!$F:$F,Trésorerie!$B47) -> -5785.63 | V47: =-SUMIFS('2023-05'!$M:$M,'2023-05'!$E:$E,Trésorerie!V$4,'2023-05'!$F:$F,Trésorerie!$B47)+SUMIFS('2023-05'!$N:$N,'2023-05'!$E:$E,Trésorerie!V$4,'2023-05'!$F:$F,Trésorerie!$B47) -> 0 | W47: =-SUMIFS('2023-06'!$M:$M,'2023-06'!$E:$E,Trésorerie!W$4,'2023-06'!$F:$F,Trésorerie!$B47)+SUMIFS('2023-06'!$N:$N,'2023-06'!$E:$E,Trésorerie!W$4,'2023-06'!$F:$F,Trésorerie!$B47) -> -5549.88 | X47: =-SUMIFS('2023-07'!$M:$M,'2023-07'!$E:$E,Trésorerie!X$4,'2023-07'!$F:$F,Trésorerie!$B47)+SUMIFS('2023-07'!$N:$N,'2023-07'!$E:$E,Trésorerie!X$4,'2023-07'!$F:$F,Trésorerie!$B47) -> -6253.92 | Y47: =-SUMIFS('2023-08'!$M:$M,'2023-08'!$E:$E,Trésorerie!Y$4,'2023-08'!$F:$F,Trésorerie!$B47)+SUMIFS('2023-08'!$N:$N,'2023-08'!$E:$E,Trésorerie!Y$4,'2023-08'!$F:$F,Trésorerie!$B47) -> -9494.9 | Z47: =-SUMIFS('2023-09'!$M:$M,'2023-09'!$E:$E,Trésorerie!Z$4,'2023-09'!$F:$F,Trésorerie!$B47)+SUMIFS('2023-09'!$N:$N,'2023-09'!$E:$E,Trésorerie!Z$4,'2023-09'!$F:$F,Trésorerie!$B47) -> -6700.09 | AA47: =-SUMIFS('2023-10'!$M:$M,'2023-10'!$E:$E,Trésorerie!AA$4,'2023-10'!$F:$F,Trésorerie!$B47)+SUMIFS('2023-10'!$N:$N,'2023-10'!$E:$E,Trésorerie!AA$4,'2023-10'!$F:$F,Trésorerie!$B47) -> -4955.12 | AB47: =IF(SUM($E47:O47)<SUM($R47:AA47),SUM($E47:O47)-SUM($R47:AA47),0) -> -7621.77 | AC47: =IF(SUM($E47:P47)<SUM($R47:AB47),SUM($E47:P47)-SUM($R47:AB47),0) -> -6154.77
A48: =SUM(E48:P48) -> -49407 | B48: 447000 | C48: TAXE SUR LES SALAIRES | D48: Sortie | E48: =-SUMIFS('2022'!$M:$M,'2022'!$E:$E,Trésorerie!E$4,'2022'!$F:$F,Trésorerie!$B48)+SUMIFS('2022'!$N:$N,'2022'!$E:$E,Trésorerie!E$4,'2022'!$F:$F,Trésorerie!$B48) -> 0 | F48: =-SUMIFS('2022'!$M:$M,'2022'!$E:$E,Trésorerie!F$4,'2022'!$F:$F,Trésorerie!$B48)+SUMIFS('2022'!$N:$N,'2022'!$E:$E,Trésorerie!F$4,'2022'!$F:$F,Trésorerie!$B48) -> -4197 | G48: =-SUMIFS('2022'!$M:$M,'2022'!$E:$E,Trésorerie!G$4,'2022'!$F:$F,Trésorerie!$B48)+SUMIFS('2022'!$N:$N,'2022'!$E:$E,Trésorerie!G$4,'2022'!$F:$F,Trésorerie!$B48) -> 0 | H48: =-SUMIFS('2022'!$M:$M,'2022'!$E:$E,Trésorerie!H$4,'2022'!$F:$F,Trésorerie!$B48)+SUMIFS('2022'!$N:$N,'2022'!$E:$E,Trésorerie!H$4,'2022'!$F:$F,Trésorerie!$B48) -> 0 | I48: =-SUMIFS('2022'!$M:$M,'2022'!$E:$E,Trésorerie!I$4,'2022'!$F:$F,Trésorerie!$B48)+SUMIFS('2022'!$N:$N,'2022'!$E:$E,Trésorerie!I$4,'2022'!$F:$F,Trésorerie!$B48) -> -3903 | J48: =-SUMIFS('2022'!$M:$M,'2022'!$E:$E,Trésorerie!J$4,'2022'!$F:$F,Trésorerie!$B48)+SUMIFS('2022'!$N:$N,'2022'!$E:$E,Trésorerie!J$4,'2022'!$F:$F,Trésorerie!$B48) -> -5642 | K48: =-SUMIFS('2022'!$M:$M,'2022'!$E:$E,Trésorerie!K$4,'2022'!$F:$F,Trésorerie!$B48)+SUMIFS('2022'!$N:$N,'2022'!$E:$E,Trésorerie!K$4,'2022'!$F:$F,Trésorerie!$B48) -> 0 | L48: =-SUMIFS('2022'!$M:$M,'2022'!$E:$E,Trésorerie!L$4,'2022'!$F:$F,Trésorerie!$B48)+SUMIFS('2022'!$N:$N,'2022'!$E:$E,Trésorerie!L$4,'2022'!$F:$F,Trésorerie!$B48) -> -14901 | ... P48: =-SUMIFS('2022'!$M:$M,'2022'!$E:$E,Trésorerie!P$4,'2022'!$F:$F,Trésorerie!$B48)+SUMIFS('2022'!$N:$N,'2022'!$E:$E,Trésorerie!P$4,'2022'!$F:$F,Trésorerie!$B48) -> -5549 | R48: =-SUMIFS('2023-01'!$M:$M,'2023-01'!$E:$E,Trésorerie!R$4,'2023-01'!$F:$F,Trésorerie!$B48)+SUMIFS('2023-01'!$N:$N,'2023-01'!$E:$E,Trésorerie!R$4,'2023-01'!$F:$F,Trésorerie!$B48) -> 0 | S48: =-SUMIFS('2023-02'!$M:$M,'2023-02'!$E:$E,Trésorerie!S$4,'2023-02'!$F:$F,Trésorerie!$B48)+SUMIFS('2023-02'!$N:$N,'2023-02'!$E:$E,Trésorerie!S$4,'2023-02'!$F:$F,Trésorerie!$B48) -> -8502 | T48: =-SUMIFS('2023-03'!$M:$M,'2023-03'!$E:$E,Trésorerie!T$4,'2023-03'!$F:$F,Trésorerie!$B48)+SUMIFS('2023-03'!$N:$N,'2023-03'!$E:$E,Trésorerie!T$4,'2023-03'!$F:$F,Trésorerie!$B48) -> 0 | U48: =-SUMIFS('2023-04'!$M:$M,'2023-04'!$E:$E,Trésorerie!U$4,'2023-04'!$F:$F,Trésorerie!$B48)+SUMIFS('2023-04'!$N:$N,'2023-04'!$E:$E,Trésorerie!U$4,'2023-04'!$F:$F,Trésorerie!$B48) -> 0 | V48: =-SUMIFS('2023-05'!$M:$M,'2023-05'!$E:$E,Trésorerie!V$4,'2023-05'!$F:$F,Trésorerie!$B48)+SUMIFS('2023-05'!$N:$N,'2023-05'!$E:$E,Trésorerie!V$4,'2023-05'!$F:$F,Trésorerie!$B48) -> -474 | W48: =-SUMIFS('2023-06'!$M:$M,'2023-06'!$E:$E,Trésorerie!W$4,'2023-06'!$F:$F,Trésorerie!$B48)+SUMIFS('2023-06'!$N:$N,'2023-06'!$E:$E,Trésorerie!W$4,'2023-06'!$F:$F,Trésorerie!$B48) -> -5985 | X48: =-SUMIFS('2023-07'!$M:$M,'2023-07'!$E:$E,Trésorerie!X$4,'2023-07'!$F:$F,Trésorerie!$B48)+SUMIFS('2023-07'!$N:$N,'2023-07'!$E:$E,Trésorerie!X$4,'2023-07'!$F:$F,Trésorerie!$B48) -> -6209 | Y48: =-SUMIFS('2023-08'!$M:$M,'2023-08'!$E:$E,Trésorerie!Y$4,'2023-08'!$F:$F,Trésorerie!$B48)+SUMIFS('2023-08'!$N:$N,'2023-08'!$E:$E,Trésorerie!Y$4,'2023-08'!$F:$F,Trésorerie!$B48) -> -7596 | Z48: =-SUMIFS('2023-09'!$M:$M,'2023-09'!$E:$E,Trésorerie!Z$4,'2023-09'!$F:$F,Trésorerie!$B48)+SUMIFS('2023-09'!$N:$N,'2023-09'!$E:$E,Trésorerie!Z$4,'2023-09'!$F:$F,Trésorerie!$B48) -> -6268 | AA48: =-SUMIFS('2023-10'!$M:$M,'2023-10'!$E:$E,Trésorerie!AA$4,'2023-10'!$F:$F,Trésorerie!$B48)+SUMIFS('2023-10'!$N:$N,'2023-10'!$E:$E,Trésorerie!AA$4,'2023-10'!$F:$F,Trésorerie!$B48) -> -4746 | AB48: =IF(SUM($E48:O48)<SUM($R48:AA48),SUM($E48:O48)-SUM($R48:AA48),0) -> -4078 | AC48: =IF(SUM($E48:P48)<SUM($R48:AB48),SUM($E48:P48)-SUM($R48:AB48),0) -> -5549
A49: =SUM(E49:P49) -> -40608.63 | B49: 467100 | C49: AUXILIAIRE SALARIES | D49: Sortie | E49: =-SUMIFS('2022'!$M:$M,'2022'!$E:$E,Trésorerie!E$4,'2022'!$F:$F,Trésorerie!$B49)+SUMIFS('2022'!$N:$N,'2022'!$E:$E,Trésorerie!E$4,'2022'!$F:$F,Trésorerie!$B49) -> -2973.38 | F49: =-SUMIFS('2022'!$M:$M,'2022'!$E:$E,Trésorerie!F$4,'2022'!$F:$F,Trésorerie!$B49)+SUMIFS('2022'!$N:$N,'2022'!$E:$E,Trésorerie!F$4,'2022'!$F:$F,Trésorerie!$B49) -> -2520.41 | G49: =-SUMIFS('2022'!$M:$M,'2022'!$E:$E,Trésorerie!G$4,'2022'!$F:$F,Trésorerie!$B49)+SUMIFS('2022'!$N:$N,'2022'!$E:$E,Trésorerie!G$4,'2022'!$F:$F,Trésorerie!$B49) -> -1736.14 | H49: =-SUMIFS('2022'!$M:$M,'2022'!$E:$E,Trésorerie!H$4,'2022'!$F:$F,Trésorerie!$B49)+SUMIFS('2022'!$N:$N,'2022'!$E:$E,Trésorerie!H$4,'2022'!$F:$F,Trésorerie!$B49) -> -3008.61 | I49: =-SUMIFS('2022'!$M:$M,'2022'!$E:$E,Trésorerie!I$4,'2022'!$F:$F,Trésorerie!$B49)+SUMIFS('2022'!$N:$N,'2022'!$E:$E,Trésorerie!I$4,'2022'!$F:$F,Trésorerie!$B49) -> -2806.59 | J49: =-SUMIFS('2022'!$M:$M,'2022'!$E:$E,Trésorerie!J$4,'2022'!$F:$F,Trésorerie!$B49)+SUMIFS('2022'!$N:$N,'2022'!$E:$E,Trésorerie!J$4,'2022'!$F:$F,Trésorerie!$B49) -> -4205.02 | K49: =-SUMIFS('2022'!$M:$M,'2022'!$E:$E,Trésorerie!K$4,'2022'!$F:$F,Trésorerie!$B49)+SUMIFS('2022'!$N:$N,'2022'!$E:$E,Trésorerie!K$4,'2022'!$F:$F,Trésorerie!$B49) -> -8237.69 | L49: =-SUMIFS('2022'!$M:$M,'2022'!$E:$E,Trésorerie!L$4,'2022'!$F:$F,Trésorerie!$B49)+SUMIFS('2022'!$N:$N,'2022'!$E:$E,Trésorerie!L$4,'2022'!$F:$F,Trésorerie!$B49) -> -420.65 | ... P49: =-SUMIFS('2022'!$M:$M,'2022'!$E:$E,Trésorerie!P$4,'2022'!$F:$F,Trésorerie!$B49)+SUMIFS('2022'!$N:$N,'2022'!$E:$E,Trésorerie!P$4,'2022'!$F:$F,Trésorerie!$B49) -> -5526.91 | R49: =-SUMIFS('2023-01'!$M:$M,'2023-01'!$E:$E,Trésorerie!R$4,'2023-01'!$F:$F,Trésorerie!$B49)+SUMIFS('2023-01'!$N:$N,'2023-01'!$E:$E,Trésorerie!R$4,'2023-01'!$F:$F,Trésorerie!$B49) -> -1699.49 | S49: =-SUMIFS('2023-02'!$M:$M,'2023-02'!$E:$E,Trésorerie!S$4,'2023-02'!$F:$F,Trésorerie!$B49)+SUMIFS('2023-02'!$N:$N,'2023-02'!$E:$E,Trésorerie!S$4,'2023-02'!$F:$F,Trésorerie!$B49) -> -2996.17 | T49: =-SUMIFS('2023-03'!$M:$M,'2023-03'!$E:$E,Trésorerie!T$4,'2023-03'!$F:$F,Trésorerie!$B49)+SUMIFS('2023-03'!$N:$N,'2023-03'!$E:$E,Trésorerie!T$4,'2023-03'!$F:$F,Trésorerie!$B49) -> -6361.98 | U49: =-SUMIFS('2023-04'!$M:$M,'2023-04'!$E:$E,Trésorerie!U$4,'2023-04'!$F:$F,Trésorerie!$B49)+SUMIFS('2023-04'!$N:$N,'2023-04'!$E:$E,Trésorerie!U$4,'2023-04'!$F:$F,Trésorerie!$B49) -> -2621.36 | V49: =-SUMIFS('2023-05'!$M:$M,'2023-05'!$E:$E,Trésorerie!V$4,'2023-05'!$F:$F,Trésorerie!$B49)+SUMIFS('2023-05'!$N:$N,'2023-05'!$E:$E,Trésorerie!V$4,'2023-05'!$F:$F,Trésorerie!$B49) -> -2546.13 | W49: =-SUMIFS('2023-06'!$M:$M,'2023-06'!$E:$E,Trésorerie!W$4,'2023-06'!$F:$F,Trésorerie!$B49)+SUMIFS('2023-06'!$N:$N,'2023-06'!$E:$E,Trésorerie!W$4,'2023-06'!$F:$F,Trésorerie!$B49) -> -2538.05 | X49: =-SUMIFS('2023-07'!$M:$M,'2023-07'!$E:$E,Trésorerie!X$4,'2023-07'!$F:$F,Trésorerie!$B49)+SUMIFS('2023-07'!$N:$N,'2023-07'!$E:$E,Trésorerie!X$4,'2023-07'!$F:$F,Trésorerie!$B49) -> -4388.08 | Y49: =-SUMIFS('2023-08'!$M:$M,'2023-08'!$E:$E,Trésorerie!Y$4,'2023-08'!$F:$F,Trésorerie!$B49)+SUMIFS('2023-08'!$N:$N,'2023-08'!$E:$E,Trésorerie!Y$4,'2023-08'!$F:$F,Trésorerie!$B49) -> -2232.42 | Z49: =-SUMIFS('2023-09'!$M:$M,'2023-09'!$E:$E,Trésorerie!Z$4,'2023-09'!$F:$F,Trésorerie!$B49)+SUMIFS('2023-09'!$N:$N,'2023-09'!$E:$E,Trésorerie!Z$4,'2023-09'!$F:$F,Trésorerie!$B49) -> -1323.43 | AA49: =-SUMIFS('2023-10'!$M:$M,'2023-10'!$E:$E,Trésorerie!AA$4,'2023-10'!$F:$F,Trésorerie!$B49)+SUMIFS('2023-10'!$N:$N,'2023-10'!$E:$E,Trésorerie!AA$4,'2023-10'!$F:$F,Trésorerie!$B49) -> -1746.58 | AB49: =IF(SUM($E49:O49)<SUM($R49:AA49),SUM($E49:O49)-SUM($R49:AA49),0) -> -6628.03 | AC49: =IF(SUM($E49:P49)<SUM($R49:AB49),SUM($E49:P49)-SUM($R49:AB49),0) -> -5526.91
A50: =SUM(E50:P50) -> -19208.42 | B50: 437000 | C50: MUTUELLE | D50: Sortie | E50: =-SUMIFS('2022'!$M:$M,'2022'!$E:$E,Trésorerie!E$4,'2022'!$F:$F,Trésorerie!$B50)+SUMIFS('2022'!$N:$N,'2022'!$E:$E,Trésorerie!E$4,'2022'!$F:$F,Trésorerie!$B50) -> -1535.4 | F50: =-SUMIFS('2022'!$M:$M,'2022'!$E:$E,Trésorerie!F$4,'2022'!$F:$F,Trésorerie!$B50)+SUMIFS('2022'!$N:$N,'2022'!$E:$E,Trésorerie!F$4,'2022'!$F:$F,Trésorerie!$B50) -> -1481.58 | G50: =-SUMIFS('2022'!$M:$M,'2022'!$E:$E,Trésorerie!G$4,'2022'!$F:$F,Trésorerie!$B50)+SUMIFS('2022'!$N:$N,'2022'!$E:$E,Trésorerie!G$4,'2022'!$F:$F,Trésorerie!$B50) -> -1589.22 | H50: =-SUMIFS('2022'!$M:$M,'2022'!$E:$E,Trésorerie!H$4,'2022'!$F:$F,Trésorerie!$B50)+SUMIFS('2022'!$N:$N,'2022'!$E:$E,Trésorerie!H$4,'2022'!$F:$F,Trésorerie!$B50) -> -1589.22 | I50: =-SUMIFS('2022'!$M:$M,'2022'!$E:$E,Trésorerie!I$4,'2022'!$F:$F,Trésorerie!$B50)+SUMIFS('2022'!$N:$N,'2022'!$E:$E,Trésorerie!I$4,'2022'!$F:$F,Trésorerie!$B50) -> -1535.4 | J50: =-SUMIFS('2022'!$M:$M,'2022'!$E:$E,Trésorerie!J$4,'2022'!$F:$F,Trésorerie!$B50)+SUMIFS('2022'!$N:$N,'2022'!$E:$E,Trésorerie!J$4,'2022'!$F:$F,Trésorerie!$B50) -> -1643.38 | K50: =-SUMIFS('2022'!$M:$M,'2022'!$E:$E,Trésorerie!K$4,'2022'!$F:$F,Trésorerie!$B50)+SUMIFS('2022'!$N:$N,'2022'!$E:$E,Trésorerie!K$4,'2022'!$F:$F,Trésorerie!$B50) -> -1697.2 | L50: =-SUMIFS('2022'!$M:$M,'2022'!$E:$E,Trésorerie!L$4,'2022'!$F:$F,Trésorerie!$B50)+SUMIFS('2022'!$N:$N,'2022'!$E:$E,Trésorerie!L$4,'2022'!$F:$F,Trésorerie!$B50) -> -1751.36 | ... P50: =-SUMIFS('2022'!$M:$M,'2022'!$E:$E,Trésorerie!P$4,'2022'!$F:$F,Trésorerie!$B50)+SUMIFS('2022'!$N:$N,'2022'!$E:$E,Trésorerie!P$4,'2022'!$F:$F,Trésorerie!$B50) -> -1643.38 | R50: =-SUMIFS('2023-01'!$M:$M,'2023-01'!$E:$E,Trésorerie!R$4,'2023-01'!$F:$F,Trésorerie!$B50)+SUMIFS('2023-01'!$N:$N,'2023-01'!$E:$E,Trésorerie!R$4,'2023-01'!$F:$F,Trésorerie!$B50) -> -1562.48 | S50: =-SUMIFS('2023-02'!$M:$M,'2023-02'!$E:$E,Trésorerie!S$4,'2023-02'!$F:$F,Trésorerie!$B50)+SUMIFS('2023-02'!$N:$N,'2023-02'!$E:$E,Trésorerie!S$4,'2023-02'!$F:$F,Trésorerie!$B50) -> -1440.44 | T50: =-SUMIFS('2023-03'!$M:$M,'2023-03'!$E:$E,Trésorerie!T$4,'2023-03'!$F:$F,Trésorerie!$B50)+SUMIFS('2023-03'!$N:$N,'2023-03'!$E:$E,Trésorerie!T$4,'2023-03'!$F:$F,Trésorerie!$B50) -> -1555.92 | U50: =-SUMIFS('2023-04'!$M:$M,'2023-04'!$E:$E,Trésorerie!U$4,'2023-04'!$F:$F,Trésorerie!$B50)+SUMIFS('2023-04'!$N:$N,'2023-04'!$E:$E,Trésorerie!U$4,'2023-04'!$F:$F,Trésorerie!$B50) -> -1989.24 | V50: =-SUMIFS('2023-05'!$M:$M,'2023-05'!$E:$E,Trésorerie!V$4,'2023-05'!$F:$F,Trésorerie!$B50)+SUMIFS('2023-05'!$N:$N,'2023-05'!$E:$E,Trésorerie!V$4,'2023-05'!$F:$F,Trésorerie!$B50) -> -1757.92 | W50: =-SUMIFS('2023-06'!$M:$M,'2023-06'!$E:$E,Trésorerie!W$4,'2023-06'!$F:$F,Trésorerie!$B50)+SUMIFS('2023-06'!$N:$N,'2023-06'!$E:$E,Trésorerie!W$4,'2023-06'!$F:$F,Trésorerie!$B50) -> 1468.32 | X50: =-SUMIFS('2023-07'!$M:$M,'2023-07'!$E:$E,Trésorerie!X$4,'2023-07'!$F:$F,Trésorerie!$B50)+SUMIFS('2023-07'!$N:$N,'2023-07'!$E:$E,Trésorerie!X$4,'2023-07'!$F:$F,Trésorerie!$B50) -> -2076.48 | Y50: =-SUMIFS('2023-08'!$M:$M,'2023-08'!$E:$E,Trésorerie!Y$4,'2023-08'!$F:$F,Trésorerie!$B50)+SUMIFS('2023-08'!$N:$N,'2023-08'!$E:$E,Trésorerie!Y$4,'2023-08'!$F:$F,Trésorerie!$B50) -> -1584.16 | Z50: =-SUMIFS('2023-09'!$M:$M,'2023-09'!$E:$E,Trésorerie!Z$4,'2023-09'!$F:$F,Trésorerie!$B50)+SUMIFS('2023-09'!$N:$N,'2023-09'!$E:$E,Trésorerie!Z$4,'2023-09'!$F:$F,Trésorerie!$B50) -> -1757.92 | AA50: =-SUMIFS('2023-10'!$M:$M,'2023-10'!$E:$E,Trésorerie!AA$4,'2023-10'!$F:$F,Trésorerie!$B50)+SUMIFS('2023-10'!$N:$N,'2023-10'!$E:$E,Trésorerie!AA$4,'2023-10'!$F:$F,Trésorerie!$B50) -> -1584.88 | AB50: =IF(SUM($E50:O50)<SUM($R50:AA50),SUM($E50:O50)-SUM($R50:AA50),0) -> -3723.92 | AC50: =IF(SUM($E50:P50)<SUM($R50:AB50),SUM($E50:P50)-SUM($R50:AB50),0) -> -1643.38
A51: =SUM(E51:P51) -> -16877 | B51: 442100 | C51: PRELEVEMENT A LA SOURCE | D51: Sortie | E51: =-SUMIFS('2022'!$M:$M,'2022'!$E:$E,Trésorerie!E$4,'2022'!$F:$F,Trésorerie!$B51)+SUMIFS('2022'!$N:$N,'2022'!$E:$E,Trésorerie!E$4,'2022'!$F:$F,Trésorerie!$B51) -> -1302 | F51: =-SUMIFS('2022'!$M:$M,'2022'!$E:$E,Trésorerie!F$4,'2022'!$F:$F,Trésorerie!$B51)+SUMIFS('2022'!$N:$N,'2022'!$E:$E,Trésorerie!F$4,'2022'!$F:$F,Trésorerie!$B51) -> -1307 | G51: =-SUMIFS('2022'!$M:$M,'2022'!$E:$E,Trésorerie!G$4,'2022'!$F:$F,Trésorerie!$B51)+SUMIFS('2022'!$N:$N,'2022'!$E:$E,Trésorerie!G$4,'2022'!$F:$F,Trésorerie!$B51) -> -1483 | H51: =-SUMIFS('2022'!$M:$M,'2022'!$E:$E,Trésorerie!H$4,'2022'!$F:$F,Trésorerie!$B51)+SUMIFS('2022'!$N:$N,'2022'!$E:$E,Trésorerie!H$4,'2022'!$F:$F,Trésorerie!$B51) -> -1147 | I51: =-SUMIFS('2022'!$M:$M,'2022'!$E:$E,Trésorerie!I$4,'2022'!$F:$F,Trésorerie!$B51)+SUMIFS('2022'!$N:$N,'2022'!$E:$E,Trésorerie!I$4,'2022'!$F:$F,Trésorerie!$B51) -> -1151 | J51: =-SUMIFS('2022'!$M:$M,'2022'!$E:$E,Trésorerie!J$4,'2022'!$F:$F,Trésorerie!$B51)+SUMIFS('2022'!$N:$N,'2022'!$E:$E,Trésorerie!J$4,'2022'!$F:$F,Trésorerie!$B51) -> -1166 | K51: =-SUMIFS('2022'!$M:$M,'2022'!$E:$E,Trésorerie!K$4,'2022'!$F:$F,Trésorerie!$B51)+SUMIFS('2022'!$N:$N,'2022'!$E:$E,Trésorerie!K$4,'2022'!$F:$F,Trésorerie!$B51) -> -1964 | L51: =-SUMIFS('2022'!$M:$M,'2022'!$E:$E,Trésorerie!L$4,'2022'!$F:$F,Trésorerie!$B51)+SUMIFS('2022'!$N:$N,'2022'!$E:$E,Trésorerie!L$4,'2022'!$F:$F,Trésorerie!$B51) -> -1892 | ... P51: =-SUMIFS('2022'!$M:$M,'2022'!$E:$E,Trésorerie!P$4,'2022'!$F:$F,Trésorerie!$B51)+SUMIFS('2022'!$N:$N,'2022'!$E:$E,Trésorerie!P$4,'2022'!$F:$F,Trésorerie!$B51) -> -1387 | R51: =-SUMIFS('2023-01'!$M:$M,'2023-01'!$E:$E,Trésorerie!R$4,'2023-01'!$F:$F,Trésorerie!$B51)+SUMIFS('2023-01'!$N:$N,'2023-01'!$E:$E,Trésorerie!R$4,'2023-01'!$F:$F,Trésorerie!$B51) -> -3586 | S51: =-SUMIFS('2023-02'!$M:$M,'2023-02'!$E:$E,Trésorerie!S$4,'2023-02'!$F:$F,Trésorerie!$B51)+SUMIFS('2023-02'!$N:$N,'2023-02'!$E:$E,Trésorerie!S$4,'2023-02'!$F:$F,Trésorerie!$B51) -> -596 | T51: =-SUMIFS('2023-03'!$M:$M,'2023-03'!$E:$E,Trésorerie!T$4,'2023-03'!$F:$F,Trésorerie!$B51)+SUMIFS('2023-03'!$N:$N,'2023-03'!$E:$E,Trésorerie!T$4,'2023-03'!$F:$F,Trésorerie!$B51) -> -573 | U51: =-SUMIFS('2023-04'!$M:$M,'2023-04'!$E:$E,Trésorerie!U$4,'2023-04'!$F:$F,Trésorerie!$B51)+SUMIFS('2023-04'!$N:$N,'2023-04'!$E:$E,Trésorerie!U$4,'2023-04'!$F:$F,Trésorerie!$B51) -> -718 | V51: =-SUMIFS('2023-05'!$M:$M,'2023-05'!$E:$E,Trésorerie!V$4,'2023-05'!$F:$F,Trésorerie!$B51)+SUMIFS('2023-05'!$N:$N,'2023-05'!$E:$E,Trésorerie!V$4,'2023-05'!$F:$F,Trésorerie!$B51) -> 0 | W51: =-SUMIFS('2023-06'!$M:$M,'2023-06'!$E:$E,Trésorerie!W$4,'2023-06'!$F:$F,Trésorerie!$B51)+SUMIFS('2023-06'!$N:$N,'2023-06'!$E:$E,Trésorerie!W$4,'2023-06'!$F:$F,Trésorerie!$B51) -> -809 | X51: =-SUMIFS('2023-07'!$M:$M,'2023-07'!$E:$E,Trésorerie!X$4,'2023-07'!$F:$F,Trésorerie!$B51)+SUMIFS('2023-07'!$N:$N,'2023-07'!$E:$E,Trésorerie!X$4,'2023-07'!$F:$F,Trésorerie!$B51) -> -825 | Y51: =-SUMIFS('2023-08'!$M:$M,'2023-08'!$E:$E,Trésorerie!Y$4,'2023-08'!$F:$F,Trésorerie!$B51)+SUMIFS('2023-08'!$N:$N,'2023-08'!$E:$E,Trésorerie!Y$4,'2023-08'!$F:$F,Trésorerie!$B51) -> -836 | Z51: =-SUMIFS('2023-09'!$M:$M,'2023-09'!$E:$E,Trésorerie!Z$4,'2023-09'!$F:$F,Trésorerie!$B51)+SUMIFS('2023-09'!$N:$N,'2023-09'!$E:$E,Trésorerie!Z$4,'2023-09'!$F:$F,Trésorerie!$B51) -> -824 | AA51: =-SUMIFS('2023-10'!$M:$M,'2023-10'!$E:$E,Trésorerie!AA$4,'2023-10'!$F:$F,Trésorerie!$B51)+SUMIFS('2023-10'!$N:$N,'2023-10'!$E:$E,Trésorerie!AA$4,'2023-10'!$F:$F,Trésorerie!$B51) -> -775 | AB51: =IF(SUM($E51:O51)<SUM($R51:AA51),SUM($E51:O51)-SUM($R51:AA51),0) -> -5948 | AC51: =IF(SUM($E51:P51)<SUM($R51:AB51),SUM($E51:P51)-SUM($R51:AB51),0) -> -1387
A52: =SUM(E52:P52) -> -15907 | B52: 448100 | C52: UNIFORMATION FPC A PAYER | D52: Sortie | E52: =-SUMIFS('2022'!$M:$M,'2022'!$E:$E,Trésorerie!E$4,'2022'!$F:$F,Trésorerie!$B52)+SUMIFS('2022'!$N:$N,'2022'!$E:$E,Trésorerie!E$4,'2022'!$F:$F,Trésorerie!$B52) -> 0 | F52: =-SUMIFS('2022'!$M:$M,'2022'!$E:$E,Trésorerie!F$4,'2022'!$F:$F,Trésorerie!$B52)+SUMIFS('2022'!$N:$N,'2022'!$E:$E,Trésorerie!F$4,'2022'!$F:$F,Trésorerie!$B52) -> 0 | G52: =-SUMIFS('2022'!$M:$M,'2022'!$E:$E,Trésorerie!G$4,'2022'!$F:$F,Trésorerie!$B52)+SUMIFS('2022'!$N:$N,'2022'!$E:$E,Trésorerie!G$4,'2022'!$F:$F,Trésorerie!$B52) -> -15907 | H52: =-SUMIFS('2022'!$M:$M,'2022'!$E:$E,Trésorerie!H$4,'2022'!$F:$F,Trésorerie!$B52)+SUMIFS('2022'!$N:$N,'2022'!$E:$E,Trésorerie!H$4,'2022'!$F:$F,Trésorerie!$B52) -> 0 | I52: =-SUMIFS('2022'!$M:$M,'2022'!$E:$E,Trésorerie!I$4,'2022'!$F:$F,Trésorerie!$B52)+SUMIFS('2022'!$N:$N,'2022'!$E:$E,Trésorerie!I$4,'2022'!$F:$F,Trésorerie!$B52) -> 0 | J52: =-SUMIFS('2022'!$M:$M,'2022'!$E:$E,Trésorerie!J$4,'2022'!$F:$F,Trésorerie!$B52)+SUMIFS('2022'!$N:$N,'2022'!$E:$E,Trésorerie!J$4,'2022'!$F:$F,Trésorerie!$B52) -> 0 | K52: =-SUMIFS('2022'!$M:$M,'2022'!$E:$E,Trésorerie!K$4,'2022'!$F:$F,Trésorerie!$B52)+SUMIFS('2022'!$N:$N,'2022'!$E:$E,Trésorerie!K$4,'2022'!$F:$F,Trésorerie!$B52) -> 0 | L52: =-SUMIFS('2022'!$M:$M,'2022'!$E:$E,Trésorerie!L$4,'2022'!$F:$F,Trésorerie!$B52)+SUMIFS('2022'!$N:$N,'2022'!$E:$E,Trésorerie!L$4,'2022'!$F:$F,Trésorerie!$B52) -> 0 | ... P52: =-SUMIFS('2022'!$M:$M,'2022'!$E:$E,Trésorerie!P$4,'2022'!$F:$F,Trésorerie!$B52)+SUMIFS('2022'!$N:$N,'2022'!$E:$E,Trésorerie!P$4,'2022'!$F:$F,Trésorerie!$B52) -> 0 | R52: =-SUMIFS('2023-01'!$M:$M,'2023-01'!$E:$E,Trésorerie!R$4,'2023-01'!$F:$F,Trésorerie!$B52)+SUMIFS('2023-01'!$N:$N,'2023-01'!$E:$E,Trésorerie!R$4,'2023-01'!$F:$F,Trésorerie!$B52) -> 0 | S52: =-SUMIFS('2023-02'!$M:$M,'2023-02'!$E:$E,Trésorerie!S$4,'2023-02'!$F:$F,Trésorerie!$B52)+SUMIFS('2023-02'!$N:$N,'2023-02'!$E:$E,Trésorerie!S$4,'2023-02'!$F:$F,Trésorerie!$B52) -> -9461 | T52: =-SUMIFS('2023-03'!$M:$M,'2023-03'!$E:$E,Trésorerie!T$4,'2023-03'!$F:$F,Trésorerie!$B52)+SUMIFS('2023-03'!$N:$N,'2023-03'!$E:$E,Trésorerie!T$4,'2023-03'!$F:$F,Trésorerie!$B52) -> 0 | U52: =-SUMIFS('2023-04'!$M:$M,'2023-04'!$E:$E,Trésorerie!U$4,'2023-04'!$F:$F,Trésorerie!$B52)+SUMIFS('2023-04'!$N:$N,'2023-04'!$E:$E,Trésorerie!U$4,'2023-04'!$F:$F,Trésorerie!$B52) -> 0 | V52: =-SUMIFS('2023-05'!$M:$M,'2023-05'!$E:$E,Trésorerie!V$4,'2023-05'!$F:$F,Trésorerie!$B52)+SUMIFS('2023-05'!$N:$N,'2023-05'!$E:$E,Trésorerie!V$4,'2023-05'!$F:$F,Trésorerie!$B52) -> 0 | W52: =-SUMIFS('2023-06'!$M:$M,'2023-06'!$E:$E,Trésorerie!W$4,'2023-06'!$F:$F,Trésorerie!$B52)+SUMIFS('2023-06'!$N:$N,'2023-06'!$E:$E,Trésorerie!W$4,'2023-06'!$F:$F,Trésorerie!$B52) -> 0 | X52: =-SUMIFS('2023-07'!$M:$M,'2023-07'!$E:$E,Trésorerie!X$4,'2023-07'!$F:$F,Trésorerie!$B52)+SUMIFS('2023-07'!$N:$N,'2023-07'!$E:$E,Trésorerie!X$4,'2023-07'!$F:$F,Trésorerie!$B52) -> 0 | Y52: =-SUMIFS('2023-08'!$M:$M,'2023-08'!$E:$E,Trésorerie!Y$4,'2023-08'!$F:$F,Trésorerie!$B52)+SUMIFS('2023-08'!$N:$N,'2023-08'!$E:$E,Trésorerie!Y$4,'2023-08'!$F:$F,Trésorerie!$B52) -> 0 | Z52: =-SUMIFS('2023-09'!$M:$M,'2023-09'!$E:$E,Trésorerie!Z$4,'2023-09'!$F:$F,Trésorerie!$B52)+SUMIFS('2023-09'!$N:$N,'2023-09'!$E:$E,Trésorerie!Z$4,'2023-09'!$F:$F,Trésorerie!$B52) -> -4488 | AA52: =-SUMIFS('2023-10'!$M:$M,'2023-10'!$E:$E,Trésorerie!AA$4,'2023-10'!$F:$F,Trésorerie!$B52)+SUMIFS('2023-10'!$N:$N,'2023-10'!$E:$E,Trésorerie!AA$4,'2023-10'!$F:$F,Trésorerie!$B52) -> 0 | AB52: =IF(SUM($E52:O52)<SUM($R52:AA52),SUM($E52:O52)-SUM($R52:AA52),0) -> -1958 | AC52: =IF(SUM($E52:P52)<SUM($R52:AB52),SUM($E52:P52)-SUM($R52:AB52),0) -> 0
A53: =SUM(E53:P53) -> -15079.83 | B53: 433100 | C53: CHORUM PREVOYANCE C+NC | D53: Sortie | E53: =-SUMIFS('2022'!$M:$M,'2022'!$E:$E,Trésorerie!E$4,'2022'!$F:$F,Trésorerie!$B53)+SUMIFS('2022'!$N:$N,'2022'!$E:$E,Trésorerie!E$4,'2022'!$F:$F,Trésorerie!$B53) -> -1242.59 | F53: =-SUMIFS('2022'!$M:$M,'2022'!$E:$E,Trésorerie!F$4,'2022'!$F:$F,Trésorerie!$B53)+SUMIFS('2022'!$N:$N,'2022'!$E:$E,Trésorerie!F$4,'2022'!$F:$F,Trésorerie!$B53) -> -1246.29 | G53: =-SUMIFS('2022'!$M:$M,'2022'!$E:$E,Trésorerie!G$4,'2022'!$F:$F,Trésorerie!$B53)+SUMIFS('2022'!$N:$N,'2022'!$E:$E,Trésorerie!G$4,'2022'!$F:$F,Trésorerie!$B53) -> -1390.27 | H53: =-SUMIFS('2022'!$M:$M,'2022'!$E:$E,Trésorerie!H$4,'2022'!$F:$F,Trésorerie!$B53)+SUMIFS('2022'!$N:$N,'2022'!$E:$E,Trésorerie!H$4,'2022'!$F:$F,Trésorerie!$B53) -> -1327.77 | I53: =-SUMIFS('2022'!$M:$M,'2022'!$E:$E,Trésorerie!I$4,'2022'!$F:$F,Trésorerie!$B53)+SUMIFS('2022'!$N:$N,'2022'!$E:$E,Trésorerie!I$4,'2022'!$F:$F,Trésorerie!$B53) -> -1348.6 | J53: =-SUMIFS('2022'!$M:$M,'2022'!$E:$E,Trésorerie!J$4,'2022'!$F:$F,Trésorerie!$B53)+SUMIFS('2022'!$N:$N,'2022'!$E:$E,Trésorerie!J$4,'2022'!$F:$F,Trésorerie!$B53) -> -1318.02 | K53: =-SUMIFS('2022'!$M:$M,'2022'!$E:$E,Trésorerie!K$4,'2022'!$F:$F,Trésorerie!$B53)+SUMIFS('2022'!$N:$N,'2022'!$E:$E,Trésorerie!K$4,'2022'!$F:$F,Trésorerie!$B53) -> -1420.75 | L53: =-SUMIFS('2022'!$M:$M,'2022'!$E:$E,Trésorerie!L$4,'2022'!$F:$F,Trésorerie!$B53)+SUMIFS('2022'!$N:$N,'2022'!$E:$E,Trésorerie!L$4,'2022'!$F:$F,Trésorerie!$B53) -> -1410.47 | ... P53: =-SUMIFS('2022'!$M:$M,'2022'!$E:$E,Trésorerie!P$4,'2022'!$F:$F,Trésorerie!$B53)+SUMIFS('2022'!$N:$N,'2022'!$E:$E,Trésorerie!P$4,'2022'!$F:$F,Trésorerie!$B53) -> -891.46 | R53: =-SUMIFS('2023-01'!$M:$M,'2023-01'!$E:$E,Trésorerie!R$4,'2023-01'!$F:$F,Trésorerie!$B53)+SUMIFS('2023-01'!$N:$N,'2023-01'!$E:$E,Trésorerie!R$4,'2023-01'!$F:$F,Trésorerie!$B53) -> -1312.38 | S53: =-SUMIFS('2023-02'!$M:$M,'2023-02'!$E:$E,Trésorerie!S$4,'2023-02'!$F:$F,Trésorerie!$B53)+SUMIFS('2023-02'!$N:$N,'2023-02'!$E:$E,Trésorerie!S$4,'2023-02'!$F:$F,Trésorerie!$B53) -> 0 | T53: =-SUMIFS('2023-03'!$M:$M,'2023-03'!$E:$E,Trésorerie!T$4,'2023-03'!$F:$F,Trésorerie!$B53)+SUMIFS('2023-03'!$N:$N,'2023-03'!$E:$E,Trésorerie!T$4,'2023-03'!$F:$F,Trésorerie!$B53) -> -2217.32 | U53: =-SUMIFS('2023-04'!$M:$M,'2023-04'!$E:$E,Trésorerie!U$4,'2023-04'!$F:$F,Trésorerie!$B53)+SUMIFS('2023-04'!$N:$N,'2023-04'!$E:$E,Trésorerie!U$4,'2023-04'!$F:$F,Trésorerie!$B53) -> -1264.41 | V53: =-SUMIFS('2023-05'!$M:$M,'2023-05'!$E:$E,Trésorerie!V$4,'2023-05'!$F:$F,Trésorerie!$B53)+SUMIFS('2023-05'!$N:$N,'2023-05'!$E:$E,Trésorerie!V$4,'2023-05'!$F:$F,Trésorerie!$B53) -> 0 | W53: =-SUMIFS('2023-06'!$M:$M,'2023-06'!$E:$E,Trésorerie!W$4,'2023-06'!$F:$F,Trésorerie!$B53)+SUMIFS('2023-06'!$N:$N,'2023-06'!$E:$E,Trésorerie!W$4,'2023-06'!$F:$F,Trésorerie!$B53) -> -1315.28 | X53: =-SUMIFS('2023-07'!$M:$M,'2023-07'!$E:$E,Trésorerie!X$4,'2023-07'!$F:$F,Trésorerie!$B53)+SUMIFS('2023-07'!$N:$N,'2023-07'!$E:$E,Trésorerie!X$4,'2023-07'!$F:$F,Trésorerie!$B53) -> -1485.08 | Y53: =-SUMIFS('2023-08'!$M:$M,'2023-08'!$E:$E,Trésorerie!Y$4,'2023-08'!$F:$F,Trésorerie!$B53)+SUMIFS('2023-08'!$N:$N,'2023-08'!$E:$E,Trésorerie!Y$4,'2023-08'!$F:$F,Trésorerie!$B53) -> -1398.47 | Z53: =-SUMIFS('2023-09'!$M:$M,'2023-09'!$E:$E,Trésorerie!Z$4,'2023-09'!$F:$F,Trésorerie!$B53)+SUMIFS('2023-09'!$N:$N,'2023-09'!$E:$E,Trésorerie!Z$4,'2023-09'!$F:$F,Trésorerie!$B53) -> 0 | AA53: =-SUMIFS('2023-10'!$M:$M,'2023-10'!$E:$E,Trésorerie!AA$4,'2023-10'!$F:$F,Trésorerie!$B53)+SUMIFS('2023-10'!$N:$N,'2023-10'!$E:$E,Trésorerie!AA$4,'2023-10'!$F:$F,Trésorerie!$B53) -> -2449.93 | AB53: =IF(SUM($E53:O53)<SUM($R53:AA53),SUM($E53:O53)-SUM($R53:AA53),0) -> -2745.5 | AC53: =IF(SUM($E53:P53)<SUM($R53:AB53),SUM($E53:P53)-SUM($R53:AB53),0) -> -891.46
A54: =SUM(E54:P54) -> -12904.62 | B54: 437100 | C54: CONTRIBUTION CNRACL | D54: Sortie | E54: =-SUMIFS('2022'!$M:$M,'2022'!$E:$E,Trésorerie!E$4,'2022'!$F:$F,Trésorerie!$B54)+SUMIFS('2022'!$N:$N,'2022'!$E:$E,Trésorerie!E$4,'2022'!$F:$F,Trésorerie!$B54) -> -1473.6 | F54: =-SUMIFS('2022'!$M:$M,'2022'!$E:$E,Trésorerie!F$4,'2022'!$F:$F,Trésorerie!$B54)+SUMIFS('2022'!$N:$N,'2022'!$E:$E,Trésorerie!F$4,'2022'!$F:$F,Trésorerie!$B54) -> -736.8 | G54: =-SUMIFS('2022'!$M:$M,'2022'!$E:$E,Trésorerie!G$4,'2022'!$F:$F,Trésorerie!$B54)+SUMIFS('2022'!$N:$N,'2022'!$E:$E,Trésorerie!G$4,'2022'!$F:$F,Trésorerie!$B54) -> -736.8 | H54: =-SUMIFS('2022'!$M:$M,'2022'!$E:$E,Trésorerie!H$4,'2022'!$F:$F,Trésorerie!$B54)+SUMIFS('2022'!$N:$N,'2022'!$E:$E,Trésorerie!H$4,'2022'!$F:$F,Trésorerie!$B54) -> 0 | I54: =-SUMIFS('2022'!$M:$M,'2022'!$E:$E,Trésorerie!I$4,'2022'!$F:$F,Trésorerie!$B54)+SUMIFS('2022'!$N:$N,'2022'!$E:$E,Trésorerie!I$4,'2022'!$F:$F,Trésorerie!$B54) -> -736.8 | J54: =-SUMIFS('2022'!$M:$M,'2022'!$E:$E,Trésorerie!J$4,'2022'!$F:$F,Trésorerie!$B54)+SUMIFS('2022'!$N:$N,'2022'!$E:$E,Trésorerie!J$4,'2022'!$F:$F,Trésorerie!$B54) -> -736.8 | K54: =-SUMIFS('2022'!$M:$M,'2022'!$E:$E,Trésorerie!K$4,'2022'!$F:$F,Trésorerie!$B54)+SUMIFS('2022'!$N:$N,'2022'!$E:$E,Trésorerie!K$4,'2022'!$F:$F,Trésorerie!$B54) -> -736.8 | L54: =-SUMIFS('2022'!$M:$M,'2022'!$E:$E,Trésorerie!L$4,'2022'!$F:$F,Trésorerie!$B54)+SUMIFS('2022'!$N:$N,'2022'!$E:$E,Trésorerie!L$4,'2022'!$F:$F,Trésorerie!$B54) -> -1404.66 | ... P54: =-SUMIFS('2022'!$M:$M,'2022'!$E:$E,Trésorerie!P$4,'2022'!$F:$F,Trésorerie!$B54)+SUMIFS('2022'!$N:$N,'2022'!$E:$E,Trésorerie!P$4,'2022'!$F:$F,Trésorerie!$B54) -> 0 | R54: =-SUMIFS('2023-01'!$M:$M,'2023-01'!$E:$E,Trésorerie!R$4,'2023-01'!$F:$F,Trésorerie!$B54)+SUMIFS('2023-01'!$N:$N,'2023-01'!$E:$E,Trésorerie!R$4,'2023-01'!$F:$F,Trésorerie!$B54) -> -3002.78 | S54: =-SUMIFS('2023-02'!$M:$M,'2023-02'!$E:$E,Trésorerie!S$4,'2023-02'!$F:$F,Trésorerie!$B54)+SUMIFS('2023-02'!$N:$N,'2023-02'!$E:$E,Trésorerie!S$4,'2023-02'!$F:$F,Trésorerie!$B54) -> 0 | T54: =-SUMIFS('2023-03'!$M:$M,'2023-03'!$E:$E,Trésorerie!T$4,'2023-03'!$F:$F,Trésorerie!$B54)+SUMIFS('2023-03'!$N:$N,'2023-03'!$E:$E,Trésorerie!T$4,'2023-03'!$F:$F,Trésorerie!$B54) -> -1409.49 | U54: =-SUMIFS('2023-04'!$M:$M,'2023-04'!$E:$E,Trésorerie!U$4,'2023-04'!$F:$F,Trésorerie!$B54)+SUMIFS('2023-04'!$N:$N,'2023-04'!$E:$E,Trésorerie!U$4,'2023-04'!$F:$F,Trésorerie!$B54) -> -1382.48 | V54: =-SUMIFS('2023-05'!$M:$M,'2023-05'!$E:$E,Trésorerie!V$4,'2023-05'!$F:$F,Trésorerie!$B54)+SUMIFS('2023-05'!$N:$N,'2023-05'!$E:$E,Trésorerie!V$4,'2023-05'!$F:$F,Trésorerie!$B54) -> 0 | W54: =-SUMIFS('2023-06'!$M:$M,'2023-06'!$E:$E,Trésorerie!W$4,'2023-06'!$F:$F,Trésorerie!$B54)+SUMIFS('2023-06'!$N:$N,'2023-06'!$E:$E,Trésorerie!W$4,'2023-06'!$F:$F,Trésorerie!$B54) -> -691.24 | X54: =-SUMIFS('2023-07'!$M:$M,'2023-07'!$E:$E,Trésorerie!X$4,'2023-07'!$F:$F,Trésorerie!$B54)+SUMIFS('2023-07'!$N:$N,'2023-07'!$E:$E,Trésorerie!X$4,'2023-07'!$F:$F,Trésorerie!$B54) -> -691.24 | Y54: =-SUMIFS('2023-08'!$M:$M,'2023-08'!$E:$E,Trésorerie!Y$4,'2023-08'!$F:$F,Trésorerie!$B54)+SUMIFS('2023-08'!$N:$N,'2023-08'!$E:$E,Trésorerie!Y$4,'2023-08'!$F:$F,Trésorerie!$B54) -> 0 | Z54: =-SUMIFS('2023-09'!$M:$M,'2023-09'!$E:$E,Trésorerie!Z$4,'2023-09'!$F:$F,Trésorerie!$B54)+SUMIFS('2023-09'!$N:$N,'2023-09'!$E:$E,Trésorerie!Z$4,'2023-09'!$F:$F,Trésorerie!$B54) -> -771.77 | AA54: =-SUMIFS('2023-10'!$M:$M,'2023-10'!$E:$E,Trésorerie!AA$4,'2023-10'!$F:$F,Trésorerie!$B54)+SUMIFS('2023-10'!$N:$N,'2023-10'!$E:$E,Trésorerie!AA$4,'2023-10'!$F:$F,Trésorerie!$B54) -> 0 | AB54: =IF(SUM($E54:O54)<SUM($R54:AA54),SUM($E54:O54)-SUM($R54:AA54),0) -> -4955.62 | AC54: =IF(SUM($E54:P54)<SUM($R54:AB54),SUM($E54:P54)-SUM($R54:AB54),0) -> 0
A55: =SUM(E55:P55) -> -9583.86 | B55: 422000 | C55: COMITE D'ETABLISSEMENT | D55: Sortie | E55: =-SUMIFS('2022'!$M:$M,'2022'!$E:$E,Trésorerie!E$4,'2022'!$F:$F,Trésorerie!$B55)+SUMIFS('2022'!$N:$N,'2022'!$E:$E,Trésorerie!E$4,'2022'!$F:$F,Trésorerie!$B55) -> 0 | F55: =-SUMIFS('2022'!$M:$M,'2022'!$E:$E,Trésorerie!F$4,'2022'!$F:$F,Trésorerie!$B55)+SUMIFS('2022'!$N:$N,'2022'!$E:$E,Trésorerie!F$4,'2022'!$F:$F,Trésorerie!$B55) -> 0 | G55: =-SUMIFS('2022'!$M:$M,'2022'!$E:$E,Trésorerie!G$4,'2022'!$F:$F,Trésorerie!$B55)+SUMIFS('2022'!$N:$N,'2022'!$E:$E,Trésorerie!G$4,'2022'!$F:$F,Trésorerie!$B55) -> -5583.86 | H55: =-SUMIFS('2022'!$M:$M,'2022'!$E:$E,Trésorerie!H$4,'2022'!$F:$F,Trésorerie!$B55)+SUMIFS('2022'!$N:$N,'2022'!$E:$E,Trésorerie!H$4,'2022'!$F:$F,Trésorerie!$B55) -> 0 | I55: =-SUMIFS('2022'!$M:$M,'2022'!$E:$E,Trésorerie!I$4,'2022'!$F:$F,Trésorerie!$B55)+SUMIFS('2022'!$N:$N,'2022'!$E:$E,Trésorerie!I$4,'2022'!$F:$F,Trésorerie!$B55) -> 0 | J55: =-SUMIFS('2022'!$M:$M,'2022'!$E:$E,Trésorerie!J$4,'2022'!$F:$F,Trésorerie!$B55)+SUMIFS('2022'!$N:$N,'2022'!$E:$E,Trésorerie!J$4,'2022'!$F:$F,Trésorerie!$B55) -> -4000 | K55: =-SUMIFS('2022'!$M:$M,'2022'!$E:$E,Trésorerie!K$4,'2022'!$F:$F,Trésorerie!$B55)+SUMIFS('2022'!$N:$N,'2022'!$E:$E,Trésorerie!K$4,'2022'!$F:$F,Trésorerie!$B55) -> 0 | L55: =-SUMIFS('2022'!$M:$M,'2022'!$E:$E,Trésorerie!L$4,'2022'!$F:$F,Trésorerie!$B55)+SUMIFS('2022'!$N:$N,'2022'!$E:$E,Trésorerie!L$4,'2022'!$F:$F,Trésorerie!$B55) -> 0 | ... P55: =-SUMIFS('2022'!$M:$M,'2022'!$E:$E,Trésorerie!P$4,'2022'!$F:$F,Trésorerie!$B55)+SUMIFS('2022'!$N:$N,'2022'!$E:$E,Trésorerie!P$4,'2022'!$F:$F,Trésorerie!$B55) -> 0 | R55: =-SUMIFS('2023-01'!$M:$M,'2023-01'!$E:$E,Trésorerie!R$4,'2023-01'!$F:$F,Trésorerie!$B55)+SUMIFS('2023-01'!$N:$N,'2023-01'!$E:$E,Trésorerie!R$4,'2023-01'!$F:$F,Trésorerie!$B55) -> 0 | S55: =-SUMIFS('2023-02'!$M:$M,'2023-02'!$E:$E,Trésorerie!S$4,'2023-02'!$F:$F,Trésorerie!$B55)+SUMIFS('2023-02'!$N:$N,'2023-02'!$E:$E,Trésorerie!S$4,'2023-02'!$F:$F,Trésorerie!$B55) -> 0 | T55: =-SUMIFS('2023-03'!$M:$M,'2023-03'!$E:$E,Trésorerie!T$4,'2023-03'!$F:$F,Trésorerie!$B55)+SUMIFS('2023-03'!$N:$N,'2023-03'!$E:$E,Trésorerie!T$4,'2023-03'!$F:$F,Trésorerie!$B55) -> 0 | U55: =-SUMIFS('2023-04'!$M:$M,'2023-04'!$E:$E,Trésorerie!U$4,'2023-04'!$F:$F,Trésorerie!$B55)+SUMIFS('2023-04'!$N:$N,'2023-04'!$E:$E,Trésorerie!U$4,'2023-04'!$F:$F,Trésorerie!$B55) -> 0 | V55: =-SUMIFS('2023-05'!$M:$M,'2023-05'!$E:$E,Trésorerie!V$4,'2023-05'!$F:$F,Trésorerie!$B55)+SUMIFS('2023-05'!$N:$N,'2023-05'!$E:$E,Trésorerie!V$4,'2023-05'!$F:$F,Trésorerie!$B55) -> -10082.18 | W55: =-SUMIFS('2023-06'!$M:$M,'2023-06'!$E:$E,Trésorerie!W$4,'2023-06'!$F:$F,Trésorerie!$B55)+SUMIFS('2023-06'!$N:$N,'2023-06'!$E:$E,Trésorerie!W$4,'2023-06'!$F:$F,Trésorerie!$B55) -> 0 | X55: =-SUMIFS('2023-07'!$M:$M,'2023-07'!$E:$E,Trésorerie!X$4,'2023-07'!$F:$F,Trésorerie!$B55)+SUMIFS('2023-07'!$N:$N,'2023-07'!$E:$E,Trésorerie!X$4,'2023-07'!$F:$F,Trésorerie!$B55) -> 0 | Y55: =-SUMIFS('2023-08'!$M:$M,'2023-08'!$E:$E,Trésorerie!Y$4,'2023-08'!$F:$F,Trésorerie!$B55)+SUMIFS('2023-08'!$N:$N,'2023-08'!$E:$E,Trésorerie!Y$4,'2023-08'!$F:$F,Trésorerie!$B55) -> 0 | Z55: =-SUMIFS('2023-09'!$M:$M,'2023-09'!$E:$E,Trésorerie!Z$4,'2023-09'!$F:$F,Trésorerie!$B55)+SUMIFS('2023-09'!$N:$N,'2023-09'!$E:$E,Trésorerie!Z$4,'2023-09'!$F:$F,Trésorerie!$B55) -> 0 | AA55: =-SUMIFS('2023-10'!$M:$M,'2023-10'!$E:$E,Trésorerie!AA$4,'2023-10'!$F:$F,Trésorerie!$B55)+SUMIFS('2023-10'!$N:$N,'2023-10'!$E:$E,Trésorerie!AA$4,'2023-10'!$F:$F,Trésorerie!$B55) -> 0 | AB55: =IF(SUM($E55:O55)<SUM($R55:AA55),SUM($E55:O55)-SUM($R55:AA55),0) -> 0 | AC55: =IF(SUM($E55:P55)<SUM($R55:AB55),SUM($E55:P55)-SUM($R55:AB55),0) -> 0
... A69: =SUM(E69:P69) -> -33.46 | B69: 427000 | C69: SAISIE SUR SALAIRE | D69: Sortie | E69: =-SUMIFS('2022'!$M:$M,'2022'!$E:$E,Trésorerie!E$4,'2022'!$F:$F,Trésorerie!$B69)+SUMIFS('2022'!$N:$N,'2022'!$E:$E,Trésorerie!E$4,'2022'!$F:$F,Trésorerie!$B69) -> 0 | F69: =-SUMIFS('2022'!$M:$M,'2022'!$E:$E,Trésorerie!F$4,'2022'!$F:$F,Trésorerie!$B69)+SUMIFS('2022'!$N:$N,'2022'!$E:$E,Trésorerie!F$4,'2022'!$F:$F,Trésorerie!$B69) -> 0 | G69: =-SUMIFS('2022'!$M:$M,'2022'!$E:$E,Trésorerie!G$4,'2022'!$F:$F,Trésorerie!$B69)+SUMIFS('2022'!$N:$N,'2022'!$E:$E,Trésorerie!G$4,'2022'!$F:$F,Trésorerie!$B69) -> 0 | H69: =-SUMIFS('2022'!$M:$M,'2022'!$E:$E,Trésorerie!H$4,'2022'!$F:$F,Trésorerie!$B69)+SUMIFS('2022'!$N:$N,'2022'!$E:$E,Trésorerie!H$4,'2022'!$F:$F,Trésorerie!$B69) -> 0 | I69: =-SUMIFS('2022'!$M:$M,'2022'!$E:$E,Trésorerie!I$4,'2022'!$F:$F,Trésorerie!$B69)+SUMIFS('2022'!$N:$N,'2022'!$E:$E,Trésorerie!I$4,'2022'!$F:$F,Trésorerie!$B69) -> 0 | J69: =-SUMIFS('2022'!$M:$M,'2022'!$E:$E,Trésorerie!J$4,'2022'!$F:$F,Trésorerie!$B69)+SUMIFS('2022'!$N:$N,'2022'!$E:$E,Trésorerie!J$4,'2022'!$F:$F,Trésorerie!$B69) -> 0 | K69: =-SUMIFS('2022'!$M:$M,'2022'!$E:$E,Trésorerie!K$4,'2022'!$F:$F,Trésorerie!$B69)+SUMIFS('2022'!$N:$N,'2022'!$E:$E,Trésorerie!K$4,'2022'!$F:$F,Trésorerie!$B69) -> 0 | L69: =-SUMIFS('2022'!$M:$M,'2022'!$E:$E,Trésorerie!L$4,'2022'!$F:$F,Trésorerie!$B69)+SUMIFS('2022'!$N:$N,'2022'!$E:$E,Trésorerie!L$4,'2022'!$F:$F,Trésorerie!$B69) -> 0 | ... P69: =-SUMIFS('2022'!$M:$M,'2022'!$E:$E,Trésorerie!P$4,'2022'!$F:$F,Trésorerie!$B69)+SUMIFS('2022'!$N:$N,'2022'!$E:$E,Trésorerie!P$4,'2022'!$F:$F,Trésorerie!$B69) -> 0 | R69: =-SUMIFS('2023-01'!$M:$M,'2023-01'!$E:$E,Trésorerie!R$4,'2023-01'!$F:$F,Trésorerie!$B69)+SUMIFS('2023-01'!$N:$N,'2023-01'!$E:$E,Trésorerie!R$4,'2023-01'!$F:$F,Trésorerie!$B69) -> -256.01 | S69: =-SUMIFS('2023-02'!$M:$M,'2023-02'!$E:$E,Trésorerie!S$4,'2023-02'!$F:$F,Trésorerie!$B69)+SUMIFS('2023-02'!$N:$N,'2023-02'!$E:$E,Trésorerie!S$4,'2023-02'!$F:$F,Trésorerie!$B69) -> 0 | T69: =-SUMIFS('2023-03'!$M:$M,'2023-03'!$E:$E,Trésorerie!T$4,'2023-03'!$F:$F,Trésorerie!$B69)+SUMIFS('2023-03'!$N:$N,'2023-03'!$E:$E,Trésorerie!T$4,'2023-03'!$F:$F,Trésorerie!$B69) -> 0 | U69: =-SUMIFS('2023-04'!$M:$M,'2023-04'!$E:$E,Trésorerie!U$4,'2023-04'!$F:$F,Trésorerie!$B69)+SUMIFS('2023-04'!$N:$N,'2023-04'!$E:$E,Trésorerie!U$4,'2023-04'!$F:$F,Trésorerie!$B69) -> 0 | V69: =-SUMIFS('2023-05'!$M:$M,'2023-05'!$E:$E,Trésorerie!V$4,'2023-05'!$F:$F,Trésorerie!$B69)+SUMIFS('2023-05'!$N:$N,'2023-05'!$E:$E,Trésorerie!V$4,'2023-05'!$F:$F,Trésorerie!$B69) -> 0 | W69: =-SUMIFS('2023-06'!$M:$M,'2023-06'!$E:$E,Trésorerie!W$4,'2023-06'!$F:$F,Trésorerie!$B69)+SUMIFS('2023-06'!$N:$N,'2023-06'!$E:$E,Trésorerie!W$4,'2023-06'!$F:$F,Trésorerie!$B69) -> 0 | X69: =-SUMIFS('2023-07'!$M:$M,'2023-07'!$E:$E,Trésorerie!X$4,'2023-07'!$F:$F,Trésorerie!$B69)+SUMIFS('2023-07'!$N:$N,'2023-07'!$E:$E,Trésorerie!X$4,'2023-07'!$F:$F,Trésorerie!$B69) -> 0 | Y69: =-SUMIFS('2023-08'!$M:$M,'2023-08'!$E:$E,Trésorerie!Y$4,'2023-08'!$F:$F,Trésorerie!$B69)+SUMIFS('2023-08'!$N:$N,'2023-08'!$E:$E,Trésorerie!Y$4,'2023-08'!$F:$F,Trésorerie!$B69) -> 0 | Z69: =-SUMIFS('2023-09'!$M:$M,'2023-09'!$E:$E,Trésorerie!Z$4,'2023-09'!$F:$F,Trésorerie!$B69)+SUMIFS('2023-09'!$N:$N,'2023-09'!$E:$E,Trésorerie!Z$4,'2023-09'!$F:$F,Trésorerie!$B69) -> 0 | AA69: =-SUMIFS('2023-10'!$M:$M,'2023-10'!$E:$E,Trésorerie!AA$4,'2023-10'!$F:$F,Trésorerie!$B69)+SUMIFS('2023-10'!$N:$N,'2023-10'!$E:$E,Trésorerie!AA$4,'2023-10'!$F:$F,Trésorerie!$B69) -> 0 | AB69: =IF(SUM($E69:O69)<SUM($R69:AA69),SUM($E69:O69)-SUM($R69:AA69),0) -> 0 | AC69: =IF(SUM($E69:P69)<SUM($R69:AB69),SUM($E69:P69)-SUM($R69:AB69),0) -> 0
A70: =SUM(E70:P70) -> 0 | B70: 471000 | C70: COMPTE D'ATTENTE | D70: Sortie | E70: =-SUMIFS('2022'!$M:$M,'2022'!$E:$E,Trésorerie!E$4,'2022'!$F:$F,Trésorerie!$B70)+SUMIFS('2022'!$N:$N,'2022'!$E:$E,Trésorerie!E$4,'2022'!$F:$F,Trésorerie!$B70) -> 0 | F70: =-SUMIFS('2022'!$M:$M,'2022'!$E:$E,Trésorerie!F$4,'2022'!$F:$F,Trésorerie!$B70)+SUMIFS('2022'!$N:$N,'2022'!$E:$E,Trésorerie!F$4,'2022'!$F:$F,Trésorerie!$B70) -> 0 | G70: =-SUMIFS('2022'!$M:$M,'2022'!$E:$E,Trésorerie!G$4,'2022'!$F:$F,Trésorerie!$B70)+SUMIFS('2022'!$N:$N,'2022'!$E:$E,Trésorerie!G$4,'2022'!$F:$F,Trésorerie!$B70) -> 0 | H70: =-SUMIFS('2022'!$M:$M,'2022'!$E:$E,Trésorerie!H$4,'2022'!$F:$F,Trésorerie!$B70)+SUMIFS('2022'!$N:$N,'2022'!$E:$E,Trésorerie!H$4,'2022'!$F:$F,Trésorerie!$B70) -> 0 | I70: =-SUMIFS('2022'!$M:$M,'2022'!$E:$E,Trésorerie!I$4,'2022'!$F:$F,Trésorerie!$B70)+SUMIFS('2022'!$N:$N,'2022'!$E:$E,Trésorerie!I$4,'2022'!$F:$F,Trésorerie!$B70) -> 0 | J70: =-SUMIFS('2022'!$M:$M,'2022'!$E:$E,Trésorerie!J$4,'2022'!$F:$F,Trésorerie!$B70)+SUMIFS('2022'!$N:$N,'2022'!$E:$E,Trésorerie!J$4,'2022'!$F:$F,Trésorerie!$B70) -> 0 | K70: =-SUMIFS('2022'!$M:$M,'2022'!$E:$E,Trésorerie!K$4,'2022'!$F:$F,Trésorerie!$B70)+SUMIFS('2022'!$N:$N,'2022'!$E:$E,Trésorerie!K$4,'2022'!$F:$F,Trésorerie!$B70) -> 0 | L70: =-SUMIFS('2022'!$M:$M,'2022'!$E:$E,Trésorerie!L$4,'2022'!$F:$F,Trésorerie!$B70)+SUMIFS('2022'!$N:$N,'2022'!$E:$E,Trésorerie!L$4,'2022'!$F:$F,Trésorerie!$B70) -> 0 | ... P70: =-SUMIFS('2022'!$M:$M,'2022'!$E:$E,Trésorerie!P$4,'2022'!$F:$F,Trésorerie!$B70)+SUMIFS('2022'!$N:$N,'2022'!$E:$E,Trésorerie!P$4,'2022'!$F:$F,Trésorerie!$B70) -> 0 | R70: =-SUMIFS('2023-01'!$M:$M,'2023-01'!$E:$E,Trésorerie!R$4,'2023-01'!$F:$F,Trésorerie!$B70)+SUMIFS('2023-01'!$N:$N,'2023-01'!$E:$E,Trésorerie!R$4,'2023-01'!$F:$F,Trésorerie!$B70) -> -28701.41 | S70: =-SUMIFS('2023-02'!$M:$M,'2023-02'!$E:$E,Trésorerie!S$4,'2023-02'!$F:$F,Trésorerie!$B70)+SUMIFS('2023-02'!$N:$N,'2023-02'!$E:$E,Trésorerie!S$4,'2023-02'!$F:$F,Trésorerie!$B70) -> -1429.15 | T70: =-SUMIFS('2023-03'!$M:$M,'2023-03'!$E:$E,Trésorerie!T$4,'2023-03'!$F:$F,Trésorerie!$B70)+SUMIFS('2023-03'!$N:$N,'2023-03'!$E:$E,Trésorerie!T$4,'2023-03'!$F:$F,Trésorerie!$B70) -> -81.14 | U70: =-SUMIFS('2023-04'!$M:$M,'2023-04'!$E:$E,Trésorerie!U$4,'2023-04'!$F:$F,Trésorerie!$B70)+SUMIFS('2023-04'!$N:$N,'2023-04'!$E:$E,Trésorerie!U$4,'2023-04'!$F:$F,Trésorerie!$B70) -> 0 | V70: =-SUMIFS('2023-05'!$M:$M,'2023-05'!$E:$E,Trésorerie!V$4,'2023-05'!$F:$F,Trésorerie!$B70)+SUMIFS('2023-05'!$N:$N,'2023-05'!$E:$E,Trésorerie!V$4,'2023-05'!$F:$F,Trésorerie!$B70) -> -78.92 | W70: =-SUMIFS('2023-06'!$M:$M,'2023-06'!$E:$E,Trésorerie!W$4,'2023-06'!$F:$F,Trésorerie!$B70)+SUMIFS('2023-06'!$N:$N,'2023-06'!$E:$E,Trésorerie!W$4,'2023-06'!$F:$F,Trésorerie!$B70) -> 66129.73 | X70: =-SUMIFS('2023-07'!$M:$M,'2023-07'!$E:$E,Trésorerie!X$4,'2023-07'!$F:$F,Trésorerie!$B70)+SUMIFS('2023-07'!$N:$N,'2023-07'!$E:$E,Trésorerie!X$4,'2023-07'!$F:$F,Trésorerie!$B70) -> 2054.55 | Y70: =-SUMIFS('2023-08'!$M:$M,'2023-08'!$E:$E,Trésorerie!Y$4,'2023-08'!$F:$F,Trésorerie!$B70)+SUMIFS('2023-08'!$N:$N,'2023-08'!$E:$E,Trésorerie!Y$4,'2023-08'!$F:$F,Trésorerie!$B70) -> 3000 | Z70: =-SUMIFS('2023-09'!$M:$M,'2023-09'!$E:$E,Trésorerie!Z$4,'2023-09'!$F:$F,Trésorerie!$B70)+SUMIFS('2023-09'!$N:$N,'2023-09'!$E:$E,Trésorerie!Z$4,'2023-09'!$F:$F,Trésorerie!$B70) -> 3503.34 | AA70: =-SUMIFS('2023-10'!$M:$M,'2023-10'!$E:$E,Trésorerie!AA$4,'2023-10'!$F:$F,Trésorerie!$B70)+SUMIFS('2023-10'!$N:$N,'2023-10'!$E:$E,Trésorerie!AA$4,'2023-10'!$F:$F,Trésorerie!$B70) -> 2400 | AB70: 0 | AC70: 0
D71: SOUS TOTAL | E71: =SUM(E44:E70) -> -129303.64 | F71: =SUM(F44:F70) -> -149272.39 | G71: =SUM(G44:G70) -> -158940.98 | H71: =SUM(H44:H70) -> -129122.14 | I71: =SUM(I44:I70) -> -147529.44 | J71: =SUM(J44:J70) -> -161289.79 | K71: =SUM(K44:K70) -> -184106.16 | L71: =SUM(L44:L70) -> -182879.66 | ... P71: =SUM(P44:P70) -> -153536.18 | R71: =SUM(R44:R70) -> -188627.64 | S71: =SUM(S44:S70) -> -125286.77 | T71: =SUM(T44:T70) -> -145403.82 | U71: =SUM(U44:U70) -> -123754.96 | V71: =SUM(V44:V70) -> -65197.39 | W71: =SUM(W44:W70) -> -81276.43 | X71: =SUM(X44:X70) -> -147630.96 | Y71: =SUM(Y44:Y70) -> -155711.68 | ... AC71: =SUM(AC44:AC70) -> -153536.18
D72: TOTAL | E72: =E71+E43 -> -108973.94 | F72: =F71+F43 -> 48376.56 | G72: =G71+G43 -> 48455.34 | H72: =H71+H43 -> -70144.73 | I72: =I71+I43 -> 44199.95 | J72: =J71+J43 -> 24908.8 | K72: =K71+K43 -> -75969.42 | L72: =L71+L43 -> -116348.68 | ... P72: =P71+P43 -> -127773.72 | R72: =R71+R43 -> -164300.14 | S72: =S71+S43 -> -92473.3 | T72: =T71+T43 -> 284009.59 | U72: =U71+U43 -> 17061.62 | V72: =V71+V43 -> -27869.36 | W72: =W71+W43 -> 50195.62 | X72: =X71+X43 -> 47167.62 | Y72: =Y71+Y43 -> -132284.45 | ... AC72: =AC71+AC43 -> -134819.74

Sheet 2022
A1: JournalCode | B1: JournalLib | C1: EcritureNum | D1: EcritureDate | F1: CompteNum | G1: CompteLib | H1: CompAuxNum | I1: CompAuxLib | J1: PieceRef | K1: PieceDate | L1: EcritureLib | M1: Debit | N1: Credit | O1: EcritureLet | P1: DateLet | Q1: ValidDate | R1: Montantdevise | S1: Idevise
A2: BFC | B2: BFCC CPTE COURANT | C2: 3 | D2: 20220103 | E2: =VALUE(MID(D2,5,2)) -> 1 | F2: 468725 | G2: ETAT CNASEA | J2: BFC2201/00207 | K2: 20220103 | L2: VIRT AIDE APPRENTIS | M2: 0 | N2: 1333.32 | O2: LM | P2: 20220308 | Q2: 20220103
A3: BFC | B3: BFCC CPTE COURANT | C3: 3 | D3: 20220103 | E3: =VALUE(MID(D3,5,2)) -> 1 | F3: 512000 | G3: BFCC COMPTE COURANT | J3: BFC2201/00207 | K3: 20220103 | L3: VIRT AIDE APPRENTIS | M3: 1333.32 | N3: 0 | Q3: 20220103
A4: BFC | B4: BFCC CPTE COURANT | C4: 3 | D4: 20220103 | E4: =VALUE(MID(D4,5,2)) -> 1 | F4: 627000 | G4: SERVICES BANCAIRES | J4: BFC2201/00208 | K4: 20220103 | L4: FRAIS BANCAIRE | M4: 7.5 | N4: 0 | Q4: 20220103
A5: BFC | B5: BFCC CPTE COURANT | C5: 3 | D5: 20220103 | E5: =VALUE(MID(D5,5,2)) -> 1 | F5: 512000 | G5: BFCC COMPTE COURANT | J5: BFC2201/00208 | K5: 20220103 | L5: FRAIS BANCAIRE | M5: 0 | N5: 7.5 | Q5: 20220103
A6: BFC | B6: BFCC CPTE COURANT | C6: 3 | D6: 20220103 | E6: =VALUE(MID(D6,5,2)) -> 1 | F6: 468200 | G6: INDEMN.JOURNAL. A RECEVOIR | J6: BFC2201/00209 | K6: 20220103 | L6: INDEMN.JOURNAL. A RECEVOIR | M6: 0 | N6: 95.96 | O6: LM | P6: 20220323 | Q6: 20220103
A7: BFC | B7: BFCC CPTE COURANT | C7: 3 | D7: 20220103 | E7: =VALUE(MID(D7,5,2)) -> 1 | F7: 512000 | G7: BFCC COMPTE COURANT | J7: BFC2201/00209 | K7: 20220103 | L7: INDEMN.JOURNAL. A RECEVOIR | M7: 95.96 | N7: 0 | Q7: 20220103
A8: BFC | B8: BFCC CPTE COURANT | C8: 3 | D8: 20220103 | E8: =VALUE(MID(D8,5,2)) -> 1 | F8: 627000 | G8: SERVICES BANCAIRES | J8: BFC2201/00210 | K8: 20220103 | L8: FRAIS BANCAIRE | M8: 50.62 | N8: 0 | Q8: 20220103
A9: BFC | B9: BFCC CPTE COURANT | C9: 3 | D9: 20220103 | E9: =VALUE(MID(D9,5,2)) -> 1 | F9: 512000 | G9: BFCC COMPTE COURANT | J9: BFC2201/00210 | K9: 20220103 | L9: FRAIS BANCAIRE | M9: 0 | N9: 50.62 | Q9: 20220103
A10: BFC | B10: BFCC CPTE COURANT | C10: 3 | D10: 20220104 | E10: =VALUE(MID(D10,5,2)) -> 1 | F10: 627000 | G10: SERVICES BANCAIRES | J10: BFC2201/00211 | K10: 20220104 | L10: FRAIS BANCAIRE | M10: 49 | N10: 0 | Q10: 20220104
A11: BFC | B11: BFCC CPTE COURANT | C11: 3 | D11: 20220104 | E11: =VALUE(MID(D11,5,2)) -> 1 | F11: 512000 | G11: BFCC COMPTE COURANT | J11: BFC2201/00211 | K11: 20220104 | L11: FRAIS BANCAIRE | M11: 0 | N11: 49 | Q11: 20220104
A12: BFC | B12: BFCC CPTE COURANT | C12: 3 | D12: 20220104 | E12: =VALUE(MID(D12,5,2)) -> 1 | F12: 627000 | G12: SERVICES BANCAIRES | J12: BFC2201/00212 | K12: 20220104 | L12: FRAIS BANCAIRE | M12: 20.15 | N12: 0 | Q12: 20220104
A13: BFC | B13: BFCC CPTE COURANT | C13: 3 | D13: 20220104 | E13: =VALUE(MID(D13,5,2)) -> 1 | F13: 512000 | G13: BFCC COMPTE COURANT | J13: BFC2201/00212 | K13: 20220104 | L13: FRAIS BANCAIRE | M13: 0 | N13: 20.15 | Q13: 20220104
A14: BFC | B14: BFCC CPTE COURANT | C14: 3 | D14: 20220105 | E14: =VALUE(MID(D14,5,2)) -> 1 | F14: 401000 | G14: COLLECTIF FOURNISSEURS | H14: DIAC | I14: DIAC | J14: BFC2201/00213 | K14: 20220105 | L14: PRLV DIAC | M14: 475.4 | N14: 0 | O14: LM | P14: 20220321 | Q14: 20220105
A15: BFC | B15: BFCC CPTE COURANT | C15: 3 | D15: 20220105 | E15: =VALUE(MID(D15,5,2)) -> 1 | F15: 512000 | G15: BFCC COMPTE COURANT | J15: BFC2201/00213 | K15: 20220105 | L15: PRLV DIAC | M15: 0 | N15: 475.4 | Q15: 20220105
A16: BFC | B16: BFCC CPTE COURANT | C16: 3 | D16: 20220107 | E16: =VALUE(MID(D16,5,2)) -> 1 | F16: 401000 | G16: COLLECTIF FOURNISSEURS | H16: ALTER | I16: ALTER INFO | J16: BFC2201/00006 | K16: 20220107 | L16: Virement ・un tiers | M16: 220.84 | N16: 0 | O16: LA | P16: 20220107 | Q16: 20220107
A17: BFC | B17: BFCC CPTE COURANT | C17: 3 | D17: 20220107 | E17: =VALUE(MID(D17,5,2)) -> 1 | F17: 401000 | G17: COLLECTIF FOURNISSEURS | H17: MELLIER | I17: MELLIER | J17: BFC2201/00006 | K17: 20220107 | L17: Virement ・un tiers | M17: 1876 | N17: 0 | O17: LA | P17: 20220107 | Q17: 20220107
A18: BFC | B18: BFCC CPTE COURANT | C18: 3 | D18: 20220107 | E18: =VALUE(MID(D18,5,2)) -> 1 | F18: 401000 | G18: COLLECTIF FOURNISSEURS | H18: BRUNEAU | I18: BRUNEAU | J18: BFC2201/00006 | K18: 20220107 | L18: Virement ・un tiers | M18: 268.36 | N18: 0 | O18: LA | P18: 20220107 | Q18: 20220107
A19: BFC | B19: BFCC CPTE COURANT | C19: 3 | D19: 20220107 | E19: =VALUE(MID(D19,5,2)) -> 1 | F19: 467100 | G19: AUXILIAIRE SALARIES | H19: SBOISSY | I19: BOISSY OLIVIER | J19: BFC2201/00006 | K19: 20220107 | L19: Virement ・un tiers | M19: 193.98 | N19: 0 | O19: LA | P19: 20220107 | Q19: 20220107
A20: BFC | B20: BFCC CPTE COURANT | C20: 3 | D20: 20220107 | E20: =VALUE(MID(D20,5,2)) -> 1 | F20: 467100 | G20: AUXILIAIRE SALARIES | H20: SCOUX | I20: COUX STEPHANE | J20: BFC2201/00006 | K20: 20220107 | L20: Virement ・un tiers | M20: 34 | N20: 0 | O20: LA | P20: 20220107 | Q20: 20220107
A21: BFC | B21: BFCC CPTE COURANT | C21: 3 | D21: 20220107 | E21: =VALUE(MID(D21,5,2)) -> 1 | F21: 467100 | G21: AUXILIAIRE SALARIES | H21: SKANNIAH | I21: KANNIAH JOSE | J21: BFC2201/00006 | K21: 20220107 | L21: Virement ・un tiers | M21: 126.75 | N21: 0 | O21: LA | P21: 20220107 | Q21: 20220107
A22: BFC | B22: BFCC CPTE COURANT | C22: 3 | D22: 20220107 | E22: =VALUE(MID(D22,5,2)) -> 1 | F22: 467100 | G22: AUXILIAIRE SALARIES | H22: SMERIMECHE | I22: DJAMILA MERIMECHE | J22: BFC2201/00006 | K22: 20220107 | L22: Virement ・un tiers | M22: 31 | N22: 0 | O22: LA | P22: 20220107 | Q22: 20220107
A23: BFC | B23: BFCC CPTE COURANT | C23: 3 | D23: 20220107 | E23: =VALUE(MID(D23,5,2)) -> 1 | F23: 401000 | G23: COLLECTIF FOURNISSEURS | H23: FEDERATION | I23: FEDERATION DES CENTRES SOCIAUX | J23: BFC2201/00006 | K23: 20220107 | L23: Virement ・un tiers | M23: 460 | N23: 0 | O23: LA | P23: 20220107 | Q23: 20220107
A24: BFC | B24: BFCC CPTE COURANT | C24: 3 | D24: 20220107 | E24: =VALUE(MID(D24,5,2)) -> 1 | F24: 401000 | G24: COLLECTIF FOURNISSEURS | H24: OLYMPIQUE | I24: OLYMPIQUE LYONNAIS | J24: BFC2201/00006 | K24: 20220107 | L24: Virement ・un tiers | M24: 496 | N24: 0 | O24: LA | P24: 20220107 | Q24: 20220107
A25: BFC | B25: BFCC CPTE COURANT | C25: 3 | D25: 20220107 | E25: =VALUE(MID(D25,5,2)) -> 1 | F25: 512000 | G25: BFCC COMPTE COURANT | J25: BFC2201/00006 | K25: 20220107 | L25: Virement ・un tiers | M25: 0 | N25: 3706.93 | Q25: 20220107
A26: BFC | B26: BFCC CPTE COURANT | C26: 3 | D26: 20220107 | E26: =VALUE(MID(D26,5,2)) -> 1 | F26: 421000 | G26: REMUNERATIONS DUES | J26: BFC2201/00009 | K26: 20220107 | L26: SALAIRE - SEBAA DOUNIA | M26: 204.61 | N26: 0 | O26: LM | P26: 20220212 | Q26: 20220107
A27: BFC | B27: BFCC CPTE COURANT | C27: 3 | D27: 20220107 | E27: =VALUE(MID(D27,5,2)) -> 1 | F27: 421000 | G27: REMUNERATIONS DUES | J27: BFC2201/00009 | K27: 20220107 | L27: SALAIRE - SEBAA DOUNIA (Prime Inflation) | M27: 100 | N27: 0 | O27: LM | P27: 20220212 | Q27: 20220107
A28: BFC | B28: BFCC CPTE COURANT | C28: 3 | D28: 20220107 | E28: =VALUE(MID(D28,5,2)) -> 1 | F28: 467100 | G28: AUXILIAIRE SALARIES | H28: SCOUX | I28: COUX STEPHANE | J28: BFC2201/00009 | K28: 20220107 | L28: Virement direct ・des tiers | M28: 771.76 | N28: 0 | O28: LM | P28: 20220118 | Q28: 20220107
A29: BFC | B29: BFCC CPTE COURANT | C29: 3 | D29: 20220107 | E29: =VALUE(MID(D29,5,2)) -> 1 | F29: 512000 | G29: BFCC COMPTE COURANT | J29: BFC2201/00009 | K29: 20220107 | L29: Virement direct ・des tiers | M29: 0 | N29: 1076.37 | Q29: 20220107
A30: BFC | B30: BFCC CPTE COURANT | C30: 3 | D30: 20220110 | E30: =VALUE(MID(D30,5,2)) -> 1 | F30: 468200 | G30: INDEMN.JOURNAL. A RECEVOIR | J30: BFC2201/00214 | K30: 20220110 | L30: INDEMN.JOURNAL. A RECEVOIR | M30: 0 | N30: 577.08 | O30: LM | P30: 20220323 | Q30: 20220110
A31: BFC | B31: BFCC CPTE COURANT | C31: 3 | D31: 20220110 | E31: =VALUE(MID(D31,5,2)) -> 1 | F31: 512000 | G31: BFCC COMPTE COURANT | J31: BFC2201/00214 | K31: 20220110 | L31: INDEMN.JOURNAL. A RECEVOIR | M31: 577.08 | N31: 0 | Q31: 20220110
A32: BFC | B32: BFCC CPTE COURANT | C32: 3 | D32: 20220112 | E32: =VALUE(MID(D32,5,2)) -> 1 | F32: 437000 | G32: MUTUELLE | J32: BFC2201/00215 | K32: 20220112 | L32: PRLV AESIO MUTUELLE | M32: 1535.4 | N32: 0 | Q32: 20220112
A33: BFC | B33: BFCC CPTE COURANT | C33: 3 | D33: 20220112 | E33: =VALUE(MID(D33,5,2)) -> 1 | F33: 512000 | G33: BFCC COMPTE COURANT | J33: BFC2201/00215 | K33: 20220112 | L33: PRLV AESIO MUTUELLE | M33: 0 | N33: 1535.4 | Q33: 20220112
A34: BFC | B34: BFCC CPTE COURANT | C34: 3 | D34: 20220112 | E34: =VALUE(MID(D34,5,2)) -> 1 | F34: 468200 | G34: INDEMN.JOURNAL. A RECEVOIR | J34: BFC2201/00216 | K34: 20220112 | L34: INDEMN.JOURNAL. A RECEVOIR | M34: 0 | N34: 267.2 | O34: LM | P34: 20220323 | Q34: 20220112
A35: BFC | B35: BFCC CPTE COURANT | C35: 3 | D35: 20220112 | E35: =VALUE(MID(D35,5,2)) -> 1 | F35: 512000 | G35: BFCC COMPTE COURANT | J35: BFC2201/00216 | K35: 20220112 | L35: INDEMN.JOURNAL. A RECEVOIR | M35: 267.2 | N35: 0 | Q35: 20220112
A36: BFC | B36: BFCC CPTE COURANT | C36: 3 | D36: 20220112 | E36: =VALUE(MID(D36,5,2)) -> 1 | F36: 627000 | G36: SERVICES BANCAIRES | J36: BFC2201/00217 | K36: 20220112 | L36: FRAIS OPPOSITION PRLV FRAUDULEUX | M36: 5 | N36: 0 | Q36: 20220112
A37: BFC | B37: BFCC CPTE COURANT | C37: 3 | D37: 20220112 | E37: =VALUE(MID(D37,5,2)) -> 1 | F37: 512000 | G37: BFCC COMPTE COURANT | J37: BFC2201/00217 | K37: 20220112 | L37: FRAIS OPPOSITION PRLV FRAUDULEUX | M37: 0 | N37: 5 | Q37: 20220112
A38: BFC | B38: BFCC CPTE COURANT | C38: 3 | D38: 20220114 | E38: =VALUE(MID(D38,5,2)) -> 1 | F38: 437100 | G38: CONTRIBUTION CNRACL | J38: BAN2201/00019 | K38: 20220114 | L38: Virement direct ・des tiers | M38: 736.8 | N38: 0 | O38: LM | P38: 20220118 | Q38: 20220114
A39: BFC | B39: BFCC CPTE COURANT | C39: 3 | D39: 20220114 | E39: =VALUE(MID(D39,5,2)) -> 1 | F39: 512000 | G39: BFCC COMPTE COURANT | J39: BAN2201/00019 | K39: 20220114 | L39: Virement direct ・des tiers | M39: 0 | N39: 736.8 | Q39: 20220114
A40: BFC | B40: BFCC CPTE COURANT | C40: 3 | D40: 20220114 | E40: =VALUE(MID(D40,5,2)) -> 1 | F40: 401000 | G40: COLLECTIF FOURNISSEURS | H40: FDIVERS | I40: DIVERS | J40: BFC2201/00218 | K40: 20220114 | L40: REMBT PRLV FRAUDULEUX 29/12 MCAFEE | M40: 0 | N40: 89.95 | O40: LM | P40: 20220307 | Q40: 20220114
A41: BFC | B41: BFCC CPTE COURANT | C41: 3 | D41: 20220114 | E41: =VALUE(MID(D41,5,2)) -> 1 | F41: 512000 | G41: BFCC COMPTE COURANT | J41: BFC2201/00218 | K41: 20220114 | L41: REMBT PRLV FRAUDULEUX 29/12 MCAFEE | M41: 89.95 | N41: 0 | Q41: 20220114
A42: BFC | B42: BFCC CPTE COURANT | C42: 3 | D42: 20220117 | E42: =VALUE(MID(D42,5,2)) -> 1 | F42: 411000 | G42: COLLECTIF CLIENTS DIVERS | H42: 6CARRON | I42: REGIE CARRON | J42: BFC2201/00228 | K42: 20220117 | L42: VIRT LOCATION REGIE CARRON/CREMIEU | M42: 0 | N42: 120 | O42: LA | P42: 20230218 | Q42: 20220117
A43: BFC | B43: BFCC CPTE COURANT | C43: 3 | D43: 20220117 | E43: =VALUE(MID(D43,5,2)) -> 1 | F43: 512000 | G43: BFCC COMPTE COURANT | J43: BFC2201/00228 | K43: 20220117 | L43: VIRT LOCATION REGIE CARRON/CREMIEU | M43: 120 | N43: 0 | Q43: 20220117
A44: BFC | B44: BFCC CPTE COURANT | C44: 3 | D44: 20220117 | E44: =VALUE(MID(D44,5,2)) -> 1 | F44: 411000 | G44: COLLECTIF CLIENTS DIVERS | H44: 6CARRON | I44: REGIE CARRON | J44: BFC2201/00229 | K44: 20220117 | L44: VIRT CAUTION REGIE CARRON/CREMIEU | M44: 0 | N44: 80 | Q44: 20220117
A45: BFC | B45: BFCC CPTE COURANT | C45: 3 | D45: 20220117 | E45: =VALUE(MID(D45,5,2)) -> 1 | F45: 512000 | G45: BFCC COMPTE COURANT | J45: BFC2201/00229 | K45: 20220117 | L45: VIRT CAUTION REGIE CARRON/CREMIEU | M45: 80 | N45: 0 | Q45: 20220117
A46: BFC | B46: BFCC CPTE COURANT | C46: 3 | D46: 20220117 | E46: =VALUE(MID(D46,5,2)) -> 1 | F46: 468200 | G46: INDEMN.JOURNAL. A RECEVOIR | J46: BFC2201/00230 | K46: 20220117 | L46: INDEMN.JOURNAL. A RECEVOIR | M46: 0 | N46: 288.54 | O46: LM | P46: 20220323 | Q46: 20220117
A47: BFC | B47: BFCC CPTE COURANT | C47: 3 | D47: 20220117 | E47: =VALUE(MID(D47,5,2)) -> 1 | F47: 512000 | G47: BFCC COMPTE COURANT | J47: BFC2201/00230 | K47: 20220117 | L47: INDEMN.JOURNAL. A RECEVOIR | M47: 288.54 | N47: 0 | Q47: 20220117
A48: BFC | B48: BFCC CPTE COURANT | C48: 3 | D48: 20220118 | E48: =VALUE(MID(D48,5,2)) -> 1 | F48: 401000 | G48: COLLECTIF FOURNISSEURS | H48: AST | I48: MEDECINE DU TRAVAIL | J48: BFC2201/00024 | K48: 20220118 | L48: Virement ・un tiers | M48: 5896.8 | N48: 0 | O48: LM | P48: 20220204 | Q48: 20220118
A49: BFC | B49: BFCC CPTE COURANT | C49: 3 | D49: 20220118 | E49: =VALUE(MID(D49,5,2)) -> 1 | F49: 401000 | G49: COLLECTIF FOURNISSEURS | H49: COURRI | I49: COURRIERS RHODANIENS | J49: BFC2201/00024 | K49: 20220118 | L49: Virement ・un tiers | M49: 662 | N49: 0 | O49: LM | P49: 20220124 | Q49: 20220118
A50: BFC | B50: BFCC CPTE COURANT | C50: 3 | D50: 20220118 | E50: =VALUE(MID(D50,5,2)) -> 1 | F50: 401000 | G50: COLLECTIF FOURNISSEURS | H50: PHARMA | I50: PHARMACIE CYPRIAN | J50: BFC2201/00024 | K50: 20220118 | L50: Virement ・un tiers | M50: 62.42 | N50: 0 | O50: LM | P50: 20220125 | Q50: 20220118
A51: BFC | B51: BFCC CPTE COURANT | C51: 3 | D51: 20220118 | E51: =VALUE(MID(D51,5,2)) -> 1 | F51: 401000 | G51: COLLECTIF FOURNISSEURS | H51: PICHON | I51: PICHON PAPETERIES | J51: BFC2201/00024 | K51: 20220118 | L51: Virement ・un tiers | M51: 91.52 | N51: 0 | O51: LM | P51: 20220125 | Q51: 20220118
